Workbook

Sheet Start_Here
A1: Start here — what this workbook is, what changed, and what still needs your data
A2: CP-45 (row 46 of 'MBA_GEN_60_Bloomberg_Capstone_Projects'). Built from your 15-Oct-2026 Bloomberg screenshots, your draft plan, and the project brief.
A4: Colour legend
A5: Blue text | B5: Value typed from a Bloomberg screenshot, or an assumption you can change
A6: Black text | B6: Formula
A7: Green text | B7: Link to another sheet
A8: Yellow fill | B8: Key assumption or headline output
A10: Sheet map
A11: Summary | B11: Headline results and findings (live)
A12: Assumptions | B12: All judgement inputs + scenario switch (Base / Adverse / Severe)
A13: ROI_ULVR / ROI_NESN / ROI_WIL | B13: Year-by-year cost-benefit: status quo vs central database vs permissioned blockchain
A14: MC_Results | B14: Monte Carlo (20,000 draws × 4 regimes) — static from Python
A15: Sensitivity | B15: Tornado + coverage × substitution heat map — static from Python
A16: Risk_Index | B16: Composite risk index built on real indicators, three weight sets
A17: Supply_Chain | B17: SPLC panels, Wilmar supplier table, brand-owner supplier tables, HHI, coverage
A18: News_Events | B18: Hand-coded controversy log (12M window)
A19: ESG | B19: BESG scores and GHG scopes
A20: Fundamentals | B20: Income statement, balance sheet and cash-flow extracts + ratios
A21: Market_Data | B21: Snapshot and CPO futures stats
A22: Price_Analytics | B22: Aligned daily prices, returns, volatility, correlation, beta
A23: Next_Steps | B23: Data still to pull and how
A25: Review of the draft plan — what I changed and why
A26: Issue in the draft | B26: Why it matters | C26: Fix applied here | D26: Still for you to do
A27: The Python code is cut off mid-formula ('+ 0.20 *') and the simulation / ROI code it promises is not in the file. | B27: Nothing runs; RQ3/RQ4 have no engine. | C27: Rebuilt end-to-end: palm_oil_traceability_model.py (market stats, NPV model, Monte Carlo, tornado, grid) and this workbook; Excel and Python NPVs tie exactly. | D27: Run the script after changing any assumption; paste refreshed tables into MC_Results/Sensitivity.
A28: 50 synthetic suppliers with random ESG, news hits and RSPO flags. | B28: Random inputs cannot answer RQ1–RQ3; an examiner will ask for the Bloomberg evidence. | C28: Replaced with the real Bloomberg data you captured (fundamentals, ESG, SPLC suppliers, news, prices). | D28: Pull the full SPLC lists and 5Y history (Next_Steps).
A29: The risk index weights (0.35 / 0.25 / 0.20 …) are chosen by hand and then a model is 'validated' against it. | B29: Circular: the model can only rediscover the weights you typed. | C29: Weights are explicit, editable, tested under three weight sets; ranking-stability check added. | D29: Calibrate against an outcome (forward drawdown, controversy count after events) once you have more firms and 5Y data.
A30: The chain 'mill → Wilmar → Unilever/Nestlé' is presented as given. | B30: SPLC does not show it; your own news screen shows Nestlé's palm partners as Musim Mas and AAK. | C30: Flagged with evidence on Supply_Chain; opacity used as a finding. | D30: Search SPLC for Wilmar / IOI / Musim Mas / AAK / Cargill; add each brand owner's published mill list.
A31: Only 'with vs without blockchain' is compared. | B31: Most of the benefit comes from traceability itself; the blockchain's value is the increment over a central database. | C31: Three options modelled; incremental NPV and P(blockchain beats database) reported. | D31: Defend the effectiveness gap (Assumptions!C43 vs D43) with evidence — it decides the answer.
A32: Price series called 'KOA Comdty'. | B32: Your screens use KOZ6 Comdty (single Dec-26 contract, MYR). | C32: Documented on Market_Data; all stats use KOZ6. | D32: Use a continuous series (KO1 Comdty — confirm) and state the roll rule.
A33: No regulatory timeline in the model. | B33: EU Deforestation Regulation obligations for large/medium operators apply from 30-Dec-2026 (per the European Commission's trade site, as fetched 22-Oct-2026). | C33: Regulatory loss channel with fine rate, EU share, scenarios (Adverse/Severe = stricter enforcement). | D33: Confirm palm oil's scope, the penalty ceiling and any further delay in the final regulation text before quoting.
A34: Zero-knowledge proofs + Hyperledger Fabric/Corda in the architecture box. | B34: ZKPs add cost and complexity; the brief needs the economics, not a build. | C34: Not modelled; architecture cost is one capex/opex line. | D34: Keep ZKPs as an optional extension (selective disclosure of supplier prices); compare Fabric / Corda / permissioned EVM qualitatively.
A35: ESG score used as a predictor. | B35: Wilmar's BESG score rose while its emissions rose — scores follow disclosure. | C35: Scored alongside conduct-risk, distress, news and balance-sheet indicators. | D35: Add disclosure-quality and certification-coverage variables.
A36: Data comparability. | B36: Unilever FY24–25 restated for the ice-cream demerger; Unilever Scope 3 has series breaks; different news filters per firm; EUR/CHF/USD. | C36: Caveats on each sheet; FX is an explicit assumption; ratios not levels. | D36: Re-run all three firms with identical filters; replace illustrative FX with Bloomberg FX.

Sheet Summary
A1: CP-45 Blockchain Sustainable Palm Oil Traceability — Unilever · Nestlé · Wilmar
A2: Headline results (live links; scenario = Assumptions!B13). Model inputs marked ASSUMPTION are placeholders: read the numbers as decision logic, not forecasts.
A4: Active scenario | B4: =Assumptions!B13 -> Base
A6: Headline metric | B6: Unilever | C6: Nestlé | D6: Wilmar | E6: Where it comes from
A7: Cost-benefit (USD m, PV over 7 years vs status quo)
A8: NPV benefit — central database | B8: =ROI_ULVR!E71 -> 20.177473 | C8: =ROI_NESN!E71 -> 44.412856 | D8: =ROI_WIL!E71 -> 89.968344 | E8: ROI_ sheets
A9: NPV benefit — permissioned blockchain | B9: =ROI_ULVR!E72 -> 15.992594 | C9: =ROI_NESN!E72 -> 46.67889 | D9: =ROI_WIL!E72 -> 86.363854 | E9: ROI_ sheets
A10: Blockchain minus database (NPV) | B10: =ROI_ULVR!E81 -> -4.1848793 | C10: =ROI_NESN!E81 -> 2.2660343 | D10: =ROI_WIL!E81 -> -3.6044897 | E10: Negative = a plain database is the better buy at these inputs
A11: Benefit / programme cost — database | B11: =ROI_ULVR!G71 -> 1.8130373 | C11: =ROI_NESN!G71 -> 3.1134386 | D11: =ROI_WIL!G71 -> 2.1099255
A12: Benefit / programme cost — blockchain | B12: =ROI_ULVR!G72 -> 1.4077029 | C12: =ROI_NESN!G72 -> 2.3560299 | D12: =ROI_WIL!G72 -> 1.7289245
A13: Discounted payback (yrs) — database | B13: =ROI_ULVR!I71 -> 3 | C13: =ROI_NESN!I71 -> 2 | D13: =ROI_WIL!I71 -> 3
A14: Discounted payback (yrs) — blockchain | B14: =ROI_ULVR!I72 -> 5 | C14: =ROI_NESN!I72 -> 3 | D14: =ROI_WIL!I72 -> 4
A15: Break-even regulatory-risk multiplier — blockchain | B15: =ROI_ULVR!H72 -> 0.34310807 | C15: =ROI_NESN!H72 -> 0.0089094669 | D15: =ROI_WIL!H72 -> 0 | E15: Factor on p_reg at which NPV = 0 (0 = pays even with no regulatory risk)
A17: Monte Carlo, mixed enforcement regimes (static, from Python)
A18: P(NPV > 0) — database | B18: =MC_Results!H11 -> 0.78925 | C18: =MC_Results!H19 -> 0.9332 | D18: =MC_Results!H27 -> 0.88505
A19: P(NPV > 0) — blockchain | B19: =MC_Results!H12 -> 0.6236 | C19: =MC_Results!H20 -> 0.8275 | D19: =MC_Results!H28 -> 0.7567
A20: P(blockchain beats database) | B20: =MC_Results!I12 -> 0.35255 | C20: =MC_Results!I20 -> 0.42045 | D20: =MC_Results!I28 -> 0.38345
A22: Risk & visibility evidence (live)
A23: Composite traceability risk index (0–100, base weights) | B23: =Risk_Index!H18 -> 53.004404 | C23: =Risk_Index!I18 -> 39.940302 | D23: =Risk_Index!J18 -> 63.512421 | E23: Risk_Index (relative ranking of 3 firms only)
A24: Palm/plantation nodes visible in SPLC top suppliers | B24: =Supply_Chain!B148 -> 0 | C24: =Supply_Chain!B117 -> 0 | D24: =Supply_Chain!B84 -> 10 | E24: Visible = shown on the captured screens (Wilmar: of 24 visible suppliers)
A25: Visible supplier cost as % of COGS (lower bound) | B25: =Supply_Chain!B147 -> 0.1657 | C25: =Supply_Chain!B116 -> 0.1287 | D25: =Supply_Chain!B82 -> 0.0266
A26: Adverse news severity, last 12M (hand-coded) | B26: =News_Events!C7 -> 12 | C26: =News_Events!C8 -> 1 | D26: =News_Events!C9 -> 19 | E26: Different screen filters per firm — see News_Events warning
A28: What the evidence says (default inputs, base scenario)
A29: 1. Traceability pays in most simulated worlds (central database positive in 79–93% of mixed-regime draws); the technology choice is the close call. A central database + satellite/audit stack captures most of the benefit. At base inputs the blockchain only matches the database if its assurance value reaches ~0.88 (Nestlé), ~0.92 (Wilmar) or ~0.96 (Unilever) versus 0.80 for the database; under Adverse enforcement the parity points fall to ~0.82–0.87. In the mixed Monte Carlo the blockchain wins in roughly 35–42% of worlds. That is the honest answer to RQ4 — and a stronger capstone than 'blockchain always helps'.
A30: 2. Bloomberg SPLC cannot see the palm chain. None of Unilever's or Nestlé's top-24 suppliers is a palm trader or plantation, Wilmar is not in either list, and the plantation nodes visible for Wilmar are ~0.4% of its cost base. The draft's 'mill → Wilmar → Unilever/Nestlé' chain is an assumption, not an SPLC finding (your Nestlé news screen shows Musim Mas and AAK as Nestlé's palm partners). This opacity IS the problem the blockchain would solve — use it as your motivating evidence, and add company mill lists as a second source.
A31: 3. Wilmar ranks highest-risk on the composite index, driven by interest cover (~2.1x vs 8–9x), supplier conduct-risk flags (37% of listed suppliers) and the news record: the May-2026 Indonesian export under-invoicing probe, a corruption conviction of a unit executive, and the Russian asset-seizure report. Note these are governance/legal events, not deforestation events — the 'traceability' narrative must be separated from the 'governance' one.
A32: 4. Wilmar's BESG score more than doubled (2.71 → 6.15) while reported Scope 1 emissions rose 2.6x: scores track disclosure, not footprint. Do not use a BESG score alone as a traceability-risk predictor (RQ1).
A33: 5. KOZ6 palm oil sits ~9% below its 8-Sep-26 high (MYR 5,115 → 4,666) after a +18% rise over the range. With only ~8 weeks of aligned prices, correlations with the three equities are statistically zero (|ρ| < 0.35 band) — pull ≥5 years of data before claiming any price–equity link (RQ2).

Sheet Assumptions
A1: Assumptions — every judgement input for the ROI / NPV model lives here
A2: Blue = input you can change (yellow = most influential). Green = pulled from Fundamentals. These are PLANNING-GRADE PLACEHOLDERS, not Bloomberg facts: calibrate each one and cite the source in the Basis column.
A4: A. Global inputs
A5: Discount rate | B5: 0.08 | F5: Use each firm's WACC (Bloomberg WACC <GO>); 8% is a generic consumer-staples/agri placeholder.
A6: Nominal growth of revenue, COGS and opex | B6: 0.02 | F6: Placeholder; replace with consensus growth (see Fundamentals 2026E/27E).
A7: Realised fine, % of EU turnover when non-compliant | B7: 0.02 | F7: EUDR maximum is at least 4% of EU turnover; base case assumes half of that is realised. Verify against the final regulation text.
A8: Price premium on re-sourced compliant volume | B8: 0.06 | F8: Placeholder; calibrate to RSPO / segregated-supply premiums.
A9: Share of non-traceable EU-bound volume excluded / re-sourced | B9: 0.3 | F9: Placeholder; supplier-exclusion rate under a compliance-only sourcing policy.
A10: Baseline traceable share today (c0) | B10: 0.3 | F10: Placeholder; use each firm's published certified / traceable-to-mill percentage.
A11: FX: EUR→USD | B11: 1.15 | F11: ILLUSTRATIVE — replace with Bloomberg FX on the data date (EURUSD Curncy).
A12: FX: CHF→USD | B12: 1.25 | F12: ILLUSTRATIVE — replace with Bloomberg FX on the data date (USDCHF Curncy, inverted).
A13: Active scenario (pick: Base / Adverse / Severe) | B13: Base | F13: Drives the three ROI sheets and the live numbers on Summary. Monte Carlo tables are static (run in Python).
A15: Scenario multipliers | B15: Regulatory prob. × | C15: Controversy prob. × | D15: Substitution premium × | E15: CPO price level ×
A16: Base | B16: 1 | C16: 1 | D16: 1 | E16: 1 | F16: Severe = strict EUDR enforcement + palm price level +30% (supply squeeze).
A17: Adverse | B17: 2 | C17: 1.5 | D17: 1.5 | E17: 1
A18: Severe | B18: 4 | C18: 2.5 | D18: 2.5 | E18: 1.3
A19: Active multipliers | B19: =INDEX(B16:B18,MATCH($B$13,$A$16:$A$18,0)) -> 1 | C19: =INDEX(C16:C18,MATCH($B$13,$A$16:$A$18,0)) -> 1 | D19: =INDEX(D16:D18,MATCH($B$13,$A$16:$A$18,0)) -> 1 | E19: =INDEX(E16:E18,MATCH($B$13,$A$16:$A$18,0)) -> 1
A21: B. Firm profiles (USD m unless stated)
A22: Parameter | B22: Unilever | C22: Nestlé | D22: Wilmar | F22: Basis
A23: Revenue FY2025 (reporting ccy m) | B23: =Fundamentals!I6 -> 50503 | C23: =Fundamentals!I35 -> 89885 | D23: =Fundamentals!I64 -> 70415.7 | F23: Bloomberg FA (EUR / CHF / USD)
A24: COGS FY2025 (reporting ccy m) | B24: =Fundamentals!I7 -> 26794 | C24: =Fundamentals!I36 -> 48694 | D24: =Fundamentals!I65 -> 64619.9 | F24: Bloomberg FA
A25: FX to USD | B25: =$B$11 -> 1.15 | C25: =$B$12 -> 1.25 | D25: 1 | F25: Wilmar reports in USD
A26: Revenue FY2025 (USD m) | B26: =B23*B25 -> 58078.45 | C26: =C23*C25 -> 112356.25 | D26: =D23*D25 -> 70415.7
A27: COGS FY2025 (USD m) | B27: =B24*B25 -> 30813.1 | C27: =C24*C25 -> 60867.5 | D27: =D24*D25 -> 64619.9
A28: a Palm-linked share of revenue | B28: 0.25 | C28: 0.15 | D28: 0.4 | F28: ASSUMPTION — share of sales in products with palm-derived inputs (home/personal care, foods; for Wilmar: palm & laurics, consumer products).
A29: ps Palm-derived spend as % of COGS | B29: 0.03 | C29: 0.015 | D29: 0.3 | F29: ASSUMPTION — calibrate from sustainability reports (tonnes palm × price) divided by COGS.
A30: eu Revenue share in EU-regulated markets | B30: 0.25 | C30: 0.25 | D30: 0.08 | F30: ASSUMPTION — Wilmar low (China 47% of revenue, see Supply_Chain); brand owners via EU retail.
A31: p_reg Annual probability of a regulatory / market-access event | B31: 0.03 | C31: 0.03 | D31: 0.05 | F31: ASSUMPTION — to calibrate from enforcement history; the Wilmar Indonesia probe (May-26) shows the order of magnitude is not zero.
A32: p_ctrv Annual probability of a controversy / boycott event | B32: 0.1 | C32: 0.1 | D32: 0.15 | F32: ASSUMPTION — calibrate from the News_Events frequency (extend to ≥5Y).
A33: rev_loss Revenue lost on palm-linked sales in a controversy | B33: 0.005 | C33: 0.005 | D33: 0.01 | F33: ASSUMPTION — event-study the 2026 Wilmar probe (needs daily prices, see Next_Steps).
A34: Central database: capex (USD m) | B34: 8 | C34: 7 | D34: 25 | F34: ASSUMPTION — planning-grade; replace with vendor quotes / pilot budgets.
A35: Central database: annual opex (USD m) | B35: 3 | C35: 2.5 | D35: 10 | F35: ASSUMPTION
A36: Permissioned blockchain: capex (USD m) | B36: 14 | C36: 12 | D36: 40 | F36: ASSUMPTION — consortium build, node onboarding, integration.
A37: Permissioned blockchain: annual opex (USD m) | B37: 4.5 | C37: 4 | D37: 14 | F37: ASSUMPTION
A39: C. Option design
A40: Parameter | B40: Status quo | C40: Central database | D40: Permissioned blockchain | F40: Basis
A41: cmax Steady-state traceable share | B41: =B10 -> 0.3 | C41: 0.8 | D41: 0.9 | F41: ASSUMPTION — blockchain coverage slightly higher (shared ledger across traders/mills) but slower to coordinate.
A42: Ramp-up years to reach cmax | B42: 1 | C42: 3 | D42: 4
A43: eff Assurance value of coverage (0–1) | B43: 0.6 | C43: 0.8 | D43: 0.9 | F43: ASSUMPTION — KEY: how much extra credibility an immutable multi-party ledger earns with regulators/retailers vs a central database. This single gap decides RQ4.
A45: Mechanics (same in Python): coverage c(t)=c0+(cmax−c0)·min(1,t/ramp); mitigation m=c·eff. Expected annual loss = [p_reg·fine·eu·Revenue + p_ctrv·rev_loss·a·Revenue]·(1−m) + PalmSpend·eu·(1−c)·q·π. Benefit = PV(total cost, status quo) − PV(total cost, option). Year 0 = build (capex only); years 1–7 = operation.

Sheet ROI_ULVR
A1: Unilever — traceability programme: status quo vs central database vs permissioned blockchain (USD m)
A2: Pure calculation sheet: all inputs are green links to 'Assumptions'. Change the scenario on Assumptions!B13. Year 0 = build year.
A4: Revenue, USD m (FY2025) | B4: =Assumptions!B26 -> 58078.45 | D4: Active scenario: | E4: =Assumptions!B13 -> Base
A5: COGS, USD m (FY2025) | B5: =Assumptions!B27 -> 30813.1
A6: a palm-linked revenue share | B6: =Assumptions!B28 -> 0.25
A7: ps palm spend / COGS | B7: =Assumptions!B29 -> 0.03
A8: eu EU-regulated revenue share | B8: =Assumptions!B30 -> 0.25
A9: p_reg (scenario-adjusted) | B9: =Assumptions!B31*Assumptions!$B$19 -> 0.03
A10: p_ctrv (scenario-adjusted) | B10: =Assumptions!B32*Assumptions!$C$19 -> 0.1
A11: rev_loss | B11: =Assumptions!B33 -> 0.005
A12: Realised fine rate | B12: =Assumptions!$B$7 -> 0.02
A13: Substitution premium π (scenario-adjusted) | B13: =Assumptions!$B$8*Assumptions!$D$19 -> 0.06
A14: Share excluded / re-sourced q | B14: =Assumptions!$B$9 -> 0.3
A15: Discount rate | B15: =Assumptions!$B$5 -> 0.08
A16: Growth | B16: =Assumptions!$B$6 -> 0.02
A17: CPO price level × (scenario) | B17: =Assumptions!$E$19 -> 1
A18: Baseline coverage c0 | B18: =Assumptions!$B$10 -> 0.3
A20: Option design | B20: cmax | C20: Ramp (yrs) | D20: eff | E20: Capex | F20: Opex / yr
A21: Status quo | B21: =Assumptions!B41 -> 0.3 | C21: =Assumptions!B42 -> 1 | D21: =Assumptions!B43 -> 0.6 | E21: 0 | F21: 0
A22: Central database | B22: =Assumptions!C41 -> 0.8 | C22: =Assumptions!C42 -> 3 | D22: =Assumptions!C43 -> 0.8 | E22: =Assumptions!B34 -> 8 | F22: =Assumptions!B35 -> 3
A23: Permissioned blockchain | B23: =Assumptions!D41 -> 0.9 | C23: =Assumptions!D42 -> 4 | D23: =Assumptions!D43 -> 0.9 | E23: =Assumptions!B36 -> 14 | F23: =Assumptions!B37 -> 4.5
A26: Year | B26: Year | C26: 0 | D26: 1 | E26: 2 | F26: 3 | G26: 4 | H26: 5 | I26: 6 | J26: 7
A27: Growth factor | C27: =(1+$B$16)^C$26 -> 1 | D27: =(1+$B$16)^D$26 -> 1.02 | E27: =(1+$B$16)^E$26 -> 1.0404 | F27: =(1+$B$16)^F$26 -> 1.061208 | G27: =(1+$B$16)^G$26 -> 1.0824322 | H27: =(1+$B$16)^H$26 -> 1.1040808 | I27: =(1+$B$16)^I$26 -> 1.1261624 | J27: =(1+$B$16)^J$26 -> 1.1486857
A28: Revenue | C28: =$B$4*C27 -> 58078.45 | D28: =$B$4*D27 -> 59240.019 | E28: =$B$4*E27 -> 60424.819 | F28: =$B$4*F27 -> 61633.316 | G28: =$B$4*G27 -> 62865.982 | H28: =$B$4*H27 -> 64123.302 | I28: =$B$4*I27 -> 65405.768 | J28: =$B$4*J27 -> 66713.883
A29: COGS | C29: =$B$5*C27 -> 30813.1 | D29: =$B$5*D27 -> 31429.362 | E29: =$B$5*E27 -> 32057.949 | F29: =$B$5*F27 -> 32699.108 | G29: =$B$5*G27 -> 33353.09 | H29: =$B$5*H27 -> 34020.152 | I29: =$B$5*I27 -> 34700.555 | J29: =$B$5*J27 -> 35394.566
A30: Discount factor | C30: =1/(1+$B$15)^C$26 -> 1 | D30: =1/(1+$B$15)^D$26 -> 0.92592593 | E30: =1/(1+$B$15)^E$26 -> 0.85733882 | F30: =1/(1+$B$15)^F$26 -> 0.79383224 | G30: =1/(1+$B$15)^G$26 -> 0.73502985 | H30: =1/(1+$B$15)^H$26 -> 0.6805832 | I30: =1/(1+$B$15)^I$26 -> 0.63016963 | J30: =1/(1+$B$15)^J$26 -> 0.5834904
A31: CPO price index | C31: =1 -> 1 | D31: =$B$17 -> 1 | E31: =$B$17 -> 1 | F31: =$B$17 -> 1 | G31: =$B$17 -> 1 | H31: =$B$17 -> 1 | I31: =$B$17 -> 1 | J31: =$B$17 -> 1
A32: Palm-derived spend | C32: =C29*$B$7*C31 -> 924.393 | D32: =D29*$B$7*D31 -> 942.88086 | E32: =E29*$B$7*E31 -> 961.73848 | F32: =F29*$B$7*F31 -> 980.97325 | G32: =G29*$B$7*G31 -> 1000.5927 | H32: =H29*$B$7*H31 -> 1020.6046 | I32: =I29*$B$7*I31 -> 1041.0167 | J32: =J29*$B$7*J31 -> 1061.837
A34: Option: Status quo
A35: Traceable coverage | C35: =$B$18 -> 0.3 | D35: =$B$18+($B$21-$B$18)*MIN(1,D$26/$C$21) -> 0.3 | E35: =$B$18+($B$21-$B$18)*MIN(1,E$26/$C$21) -> 0.3 | F35: =$B$18+($B$21-$B$18)*MIN(1,F$26/$C$21) -> 0.3 | G35: =$B$18+($B$21-$B$18)*MIN(1,G$26/$C$21) -> 0.3 | H35: =$B$18+($B$21-$B$18)*MIN(1,H$26/$C$21) -> 0.3 | I35: =$B$18+($B$21-$B$18)*MIN(1,I$26/$C$21) -> 0.3 | J35: =$B$18+($B$21-$B$18)*MIN(1,J$26/$C$21) -> 0.3
A36: Mitigation (coverage × eff) | C36: =C35*$D$21 -> 0.18 | D36: =D35*$D$21 -> 0.18 | E36: =E35*$D$21 -> 0.18 | F36: =F35*$D$21 -> 0.18 | G36: =G35*$D$21 -> 0.18 | H36: =H35*$D$21 -> 0.18 | I36: =I35*$D$21 -> 0.18 | J36: =J35*$D$21 -> 0.18
A37: Regulatory loss (expected) | C37: 0 | D37: =$B$9*$B$12*$B$8*D$28*(1-D36) -> 7.2865223 | E37: =$B$9*$B$12*$B$8*E$28*(1-E36) -> 7.4322528 | F37: =$B$9*$B$12*$B$8*F$28*(1-F36) -> 7.5808978 | G37: =$B$9*$B$12*$B$8*G$28*(1-G36) -> 7.7325158 | H37: =$B$9*$B$12*$B$8*H$28*(1-H36) -> 7.8871661 | I37: =$B$9*$B$12*$B$8*I$28*(1-I36) -> 8.0449094 | J37: =$B$9*$B$12*$B$8*J$28*(1-J36) -> 8.2058076
A38: Supplier substitution cost | C38: 0 | D38: =D$32*$B$8*(1-D35)*$B$14*$B$13 -> 2.9700747 | E38: =E$32*$B$8*(1-E35)*$B$14*$B$13 -> 3.0294762 | F38: =F$32*$B$8*(1-F35)*$B$14*$B$13 -> 3.0900657 | G38: =G$32*$B$8*(1-G35)*$B$14*$B$13 -> 3.151867 | H38: =H$32*$B$8*(1-H35)*$B$14*$B$13 -> 3.2149044 | I38: =I$32*$B$8*(1-I35)*$B$14*$B$13 -> 3.2792025 | J38: =J$32*$B$8*(1-J35)*$B$14*$B$13 -> 3.3447865
A39: Reputational / controversy loss (expected) | C39: 0 | D39: =$B$10*$B$11*$B$6*D$28*(1-D36) -> 6.0721019 | E39: =$B$10*$B$11*$B$6*E$28*(1-E36) -> 6.193544 | F39: =$B$10*$B$11*$B$6*F$28*(1-F36) -> 6.3174149 | G39: =$B$10*$B$11*$B$6*G$28*(1-G36) -> 6.4437632 | H39: =$B$10*$B$11*$B$6*H$28*(1-H36) -> 6.5726384 | I39: =$B$10*$B$11*$B$6*I$28*(1-I36) -> 6.7040912 | J39: =$B$10*$B$11*$B$6*J$28*(1-J36) -> 6.838173
A40: Programme opex | C40: 0 | D40: =$F$21*D$27 -> 0 | E40: =$F$21*E$27 -> 0 | F40: =$F$21*F$27 -> 0 | G40: =$F$21*G$27 -> 0 | H40: =$F$21*H$27 -> 0 | I40: =$F$21*I$27 -> 0 | J40: =$F$21*J$27 -> 0
A41: Programme capex | C41: =$E$21 -> 0 | D41: 0 | E41: 0 | F41: 0 | G41: 0 | H41: 0 | I41: 0 | J41: 0
A42: Total cost (losses + programme) | C42: =SUM(C37:C41) -> 0 | D42: =SUM(D37:D41) -> 16.328699 | E42: =SUM(E37:E41) -> 16.655273 | F42: =SUM(F37:F41) -> 16.988378 | G42: =SUM(G37:G41) -> 17.328146 | H42: =SUM(H37:H41) -> 17.674709 | I42: =SUM(I37:I41) -> 18.028203 | J42: =SUM(J37:J41) -> 18.388767
A43: PV of total cost | C43: =C42*C$30 -> 0 | D43: =D42*D$30 -> 15.119166 | E43: =E42*E$30 -> 14.279212 | F43: =F42*F$30 -> 13.485923 | G43: =G42*G$30 -> 12.736705 | H43: =H42*H$30 -> 12.02911 | I43: =I42*I$30 -> 11.360826 | J43: =J42*J$30 -> 10.729669
A45: Option: Central database
A46: Traceable coverage | C46: =$B$18 -> 0.3 | D46: =$B$18+($B$22-$B$18)*MIN(1,D$26/$C$22) -> 0.46666667 | E46: =$B$18+($B$22-$B$18)*MIN(1,E$26/$C$22) -> 0.63333333 | F46: =$B$18+($B$22-$B$18)*MIN(1,F$26/$C$22) -> 0.8 | G46: =$B$18+($B$22-$B$18)*MIN(1,G$26/$C$22) -> 0.8 | H46: =$B$18+($B$22-$B$18)*MIN(1,H$26/$C$22) -> 0.8 | I46: =$B$18+($B$22-$B$18)*MIN(1,I$26/$C$22) -> 0.8 | J46: =$B$18+($B$22-$B$18)*MIN(1,J$26/$C$22) -> 0.8
A47: Mitigation (coverage × eff) | C47: =C46*$D$22 -> 0.24 | D47: =D46*$D$22 -> 0.37333333 | E47: =E46*$D$22 -> 0.50666667 | F47: =F46*$D$22 -> 0.64 | G47: =G46*$D$22 -> 0.64 | H47: =H46*$D$22 -> 0.64 | I47: =I46*$D$22 -> 0.64 | J47: =J46*$D$22 -> 0.64
A48: Regulatory loss (expected) | C48: 0 | D48: =$B$9*$B$12*$B$8*D$28*(1-D47) -> 5.5685618 | E48: =$B$9*$B$12*$B$8*E$28*(1-E47) -> 4.4714366 | F48: =$B$9*$B$12*$B$8*F$28*(1-F47) -> 3.3281991 | G48: =$B$9*$B$12*$B$8*G$28*(1-G47) -> 3.394763 | H48: =$B$9*$B$12*$B$8*H$28*(1-H47) -> 3.4626583 | I48: =$B$9*$B$12*$B$8*I$28*(1-I47) -> 3.5319115 | J48: =$B$9*$B$12*$B$8*J$28*(1-J47) -> 3.6025497
A49: Supplier substitution cost | C49: 0 | D49: =D$32*$B$8*(1-D46)*$B$14*$B$13 -> 2.2629141 | E49: =E$32*$B$8*(1-E46)*$B$14*$B$13 -> 1.5868685 | F49: =F$32*$B$8*(1-F46)*$B$14*$B$13 -> 0.88287592 | G49: =G$32*$B$8*(1-G46)*$B$14*$B$13 -> 0.90053344 | H49: =H$32*$B$8*(1-H46)*$B$14*$B$13 -> 0.91854411 | I49: =I$32*$B$8*(1-I46)*$B$14*$B$13 -> 0.93691499 | J49: =J$32*$B$8*(1-J46)*$B$14*$B$13 -> 0.95565329
A50: Reputational / controversy loss (expected) | C50: 0 | D50: =$B$10*$B$11*$B$6*D$28*(1-D47) -> 4.6404682 | E50: =$B$10*$B$11*$B$6*E$28*(1-E47) -> 3.7261972 | F50: =$B$10*$B$11*$B$6*F$28*(1-F47) -> 2.7734992 | G50: =$B$10*$B$11*$B$6*G$28*(1-G47) -> 2.8289692 | H50: =$B$10*$B$11*$B$6*H$28*(1-H47) -> 2.8855486 | I50: =$B$10*$B$11*$B$6*I$28*(1-I47) -> 2.9432595 | J50: =$B$10*$B$11*$B$6*J$28*(1-J47) -> 3.0021247
A51: Programme opex | C51: 0 | D51: =$F$22*D$27 -> 3.06 | E51: =$F$22*E$27 -> 3.1212 | F51: =$F$22*F$27 -> 3.183624 | G51: =$F$22*G$27 -> 3.2472965 | H51: =$F$22*H$27 -> 3.3122424 | I51: =$F$22*I$27 -> 3.3784873 | J51: =$F$22*J$27 -> 3.446057
A52: Programme capex | C52: =$E$22 -> 8 | D52: 0 | E52: 0 | F52: 0 | G52: 0 | H52: 0 | I52: 0 | J52: 0
A53: Total cost (losses + programme) | C53: =SUM(C48:C52) -> 8 | D53: =SUM(D48:D52) -> 15.531944 | E53: =SUM(E48:E52) -> 12.905702 | F53: =SUM(F48:F52) -> 10.168198 | G53: =SUM(G48:G52) -> 10.371562 | H53: =SUM(H48:H52) -> 10.578993 | I53: =SUM(I48:I52) -> 10.790573 | J53: =SUM(J48:J52) -> 11.006385
A54: PV of total cost | C54: =C53*C$30 -> 8 | D54: =D53*D$30 -> 14.38143 | E54: =E53*E$30 -> 11.06456 | F54: =F53*F$30 -> 8.0718436 | G54: =G53*G$30 -> 7.6234078 | H54: =H53*H$30 -> 7.1998851 | I54: =I53*I$30 -> 6.7998915 | J54: =J53*J$30 -> 6.4221198
A56: Option: Permissioned blockchain
A57: Traceable coverage | C57: =$B$18 -> 0.3 | D57: =$B$18+($B$23-$B$18)*MIN(1,D$26/$C$23) -> 0.45 | E57: =$B$18+($B$23-$B$18)*MIN(1,E$26/$C$23) -> 0.6 | F57: =$B$18+($B$23-$B$18)*MIN(1,F$26/$C$23) -> 0.75 | G57: =$B$18+($B$23-$B$18)*MIN(1,G$26/$C$23) -> 0.9 | H57: =$B$18+($B$23-$B$18)*MIN(1,H$26/$C$23) -> 0.9 | I57: =$B$18+($B$23-$B$18)*MIN(1,I$26/$C$23) -> 0.9 | J57: =$B$18+($B$23-$B$18)*MIN(1,J$26/$C$23) -> 0.9
A58: Mitigation (coverage × eff) | C58: =C57*$D$23 -> 0.27 | D58: =D57*$D$23 -> 0.405 | E58: =E57*$D$23 -> 0.54 | F58: =F57*$D$23 -> 0.675 | G58: =G57*$D$23 -> 0.81 | H58: =H57*$D$23 -> 0.81 | I58: =I57*$D$23 -> 0.81 | J58: =J57*$D$23 -> 0.81
A59: Regulatory loss (expected) | C59: 0 | D59: =$B$9*$B$12*$B$8*D$28*(1-D58) -> 5.2871717 | E59: =$B$9*$B$12*$B$8*E$28*(1-E58) -> 4.1693125 | F59: =$B$9*$B$12*$B$8*F$28*(1-F58) -> 3.0046241 | G59: =$B$9*$B$12*$B$8*G$28*(1-G58) -> 1.7916805 | H59: =$B$9*$B$12*$B$8*H$28*(1-H58) -> 1.8275141 | I59: =$B$9*$B$12*$B$8*I$28*(1-I58) -> 1.8640644 | J59: =$B$9*$B$12*$B$8*J$28*(1-J58) -> 1.9013457
A60: Supplier substitution cost | C60: 0 | D60: =D$32*$B$8*(1-D57)*$B$14*$B$13 -> 2.3336301 | E60: =E$32*$B$8*(1-E57)*$B$14*$B$13 -> 1.7311293 | F60: =F$32*$B$8*(1-F57)*$B$14*$B$13 -> 1.1035949 | G60: =G$32*$B$8*(1-G57)*$B$14*$B$13 -> 0.45026672 | H60: =H$32*$B$8*(1-H57)*$B$14*$B$13 -> 0.45927205 | I60: =I$32*$B$8*(1-I57)*$B$14*$B$13 -> 0.4684575 | J60: =J$32*$B$8*(1-J57)*$B$14*$B$13 -> 0.47782665
A61: Reputational / controversy loss (expected) | C61: 0 | D61: =$B$10*$B$11*$B$6*D$28*(1-D58) -> 4.4059764 | E61: =$B$10*$B$11*$B$6*E$28*(1-E58) -> 3.4744271 | F61: =$B$10*$B$11*$B$6*F$28*(1-F58) -> 2.5038535 | G61: =$B$10*$B$11*$B$6*G$28*(1-G58) -> 1.4930671 | H61: =$B$10*$B$11*$B$6*H$28*(1-H58) -> 1.5229284 | I61: =$B$10*$B$11*$B$6*I$28*(1-I58) -> 1.553387 | J61: =$B$10*$B$11*$B$6*J$28*(1-J58) -> 1.5844547
A62: Programme opex | C62: 0 | D62: =$F$23*D$27 -> 4.59 | E62: =$F$23*E$27 -> 4.6818 | F62: =$F$23*F$27 -> 4.775436 | G62: =$F$23*G$27 -> 4.8709447 | H62: =$F$23*H$27 -> 4.9683636 | I62: =$F$23*I$27 -> 5.0677309 | J62: =$F$23*J$27 -> 5.1690855
A63: Programme capex | C63: =$E$23 -> 14 | D63: 0 | E63: 0 | F63: 0 | G63: 0 | H63: 0 | I63: 0 | J63: 0
A64: Total cost (losses + programme) | C64: =SUM(C59:C63) -> 14 | D64: =SUM(D59:D63) -> 16.616778 | E64: =SUM(E59:E63) -> 14.056669 | F64: =SUM(F59:F63) -> 11.387508 | G64: =SUM(G59:G63) -> 8.605959 | H64: =SUM(H59:H63) -> 8.7780782 | I64: =SUM(I59:I63) -> 8.9536397 | J64: =SUM(J59:J63) -> 9.1327125
A65: PV of total cost | C65: =C64*C$30 -> 14 | D65: =D64*D$30 -> 15.385906 | E65: =E64*E$30 -> 12.051328 | F65: =F64*F$30 -> 9.0397714 | G65: =G64*G$30 -> 6.3256368 | H65: =H64*H$30 -> 5.9742125 | I65: =I64*I$30 -> 5.6423118 | J65: =J64*J$30 -> 5.3288501
A68: Summary (PV at year 0, USD m)
A69: Option | B69: PV expected losses | C69: PV programme cost | D69: PV total cost | E69: Benefit vs status quo (NPV) | F69: PV avoided losses | G69: Benefit / programme cost | H69: Break-even p_reg multiplier | I69: Discounted payback (yr)
A70: Status quo | B70: =SUMPRODUCT((C37:J37+C38:J38+C39:J39)*$C$30:$J$30) -> 89.74061 | C70: =SUMPRODUCT((C40:J40+C41:J41)*$C$30:$J$30) -> 0 | D70: =SUM(C43:J43) -> 89.74061
A71: Central database | B71: =SUMPRODUCT((C48:J48+C49:J49+C50:J50)*$C$30:$J$30) -> 44.745737 | C71: =SUMPRODUCT((C51:J51+C52:J52)*$C$30:$J$30) -> 24.8174 | D71: =SUM(C54:J54) -> 69.563137 | E71: =$D$70-D71 -> 20.177473 | F71: =$B$70-B71 -> 44.994873 | G71: =IF(C71=0,0,F71/C71) -> 1.8130373 | H71: =IFERROR(MAX(0,1-E71/SUMPRODUCT((C37:J37-C48:J48)*$C$30:$J$30)),0) -> 0 | I71: =IF(MIN(C77:J77)=99,"> 7",MIN(C77:J77)) -> 3
A72: Permissioned blockchain | B72: =SUMPRODUCT((C59:J59+C60:J60+C61:J61)*$C$30:$J$30) -> 34.521916 | C72: =SUMPRODUCT((C62:J62+C63:J63)*$C$30:$J$30) -> 39.2261 | D72: =SUM(C65:J65) -> 73.748016 | E72: =$D$70-D72 -> 15.992594 | F72: =$B$70-B72 -> 55.218694 | G72: =IF(C72=0,0,F72/C72) -> 1.4077029 | H72: =IFERROR(MAX(0,1-E72/SUMPRODUCT((C37:J37-C59:J59)*$C$30:$J$30)),0) -> 0.34310807 | I72: =IF(MIN(C79:J79)=99,"> 7",MIN(C79:J79)) -> 5
A75: Cumulative discounted net benefit vs status quo
A76: Central database — cumulative | C76: =(C42-C53)*C$30 -> -8 | D76: =(D42-D53)*D$30+C76 -> -7.2622639 | E76: =(E42-E53)*E$30+D76 -> -4.0476114 | F76: =(F42-F53)*F$30+E76 -> 1.3664676 | G76: =(G42-G53)*G$30+F76 -> 6.4797644 | H76: =(H42-H53)*H$30+G76 -> 11.308989 | I76: =(I42-I53)*I$30+H76 -> 15.869924 | J76: =(J42-J53)*J$30+I76 -> 20.177473
A77: payback flag (year if cumulative ≥ 0, else 99) | C77: =IF(C76>=0,C$26,99) -> 99 | D77: =IF(D76>=0,D$26,99) -> 99 | E77: =IF(E76>=0,E$26,99) -> 99 | F77: =IF(F76>=0,F$26,99) -> 3 | G77: =IF(G76>=0,G$26,99) -> 4 | H77: =IF(H76>=0,H$26,99) -> 5 | I77: =IF(I76>=0,I$26,99) -> 6 | J77: =IF(J76>=0,J$26,99) -> 7
A78: Permissioned blockchain — cumulative | C78: =(C42-C64)*C$30 -> -14 | D78: =(D42-D64)*D$30+C78 -> -14.26674 | E78: =(E42-E64)*E$30+D78 -> -12.038856 | F78: =(F42-F64)*F$30+E78 -> -7.5927048 | G78: =(G42-G64)*G$30+F78 -> -1.1816369 | H78: =(H42-H64)*H$30+G78 -> 4.8732604 | I78: =(I42-I64)*I$30+H78 -> 10.591775 | J78: =(J42-J64)*J$30+I78 -> 15.992594
A79: payback flag (year if cumulative ≥ 0, else 99) | C79: =IF(C78>=0,C$26,99) -> 99 | D79: =IF(D78>=0,D$26,99) -> 99 | E79: =IF(E78>=0,E$26,99) -> 99 | F79: =IF(F78>=0,F$26,99) -> 99 | G79: =IF(G78>=0,G$26,99) -> 99 | H79: =IF(H78>=0,H$26,99) -> 5 | I79: =IF(I78>=0,I$26,99) -> 6 | J79: =IF(J78>=0,J$26,99) -> 7
A81: Blockchain minus central database (NPV) | E81: =E72-E71 -> -4.1848793
A82: Break-even p_reg multiplier: the factor on the regulatory-event probability at which the option's NPV is zero (0 = pays back even with no regulatory risk, because substitution and reputation benefits already cover costs).

Sheet ROI_NESN
A1: Nestlé — traceability programme: status quo vs central database vs permissioned blockchain (USD m)
A2: Pure calculation sheet: all inputs are green links to 'Assumptions'. Change the scenario on Assumptions!B13. Year 0 = build year.
A4: Revenue, USD m (FY2025) | B4: =Assumptions!C26 -> 112356.25 | D4: Active scenario: | E4: =Assumptions!B13 -> Base
A5: COGS, USD m (FY2025) | B5: =Assumptions!C27 -> 60867.5
A6: a palm-linked revenue share | B6: =Assumptions!C28 -> 0.15
A7: ps palm spend / COGS | B7: =Assumptions!C29 -> 0.015
A8: eu EU-regulated revenue share | B8: =Assumptions!C30 -> 0.25
A9: p_reg (scenario-adjusted) | B9: =Assumptions!C31*Assumptions!$B$19 -> 0.03
A10: p_ctrv (scenario-adjusted) | B10: =Assumptions!C32*Assumptions!$C$19 -> 0.1
A11: rev_loss | B11: =Assumptions!C33 -> 0.005
A12: Realised fine rate | B12: =Assumptions!$B$7 -> 0.02
A13: Substitution premium π (scenario-adjusted) | B13: =Assumptions!$B$8*Assumptions!$D$19 -> 0.06
A14: Share excluded / re-sourced q | B14: =Assumptions!$B$9 -> 0.3
A15: Discount rate | B15: =Assumptions!$B$5 -> 0.08
A16: Growth | B16: =Assumptions!$B$6 -> 0.02
A17: CPO price level × (scenario) | B17: =Assumptions!$E$19 -> 1
A18: Baseline coverage c0 | B18: =Assumptions!$B$10 -> 0.3
A20: Option design | B20: cmax | C20: Ramp (yrs) | D20: eff | E20: Capex | F20: Opex / yr
A21: Status quo | B21: =Assumptions!B41 -> 0.3 | C21: =Assumptions!B42 -> 1 | D21: =Assumptions!B43 -> 0.6 | E21: 0 | F21: 0
A22: Central database | B22: =Assumptions!C41 -> 0.8 | C22: =Assumptions!C42 -> 3 | D22: =Assumptions!C43 -> 0.8 | E22: =Assumptions!C34 -> 7 | F22: =Assumptions!C35 -> 2.5
A23: Permissioned blockchain | B23: =Assumptions!D41 -> 0.9 | C23: =Assumptions!D42 -> 4 | D23: =Assumptions!D43 -> 0.9 | E23: =Assumptions!C36 -> 12 | F23: =Assumptions!C37 -> 4
A26: Year | B26: Year | C26: 0 | D26: 1 | E26: 2 | F26: 3 | G26: 4 | H26: 5 | I26: 6 | J26: 7
A27: Growth factor | C27: =(1+$B$16)^C$26 -> 1 | D27: =(1+$B$16)^D$26 -> 1.02 | E27: =(1+$B$16)^E$26 -> 1.0404 | F27: =(1+$B$16)^F$26 -> 1.061208 | G27: =(1+$B$16)^G$26 -> 1.0824322 | H27: =(1+$B$16)^H$26 -> 1.1040808 | I27: =(1+$B$16)^I$26 -> 1.1261624 | J27: =(1+$B$16)^J$26 -> 1.1486857
A28: Revenue | C28: =$B$4*C27 -> 112356.25 | D28: =$B$4*D27 -> 114603.38 | E28: =$B$4*E27 -> 116895.44 | F28: =$B$4*F27 -> 119233.35 | G28: =$B$4*G27 -> 121618.02 | H28: =$B$4*H27 -> 124050.38 | I28: =$B$4*I27 -> 126531.39 | J28: =$B$4*J27 -> 129062.01
A29: COGS | C29: =$B$5*C27 -> 60867.5 | D29: =$B$5*D27 -> 62084.85 | E29: =$B$5*E27 -> 63326.547 | F29: =$B$5*F27 -> 64593.078 | G29: =$B$5*G27 -> 65884.939 | H29: =$B$5*H27 -> 67202.638 | I29: =$B$5*I27 -> 68546.691 | J29: =$B$5*J27 -> 69917.625
A30: Discount factor | C30: =1/(1+$B$15)^C$26 -> 1 | D30: =1/(1+$B$15)^D$26 -> 0.92592593 | E30: =1/(1+$B$15)^E$26 -> 0.85733882 | F30: =1/(1+$B$15)^F$26 -> 0.79383224 | G30: =1/(1+$B$15)^G$26 -> 0.73502985 | H30: =1/(1+$B$15)^H$26 -> 0.6805832 | I30: =1/(1+$B$15)^I$26 -> 0.63016963 | J30: =1/(1+$B$15)^J$26 -> 0.5834904
A31: CPO price index | C31: =1 -> 1 | D31: =$B$17 -> 1 | E31: =$B$17 -> 1 | F31: =$B$17 -> 1 | G31: =$B$17 -> 1 | H31: =$B$17 -> 1 | I31: =$B$17 -> 1 | J31: =$B$17 -> 1
A32: Palm-derived spend | C32: =C29*$B$7*C31 -> 913.0125 | D32: =D29*$B$7*D31 -> 931.27275 | E32: =E29*$B$7*E31 -> 949.8982 | F32: =F29*$B$7*F31 -> 968.89617 | G32: =G29*$B$7*G31 -> 988.27409 | H32: =H29*$B$7*H31 -> 1008.0396 | I32: =I29*$B$7*I31 -> 1028.2004 | J32: =J29*$B$7*J31 -> 1048.7644
A34: Option: Status quo
A35: Traceable coverage | C35: =$B$18 -> 0.3 | D35: =$B$18+($B$21-$B$18)*MIN(1,D$26/$C$21) -> 0.3 | E35: =$B$18+($B$21-$B$18)*MIN(1,E$26/$C$21) -> 0.3 | F35: =$B$18+($B$21-$B$18)*MIN(1,F$26/$C$21) -> 0.3 | G35: =$B$18+($B$21-$B$18)*MIN(1,G$26/$C$21) -> 0.3 | H35: =$B$18+($B$21-$B$18)*MIN(1,H$26/$C$21) -> 0.3 | I35: =$B$18+($B$21-$B$18)*MIN(1,I$26/$C$21) -> 0.3 | J35: =$B$18+($B$21-$B$18)*MIN(1,J$26/$C$21) -> 0.3
A36: Mitigation (coverage × eff) | C36: =C35*$D$21 -> 0.18 | D36: =D35*$D$21 -> 0.18 | E36: =E35*$D$21 -> 0.18 | F36: =F35*$D$21 -> 0.18 | G36: =G35*$D$21 -> 0.18 | H36: =H35*$D$21 -> 0.18 | I36: =I35*$D$21 -> 0.18 | J36: =J35*$D$21 -> 0.18
A37: Regulatory loss (expected) | C37: 0 | D37: =$B$9*$B$12*$B$8*D$28*(1-D36) -> 14.096215 | E37: =$B$9*$B$12*$B$8*E$28*(1-E36) -> 14.378139 | F37: =$B$9*$B$12*$B$8*F$28*(1-F36) -> 14.665702 | G37: =$B$9*$B$12*$B$8*G$28*(1-G36) -> 14.959016 | H37: =$B$9*$B$12*$B$8*H$28*(1-H36) -> 15.258197 | I37: =$B$9*$B$12*$B$8*I$28*(1-I36) -> 15.563361 | J37: =$B$9*$B$12*$B$8*J$28*(1-J36) -> 15.874628
A38: Supplier substitution cost | C38: 0 | D38: =D$32*$B$8*(1-D35)*$B$14*$B$13 -> 2.9335092 | E38: =E$32*$B$8*(1-E35)*$B$14*$B$13 -> 2.9921793 | F38: =F$32*$B$8*(1-F35)*$B$14*$B$13 -> 3.0520229 | G38: =G$32*$B$8*(1-G35)*$B$14*$B$13 -> 3.1130634 | H38: =H$32*$B$8*(1-H35)*$B$14*$B$13 -> 3.1753247 | I38: =I$32*$B$8*(1-I35)*$B$14*$B$13 -> 3.2388312 | J38: =J$32*$B$8*(1-J35)*$B$14*$B$13 -> 3.3036078
A39: Reputational / controversy loss (expected) | C39: 0 | D39: =$B$10*$B$11*$B$6*D$28*(1-D36) -> 7.0481076 | E39: =$B$10*$B$11*$B$6*E$28*(1-E36) -> 7.1890697 | F39: =$B$10*$B$11*$B$6*F$28*(1-F36) -> 7.3328511 | G39: =$B$10*$B$11*$B$6*G$28*(1-G36) -> 7.4795081 | H39: =$B$10*$B$11*$B$6*H$28*(1-H36) -> 7.6290983 | I39: =$B$10*$B$11*$B$6*I$28*(1-I36) -> 7.7816803 | J39: =$B$10*$B$11*$B$6*J$28*(1-J36) -> 7.9373139
A40: Programme opex | C40: 0 | D40: =$F$21*D$27 -> 0 | E40: =$F$21*E$27 -> 0 | F40: =$F$21*F$27 -> 0 | G40: =$F$21*G$27 -> 0 | H40: =$F$21*H$27 -> 0 | I40: =$F$21*I$27 -> 0 | J40: =$F$21*J$27 -> 0
A41: Programme capex | C41: =$E$21 -> 0 | D41: 0 | E41: 0 | F41: 0 | G41: 0 | H41: 0 | I41: 0 | J41: 0
A42: Total cost (losses + programme) | C42: =SUM(C37:C41) -> 0 | D42: =SUM(D37:D41) -> 24.077832 | E42: =SUM(E37:E41) -> 24.559388 | F42: =SUM(F37:F41) -> 25.050576 | G42: =SUM(G37:G41) -> 25.551588 | H42: =SUM(H37:H41) -> 26.06262 | I42: =SUM(I37:I41) -> 26.583872 | J42: =SUM(J37:J41) -> 27.115549
A43: PV of total cost | C43: =C42*C$30 -> 0 | D43: =D42*D$30 -> 22.294289 | E43: =E42*E$30 -> 21.055717 | F43: =F42*F$30 -> 19.885955 | G43: =G42*G$30 -> 18.78118 | H43: =H42*H$30 -> 17.737781 | I43: =I42*I$30 -> 16.752349 | J43: =J42*J$30 -> 15.821663
A45: Option: Central database
A46: Traceable coverage | C46: =$B$18 -> 0.3 | D46: =$B$18+($B$22-$B$18)*MIN(1,D$26/$C$22) -> 0.46666667 | E46: =$B$18+($B$22-$B$18)*MIN(1,E$26/$C$22) -> 0.63333333 | F46: =$B$18+($B$22-$B$18)*MIN(1,F$26/$C$22) -> 0.8 | G46: =$B$18+($B$22-$B$18)*MIN(1,G$26/$C$22) -> 0.8 | H46: =$B$18+($B$22-$B$18)*MIN(1,H$26/$C$22) -> 0.8 | I46: =$B$18+($B$22-$B$18)*MIN(1,I$26/$C$22) -> 0.8 | J46: =$B$18+($B$22-$B$18)*MIN(1,J$26/$C$22) -> 0.8
A47: Mitigation (coverage × eff) | C47: =C46*$D$22 -> 0.24 | D47: =D46*$D$22 -> 0.37333333 | E47: =E46*$D$22 -> 0.50666667 | F47: =F46*$D$22 -> 0.64 | G47: =G46*$D$22 -> 0.64 | H47: =H46*$D$22 -> 0.64 | I47: =I46*$D$22 -> 0.64 | J47: =J46*$D$22 -> 0.64
A48: Regulatory loss (expected) | C48: 0 | D48: =$B$9*$B$12*$B$8*D$28*(1-D47) -> 10.772717 | E48: =$B$9*$B$12*$B$8*E$28*(1-E47) -> 8.6502627 | F48: =$B$9*$B$12*$B$8*F$28*(1-F47) -> 6.438601 | G48: =$B$9*$B$12*$B$8*G$28*(1-G47) -> 6.567373 | H48: =$B$9*$B$12*$B$8*H$28*(1-H47) -> 6.6987205 | I48: =$B$9*$B$12*$B$8*I$28*(1-I47) -> 6.8326949 | J48: =$B$9*$B$12*$B$8*J$28*(1-J47) -> 6.9693488
A49: Supplier substitution cost | C49: 0 | D49: =D$32*$B$8*(1-D46)*$B$14*$B$13 -> 2.2350546 | E49: =E$32*$B$8*(1-E46)*$B$14*$B$13 -> 1.567332 | F49: =F$32*$B$8*(1-F46)*$B$14*$B$13 -> 0.87200655 | G49: =G$32*$B$8*(1-G46)*$B$14*$B$13 -> 0.88944668 | H49: =H$32*$B$8*(1-H46)*$B$14*$B$13 -> 0.90723562 | I49: =I$32*$B$8*(1-I46)*$B$14*$B$13 -> 0.92538033 | J49: =J$32*$B$8*(1-J46)*$B$14*$B$13 -> 0.94388794
A50: Reputational / controversy loss (expected) | C50: 0 | D50: =$B$10*$B$11*$B$6*D$28*(1-D47) -> 5.3863586 | E50: =$B$10*$B$11*$B$6*E$28*(1-E47) -> 4.3251314 | F50: =$B$10*$B$11*$B$6*F$28*(1-F47) -> 3.2193005 | G50: =$B$10*$B$11*$B$6*G$28*(1-G47) -> 3.2836865 | H50: =$B$10*$B$11*$B$6*H$28*(1-H47) -> 3.3493602 | I50: =$B$10*$B$11*$B$6*I$28*(1-I47) -> 3.4163474 | J50: =$B$10*$B$11*$B$6*J$28*(1-J47) -> 3.4846744
A51: Programme opex | C51: 0 | D51: =$F$22*D$27 -> 2.55 | E51: =$F$22*E$27 -> 2.601 | F51: =$F$22*F$27 -> 2.65302 | G51: =$F$22*G$27 -> 2.7060804 | H51: =$F$22*H$27 -> 2.760202 | I51: =$F$22*I$27 -> 2.815406 | J51: =$F$22*J$27 -> 2.8717142
A52: Programme capex | C52: =$E$22 -> 7 | D52: 0 | E52: 0 | F52: 0 | G52: 0 | H52: 0 | I52: 0 | J52: 0
A53: Total cost (losses + programme) | C53: =SUM(C48:C52) -> 7 | D53: =SUM(D48:D52) -> 20.94413 | E53: =SUM(E48:E52) -> 17.143726 | F53: =SUM(F48:F52) -> 13.182928 | G53: =SUM(G48:G52) -> 13.446587 | H53: =SUM(H48:H52) -> 13.715518 | I53: =SUM(I48:I52) -> 13.989829 | J53: =SUM(J48:J52) -> 14.269625
A54: PV of total cost | C54: =C53*C$30 -> 7 | D54: =D53*D$30 -> 19.392713 | E54: =E53*E$30 -> 14.697982 | F54: =F53*F$30 -> 10.465033 | G54: =G53*G$30 -> 9.8836425 | H54: =H53*H$30 -> 9.3345513 | I54: =I53*I$30 -> 8.8159651 | J54: =J53*J$30 -> 8.3261893
A56: Option: Permissioned blockchain
A57: Traceable coverage | C57: =$B$18 -> 0.3 | D57: =$B$18+($B$23-$B$18)*MIN(1,D$26/$C$23) -> 0.45 | E57: =$B$18+($B$23-$B$18)*MIN(1,E$26/$C$23) -> 0.6 | F57: =$B$18+($B$23-$B$18)*MIN(1,F$26/$C$23) -> 0.75 | G57: =$B$18+($B$23-$B$18)*MIN(1,G$26/$C$23) -> 0.9 | H57: =$B$18+($B$23-$B$18)*MIN(1,H$26/$C$23) -> 0.9 | I57: =$B$18+($B$23-$B$18)*MIN(1,I$26/$C$23) -> 0.9 | J57: =$B$18+($B$23-$B$18)*MIN(1,J$26/$C$23) -> 0.9
A58: Mitigation (coverage × eff) | C58: =C57*$D$23 -> 0.27 | D58: =D57*$D$23 -> 0.405 | E58: =E57*$D$23 -> 0.54 | F58: =F57*$D$23 -> 0.675 | G58: =G57*$D$23 -> 0.81 | H58: =H57*$D$23 -> 0.81 | I58: =I57*$D$23 -> 0.81 | J58: =J57*$D$23 -> 0.81
A59: Regulatory loss (expected) | C59: 0 | D59: =$B$9*$B$12*$B$8*D$28*(1-D58) -> 10.228351 | E59: =$B$9*$B$12*$B$8*E$28*(1-E58) -> 8.0657855 | F59: =$B$9*$B$12*$B$8*F$28*(1-F58) -> 5.8126259 | G59: =$B$9*$B$12*$B$8*G$28*(1-G58) -> 3.4661135 | H59: =$B$9*$B$12*$B$8*H$28*(1-H58) -> 3.5354358 | I59: =$B$9*$B$12*$B$8*I$28*(1-I58) -> 3.6061445 | J59: =$B$9*$B$12*$B$8*J$28*(1-J58) -> 3.6782674
A60: Supplier substitution cost | C60: 0 | D60: =D$32*$B$8*(1-D57)*$B$14*$B$13 -> 2.3049001 | E60: =E$32*$B$8*(1-E57)*$B$14*$B$13 -> 1.7098168 | F60: =F$32*$B$8*(1-F57)*$B$14*$B$13 -> 1.0900082 | G60: =G$32*$B$8*(1-G57)*$B$14*$B$13 -> 0.44472334 | H60: =H$32*$B$8*(1-H57)*$B$14*$B$13 -> 0.45361781 | I60: =I$32*$B$8*(1-I57)*$B$14*$B$13 -> 0.46269016 | J60: =J$32*$B$8*(1-J57)*$B$14*$B$13 -> 0.47194397
A61: Reputational / controversy loss (expected) | C61: 0 | D61: =$B$10*$B$11*$B$6*D$28*(1-D58) -> 5.1141756 | E61: =$B$10*$B$11*$B$6*E$28*(1-E58) -> 4.0328928 | F61: =$B$10*$B$11*$B$6*F$28*(1-F58) -> 2.9063129 | G61: =$B$10*$B$11*$B$6*G$28*(1-G58) -> 1.7330568 | H61: =$B$10*$B$11*$B$6*H$28*(1-H58) -> 1.7677179 | I61: =$B$10*$B$11*$B$6*I$28*(1-I58) -> 1.8030723 | J61: =$B$10*$B$11*$B$6*J$28*(1-J58) -> 1.8391337
A62: Programme opex | C62: 0 | D62: =$F$23*D$27 -> 4.08 | E62: =$F$23*E$27 -> 4.1616 | F62: =$F$23*F$27 -> 4.244832 | G62: =$F$23*G$27 -> 4.3297286 | H62: =$F$23*H$27 -> 4.4163232 | I62: =$F$23*I$27 -> 4.5046497 | J62: =$F$23*J$27 -> 4.5947427
A63: Programme capex | C63: =$E$23 -> 12 | D63: 0 | E63: 0 | F63: 0 | G63: 0 | H63: 0 | I63: 0 | J63: 0
A64: Total cost (losses + programme) | C64: =SUM(C59:C63) -> 12 | D64: =SUM(D59:D63) -> 21.727427 | E64: =SUM(E59:E63) -> 17.970095 | F64: =SUM(F59:F63) -> 14.053779 | G64: =SUM(G59:G63) -> 9.9736223 | H64: =SUM(H59:H63) -> 10.173095 | I64: =SUM(I59:I63) -> 10.376557 | J64: =SUM(J59:J63) -> 10.584088
A65: PV of total cost | C65: =C64*C$30 -> 12 | D65: =D64*D$30 -> 20.117988 | E65: =E64*E$30 -> 15.40646 | F65: =F64*F$30 -> 11.156343 | G65: =G64*G$30 -> 7.3309101 | H65: =H64*H$30 -> 6.9236373 | I65: =I64*I$30 -> 6.5389908 | J65: =J64*J$30 -> 6.1757135
A68: Summary (PV at year 0, USD m)
A69: Option | B69: PV expected losses | C69: PV programme cost | D69: PV total cost | E69: Benefit vs status quo (NPV) | F69: PV avoided losses | G69: Benefit / programme cost | H69: Break-even p_reg multiplier | I69: Discounted payback (yr)
A70: Status quo | B70: =SUMPRODUCT((C37:J37+C38:J38+C39:J39)*$C$30:$J$30) -> 132.32893 | C70: =SUMPRODUCT((C40:J40+C41:J41)*$C$30:$J$30) -> 0 | D70: =SUM(C43:J43) -> 132.32893
A71: Central database | B71: =SUMPRODUCT((C48:J48+C49:J49+C50:J50)*$C$30:$J$30) -> 66.901577 | C71: =SUMPRODUCT((C51:J51+C52:J52)*$C$30:$J$30) -> 21.0145 | D71: =SUM(C54:J54) -> 87.916077 | E71: =$D$70-D71 -> 44.412856 | F71: =$B$70-B71 -> 65.427356 | G71: =IF(C71=0,0,F71/C71) -> 3.1134386 | H71: =IFERROR(MAX(0,1-E71/SUMPRODUCT((C37:J37-C48:J48)*$C$30:$J$30)),0) -> 0 | I71: =IF(MIN(C77:J77)=99,"> 7",MIN(C77:J77)) -> 2
A72: Permissioned blockchain | B72: =SUMPRODUCT((C59:J59+C60:J60+C61:J61)*$C$30:$J$30) -> 51.226842 | C72: =SUMPRODUCT((C62:J62+C63:J63)*$C$30:$J$30) -> 34.4232 | D72: =SUM(C65:J65) -> 85.650043 | E72: =$D$70-D72 -> 46.67889 | F72: =$B$70-B72 -> 81.102091 | G72: =IF(C72=0,0,F72/C72) -> 2.3560299 | H72: =IFERROR(MAX(0,1-E72/SUMPRODUCT((C37:J37-C59:J59)*$C$30:$J$30)),0) -> 0.0089094669 | I72: =IF(MIN(C79:J79)=99,"> 7",MIN(C79:J79)) -> 3
A75: Cumulative discounted net benefit vs status quo
A76: Central database — cumulative | C76: =(C42-C53)*C$30 -> -7 | D76: =(D42-D53)*D$30+C76 -> -4.0984247 | E76: =(E42-E53)*E$30+D76 -> 2.2593105 | F76: =(F42-F53)*F$30+E76 -> 11.680232 | G76: =(G42-G53)*G$30+F76 -> 20.57777 | H76: =(H42-H53)*H$30+G76 -> 28.980999 | I76: =(I42-I53)*I$30+H76 -> 36.917383 | J76: =(J42-J53)*J$30+I76 -> 44.412856
A77: payback flag (year if cumulative ≥ 0, else 99) | C77: =IF(C76>=0,C$26,99) -> 99 | D77: =IF(D76>=0,D$26,99) -> 99 | E77: =IF(E76>=0,E$26,99) -> 2 | F77: =IF(F76>=0,F$26,99) -> 3 | G77: =IF(G76>=0,G$26,99) -> 4 | H77: =IF(H76>=0,H$26,99) -> 5 | I77: =IF(I76>=0,I$26,99) -> 6 | J77: =IF(J76>=0,J$26,99) -> 7
A78: Permissioned blockchain — cumulative | C78: =(C42-C64)*C$30 -> -12 | D78: =(D42-D64)*D$30+C78 -> -9.8236991 | E78: =(E42-E64)*E$30+D78 -> -4.1744421 | F78: =(F42-F64)*F$30+E78 -> 4.5551701 | G78: =(G42-G64)*G$30+F78 -> 16.00544 | H78: =(H42-H64)*H$30+G78 -> 26.819583 | I78: =(I42-I64)*I$30+H78 -> 37.032941 | J78: =(J42-J64)*J$30+I78 -> 46.67889
A79: payback flag (year if cumulative ≥ 0, else 99) | C79: =IF(C78>=0,C$26,99) -> 99 | D79: =IF(D78>=0,D$26,99) -> 99 | E79: =IF(E78>=0,E$26,99) -> 99 | F79: =IF(F78>=0,F$26,99) -> 3 | G79: =IF(G78>=0,G$26,99) -> 4 | H79: =IF(H78>=0,H$26,99) -> 5 | I79: =IF(I78>=0,I$26,99) -> 6 | J79: =IF(J78>=0,J$26,99) -> 7
A81: Blockchain minus central database (NPV) | E81: =E72-E71 -> 2.2660343
A82: Break-even p_reg multiplier: the factor on the regulatory-event probability at which the option's NPV is zero (0 = pays back even with no regulatory risk, because substitution and reputation benefits already cover costs).

Sheet ROI_WIL
A1: Wilmar — traceability programme: status quo vs central database vs permissioned blockchain (USD m)
A2: Pure calculation sheet: all inputs are green links to 'Assumptions'. Change the scenario on Assumptions!B13. Year 0 = build year.
A4: Revenue, USD m (FY2025) | B4: =Assumptions!D26 -> 70415.7 | D4: Active scenario: | E4: =Assumptions!B13 -> Base
A5: COGS, USD m (FY2025) | B5: =Assumptions!D27 -> 64619.9
A6: a palm-linked revenue share | B6: =Assumptions!D28 -> 0.4
A7: ps palm spend / COGS | B7: =Assumptions!D29 -> 0.3
A8: eu EU-regulated revenue share | B8: =Assumptions!D30 -> 0.08
A9: p_reg (scenario-adjusted) | B9: =Assumptions!D31*Assumptions!$B$19 -> 0.05
A10: p_ctrv (scenario-adjusted) | B10: =Assumptions!D32*Assumptions!$C$19 -> 0.15
A11: rev_loss | B11: =Assumptions!D33 -> 0.01
A12: Realised fine rate | B12: =Assumptions!$B$7 -> 0.02
A13: Substitution premium π (scenario-adjusted) | B13: =Assumptions!$B$8*Assumptions!$D$19 -> 0.06
A14: Share excluded / re-sourced q | B14: =Assumptions!$B$9 -> 0.3
A15: Discount rate | B15: =Assumptions!$B$5 -> 0.08
A16: Growth | B16: =Assumptions!$B$6 -> 0.02
A17: CPO price level × (scenario) | B17: =Assumptions!$E$19 -> 1
A18: Baseline coverage c0 | B18: =Assumptions!$B$10 -> 0.3
A20: Option design | B20: cmax | C20: Ramp (yrs) | D20: eff | E20: Capex | F20: Opex / yr
A21: Status quo | B21: =Assumptions!B41 -> 0.3 | C21: =Assumptions!B42 -> 1 | D21: =Assumptions!B43 -> 0.6 | E21: 0 | F21: 0
A22: Central database | B22: =Assumptions!C41 -> 0.8 | C22: =Assumptions!C42 -> 3 | D22: =Assumptions!C43 -> 0.8 | E22: =Assumptions!D34 -> 25 | F22: =Assumptions!D35 -> 10
A23: Permissioned blockchain | B23: =Assumptions!D41 -> 0.9 | C23: =Assumptions!D42 -> 4 | D23: =Assumptions!D43 -> 0.9 | E23: =Assumptions!D36 -> 40 | F23: =Assumptions!D37 -> 14
A26: Year | B26: Year | C26: 0 | D26: 1 | E26: 2 | F26: 3 | G26: 4 | H26: 5 | I26: 6 | J26: 7
A27: Growth factor | C27: =(1+$B$16)^C$26 -> 1 | D27: =(1+$B$16)^D$26 -> 1.02 | E27: =(1+$B$16)^E$26 -> 1.0404 | F27: =(1+$B$16)^F$26 -> 1.061208 | G27: =(1+$B$16)^G$26 -> 1.0824322 | H27: =(1+$B$16)^H$26 -> 1.1040808 | I27: =(1+$B$16)^I$26 -> 1.1261624 | J27: =(1+$B$16)^J$26 -> 1.1486857
A28: Revenue | C28: =$B$4*C27 -> 70415.7 | D28: =$B$4*D27 -> 71824.014 | E28: =$B$4*E27 -> 73260.494 | F28: =$B$4*F27 -> 74725.704 | G28: =$B$4*G27 -> 76220.218 | H28: =$B$4*H27 -> 77744.623 | I28: =$B$4*I27 -> 79299.515 | J28: =$B$4*J27 -> 80885.505
A29: COGS | C29: =$B$5*C27 -> 64619.9 | D29: =$B$5*D27 -> 65912.298 | E29: =$B$5*E27 -> 67230.544 | F29: =$B$5*F27 -> 68575.155 | G29: =$B$5*G27 -> 69946.658 | H29: =$B$5*H27 -> 71345.591 | I29: =$B$5*I27 -> 72772.503 | J29: =$B$5*J27 -> 74227.953
A30: Discount factor | C30: =1/(1+$B$15)^C$26 -> 1 | D30: =1/(1+$B$15)^D$26 -> 0.92592593 | E30: =1/(1+$B$15)^E$26 -> 0.85733882 | F30: =1/(1+$B$15)^F$26 -> 0.79383224 | G30: =1/(1+$B$15)^G$26 -> 0.73502985 | H30: =1/(1+$B$15)^H$26 -> 0.6805832 | I30: =1/(1+$B$15)^I$26 -> 0.63016963 | J30: =1/(1+$B$15)^J$26 -> 0.5834904
A31: CPO price index | C31: =1 -> 1 | D31: =$B$17 -> 1 | E31: =$B$17 -> 1 | F31: =$B$17 -> 1 | G31: =$B$17 -> 1 | H31: =$B$17 -> 1 | I31: =$B$17 -> 1 | J31: =$B$17 -> 1
A32: Palm-derived spend | C32: =C29*$B$7*C31 -> 19385.97 | D32: =D29*$B$7*D31 -> 19773.689 | E32: =E29*$B$7*E31 -> 20169.163 | F32: =F29*$B$7*F31 -> 20572.546 | G32: =G29*$B$7*G31 -> 20983.997 | H32: =H29*$B$7*H31 -> 21403.677 | I32: =I29*$B$7*I31 -> 21831.751 | J32: =J29*$B$7*J31 -> 22268.386
A34: Option: Status quo
A35: Traceable coverage | C35: =$B$18 -> 0.3 | D35: =$B$18+($B$21-$B$18)*MIN(1,D$26/$C$21) -> 0.3 | E35: =$B$18+($B$21-$B$18)*MIN(1,E$26/$C$21) -> 0.3 | F35: =$B$18+($B$21-$B$18)*MIN(1,F$26/$C$21) -> 0.3 | G35: =$B$18+($B$21-$B$18)*MIN(1,G$26/$C$21) -> 0.3 | H35: =$B$18+($B$21-$B$18)*MIN(1,H$26/$C$21) -> 0.3 | I35: =$B$18+($B$21-$B$18)*MIN(1,I$26/$C$21) -> 0.3 | J35: =$B$18+($B$21-$B$18)*MIN(1,J$26/$C$21) -> 0.3
A36: Mitigation (coverage × eff) | C36: =C35*$D$21 -> 0.18 | D36: =D35*$D$21 -> 0.18 | E36: =E35*$D$21 -> 0.18 | F36: =F35*$D$21 -> 0.18 | G36: =G35*$D$21 -> 0.18 | H36: =H35*$D$21 -> 0.18 | I36: =I35*$D$21 -> 0.18 | J36: =J35*$D$21 -> 0.18
A37: Regulatory loss (expected) | C37: 0 | D37: =$B$9*$B$12*$B$8*D$28*(1-D36) -> 4.7116553 | E37: =$B$9*$B$12*$B$8*E$28*(1-E36) -> 4.8058884 | F37: =$B$9*$B$12*$B$8*F$28*(1-F36) -> 4.9020062 | G37: =$B$9*$B$12*$B$8*G$28*(1-G36) -> 5.0000463 | H37: =$B$9*$B$12*$B$8*H$28*(1-H36) -> 5.1000472 | I37: =$B$9*$B$12*$B$8*I$28*(1-I36) -> 5.2020482 | J37: =$B$9*$B$12*$B$8*J$28*(1-J36) -> 5.3060892
A38: Supplier substitution cost | C38: 0 | D38: =D$32*$B$8*(1-D35)*$B$14*$B$13 -> 19.931879 | E38: =E$32*$B$8*(1-E35)*$B$14*$B$13 -> 20.330516 | F38: =F$32*$B$8*(1-F35)*$B$14*$B$13 -> 20.737127 | G38: =G$32*$B$8*(1-G35)*$B$14*$B$13 -> 21.151869 | H38: =H$32*$B$8*(1-H35)*$B$14*$B$13 -> 21.574907 | I38: =I$32*$B$8*(1-I35)*$B$14*$B$13 -> 22.006405 | J38: =J$32*$B$8*(1-J35)*$B$14*$B$13 -> 22.446533
A39: Reputational / controversy loss (expected) | C39: 0 | D39: =$B$10*$B$11*$B$6*D$28*(1-D36) -> 35.337415 | E39: =$B$10*$B$11*$B$6*E$28*(1-E36) -> 36.044163 | F39: =$B$10*$B$11*$B$6*F$28*(1-F36) -> 36.765046 | G39: =$B$10*$B$11*$B$6*G$28*(1-G36) -> 37.500347 | H39: =$B$10*$B$11*$B$6*H$28*(1-H36) -> 38.250354 | I39: =$B$10*$B$11*$B$6*I$28*(1-I36) -> 39.015361 | J39: =$B$10*$B$11*$B$6*J$28*(1-J36) -> 39.795669
A40: Programme opex | C40: 0 | D40: =$F$21*D$27 -> 0 | E40: =$F$21*E$27 -> 0 | F40: =$F$21*F$27 -> 0 | G40: =$F$21*G$27 -> 0 | H40: =$F$21*H$27 -> 0 | I40: =$F$21*I$27 -> 0 | J40: =$F$21*J$27 -> 0
A41: Programme capex | C41: =$E$21 -> 0 | D41: 0 | E41: 0 | F41: 0 | G41: 0 | H41: 0 | I41: 0 | J41: 0
A42: Total cost (losses + programme) | C42: =SUM(C37:C41) -> 0 | D42: =SUM(D37:D41) -> 59.980949 | E42: =SUM(E37:E41) -> 61.180568 | F42: =SUM(F37:F41) -> 62.404179 | G42: =SUM(G37:G41) -> 63.652263 | H42: =SUM(H37:H41) -> 64.925308 | I42: =SUM(I37:I41) -> 66.223814 | J42: =SUM(J37:J41) -> 67.548291
A43: PV of total cost | C43: =C42*C$30 -> 0 | D43: =D42*D$30 -> 55.537916 | E43: =E42*E$30 -> 52.452476 | F43: =F42*F$30 -> 49.53845 | G43: =G42*G$30 -> 46.786314 | H43: =H42*H$30 -> 44.187074 | I43: =I42*I$30 -> 41.732236 | J43: =J42*J$30 -> 39.413779
A45: Option: Central database
A46: Traceable coverage | C46: =$B$18 -> 0.3 | D46: =$B$18+($B$22-$B$18)*MIN(1,D$26/$C$22) -> 0.46666667 | E46: =$B$18+($B$22-$B$18)*MIN(1,E$26/$C$22) -> 0.63333333 | F46: =$B$18+($B$22-$B$18)*MIN(1,F$26/$C$22) -> 0.8 | G46: =$B$18+($B$22-$B$18)*MIN(1,G$26/$C$22) -> 0.8 | H46: =$B$18+($B$22-$B$18)*MIN(1,H$26/$C$22) -> 0.8 | I46: =$B$18+($B$22-$B$18)*MIN(1,I$26/$C$22) -> 0.8 | J46: =$B$18+($B$22-$B$18)*MIN(1,J$26/$C$22) -> 0.8
A47: Mitigation (coverage × eff) | C47: =C46*$D$22 -> 0.24 | D47: =D46*$D$22 -> 0.37333333 | E47: =E46*$D$22 -> 0.50666667 | F47: =F46*$D$22 -> 0.64 | G47: =G46*$D$22 -> 0.64 | H47: =H46*$D$22 -> 0.64 | I47: =I46*$D$22 -> 0.64 | J47: =J46*$D$22 -> 0.64
A48: Regulatory loss (expected) | C48: 0 | D48: =$B$9*$B$12*$B$8*D$28*(1-D47) -> 3.6007772 | E48: =$B$9*$B$12*$B$8*E$28*(1-E47) -> 2.8913475 | F48: =$B$9*$B$12*$B$8*F$28*(1-F47) -> 2.1521003 | G48: =$B$9*$B$12*$B$8*G$28*(1-G47) -> 2.1951423 | H48: =$B$9*$B$12*$B$8*H$28*(1-H47) -> 2.2390451 | I48: =$B$9*$B$12*$B$8*I$28*(1-I47) -> 2.283826 | J48: =$B$9*$B$12*$B$8*J$28*(1-J47) -> 2.3295026
A49: Supplier substitution cost | C49: 0 | D49: =D$32*$B$8*(1-D46)*$B$14*$B$13 -> 15.186193 | E49: =E$32*$B$8*(1-E46)*$B$14*$B$13 -> 10.649318 | F49: =F$32*$B$8*(1-F46)*$B$14*$B$13 -> 5.9248934 | G49: =G$32*$B$8*(1-G46)*$B$14*$B$13 -> 6.0433912 | H49: =H$32*$B$8*(1-H46)*$B$14*$B$13 -> 6.1642591 | I49: =I$32*$B$8*(1-I46)*$B$14*$B$13 -> 6.2875443 | J49: =J$32*$B$8*(1-J46)*$B$14*$B$13 -> 6.4132951
A50: Reputational / controversy loss (expected) | C50: 0 | D50: =$B$10*$B$11*$B$6*D$28*(1-D47) -> 27.005829 | E50: =$B$10*$B$11*$B$6*E$28*(1-E47) -> 21.685106 | F50: =$B$10*$B$11*$B$6*F$28*(1-F47) -> 16.140752 | G50: =$B$10*$B$11*$B$6*G$28*(1-G47) -> 16.463567 | H50: =$B$10*$B$11*$B$6*H$28*(1-H47) -> 16.792838 | I50: =$B$10*$B$11*$B$6*I$28*(1-I47) -> 17.128695 | J50: =$B$10*$B$11*$B$6*J$28*(1-J47) -> 17.471269
A51: Programme opex | C51: 0 | D51: =$F$22*D$27 -> 10.2 | E51: =$F$22*E$27 -> 10.404 | F51: =$F$22*F$27 -> 10.61208 | G51: =$F$22*G$27 -> 10.824322 | H51: =$F$22*H$27 -> 11.040808 | I51: =$F$22*I$27 -> 11.261624 | J51: =$F$22*J$27 -> 11.486857
A52: Programme capex | C52: =$E$22 -> 25 | D52: 0 | E52: 0 | F52: 0 | G52: 0 | H52: 0 | I52: 0 | J52: 0
A53: Total cost (losses + programme) | C53: =SUM(C48:C52) -> 25 | D53: =SUM(D48:D52) -> 55.9928 | E53: =SUM(E48:E52) -> 45.629772 | F53: =SUM(F48:F52) -> 34.829826 | G53: =SUM(G48:G52) -> 35.526422 | H53: =SUM(H48:H52) -> 36.236951 | I53: =SUM(I48:I52) -> 36.96169 | J53: =SUM(J48:J52) -> 37.700924
A54: PV of total cost | C54: =C53*C$30 -> 25 | D54: =D53*D$30 -> 51.845185 | E54: =E53*E$30 -> 39.120175 | F54: =F53*F$30 -> 27.649039 | G54: =G53*G$30 -> 26.112981 | H54: =H53*H$30 -> 24.66226 | I54: =I53*I$30 -> 23.292134 | J54: =J53*J$30 -> 21.998127
A56: Option: Permissioned blockchain
A57: Traceable coverage | C57: =$B$18 -> 0.3 | D57: =$B$18+($B$23-$B$18)*MIN(1,D$26/$C$23) -> 0.45 | E57: =$B$18+($B$23-$B$18)*MIN(1,E$26/$C$23) -> 0.6 | F57: =$B$18+($B$23-$B$18)*MIN(1,F$26/$C$23) -> 0.75 | G57: =$B$18+($B$23-$B$18)*MIN(1,G$26/$C$23) -> 0.9 | H57: =$B$18+($B$23-$B$18)*MIN(1,H$26/$C$23) -> 0.9 | I57: =$B$18+($B$23-$B$18)*MIN(1,I$26/$C$23) -> 0.9 | J57: =$B$18+($B$23-$B$18)*MIN(1,J$26/$C$23) -> 0.9
A58: Mitigation (coverage × eff) | C58: =C57*$D$23 -> 0.27 | D58: =D57*$D$23 -> 0.405 | E58: =E57*$D$23 -> 0.54 | F58: =F57*$D$23 -> 0.675 | G58: =G57*$D$23 -> 0.81 | H58: =H57*$D$23 -> 0.81 | I58: =I57*$D$23 -> 0.81 | J58: =J57*$D$23 -> 0.81
A59: Regulatory loss (expected) | C59: 0 | D59: =$B$9*$B$12*$B$8*D$28*(1-D58) -> 3.4188231 | E59: =$B$9*$B$12*$B$8*E$28*(1-E58) -> 2.6959862 | F59: =$B$9*$B$12*$B$8*F$28*(1-F58) -> 1.9428683 | G59: =$B$9*$B$12*$B$8*G$28*(1-G58) -> 1.1585473 | H59: =$B$9*$B$12*$B$8*H$28*(1-H58) -> 1.1817183 | I59: =$B$9*$B$12*$B$8*I$28*(1-I58) -> 1.2053526 | J59: =$B$9*$B$12*$B$8*J$28*(1-J58) -> 1.2294597
A60: Supplier substitution cost | C60: 0 | D60: =D$32*$B$8*(1-D57)*$B$14*$B$13 -> 15.660762 | E60: =E$32*$B$8*(1-E57)*$B$14*$B$13 -> 11.617438 | F60: =F$32*$B$8*(1-F57)*$B$14*$B$13 -> 7.4061167 | G60: =G$32*$B$8*(1-G57)*$B$14*$B$13 -> 3.0216956 | H60: =H$32*$B$8*(1-H57)*$B$14*$B$13 -> 3.0821295 | I60: =I$32*$B$8*(1-I57)*$B$14*$B$13 -> 3.1437721 | J60: =J$32*$B$8*(1-J57)*$B$14*$B$13 -> 3.2066476
A61: Reputational / controversy loss (expected) | C61: 0 | D61: =$B$10*$B$11*$B$6*D$28*(1-D58) -> 25.641173 | E61: =$B$10*$B$11*$B$6*E$28*(1-E58) -> 20.219896 | F61: =$B$10*$B$11*$B$6*F$28*(1-F58) -> 14.571512 | G61: =$B$10*$B$11*$B$6*G$28*(1-G58) -> 8.6891049 | H61: =$B$10*$B$11*$B$6*H$28*(1-H58) -> 8.862887 | I61: =$B$10*$B$11*$B$6*I$28*(1-I58) -> 9.0401447 | J61: =$B$10*$B$11*$B$6*J$28*(1-J58) -> 9.2209476
A62: Programme opex | C62: 0 | D62: =$F$23*D$27 -> 14.28 | E62: =$F$23*E$27 -> 14.5656 | F62: =$F$23*F$27 -> 14.856912 | G62: =$F$23*G$27 -> 15.15405 | H62: =$F$23*H$27 -> 15.457131 | I62: =$F$23*I$27 -> 15.766274 | J62: =$F$23*J$27 -> 16.081599
A63: Programme capex | C63: =$E$23 -> 40 | D63: 0 | E63: 0 | F63: 0 | G63: 0 | H63: 0 | I63: 0 | J63: 0
A64: Total cost (losses + programme) | C64: =SUM(C59:C63) -> 40 | D64: =SUM(D59:D63) -> 59.000758 | E64: =SUM(E59:E63) -> 49.098921 | F64: =SUM(F59:F63) -> 38.777409 | G64: =SUM(G59:G63) -> 28.023398 | H64: =SUM(H59:H63) -> 28.583866 | I64: =SUM(I59:I63) -> 29.155543 | J64: =SUM(J59:J63) -> 29.738654
A65: PV of total cost | C65: =C64*C$30 -> 40 | D65: =D64*D$30 -> 54.630332 | E65: =E64*E$30 -> 42.094411 | F65: =F64*F$30 -> 30.782758 | G65: =G64*G$30 -> 20.598034 | H65: =H64*H$30 -> 19.453699 | I65: =I64*I$30 -> 18.372938 | J65: =J64*J$30 -> 17.352219
A68: Summary (PV at year 0, USD m)
A69: Option | B69: PV expected losses | C69: PV programme cost | D69: PV total cost | E69: Benefit vs status quo (NPV) | F69: PV avoided losses | G69: Benefit / programme cost | H69: Break-even p_reg multiplier | I69: Discounted payback (yr)
A70: Status quo | B70: =SUMPRODUCT((C37:J37+C38:J38+C39:J39)*$C$30:$J$30) -> 329.64824 | C70: =SUMPRODUCT((C40:J40+C41:J41)*$C$30:$J$30) -> 0 | D70: =SUM(C43:J43) -> 329.64824
A71: Central database | B71: =SUMPRODUCT((C48:J48+C49:J49+C50:J50)*$C$30:$J$30) -> 158.6219 | C71: =SUMPRODUCT((C51:J51+C52:J52)*$C$30:$J$30) -> 81.058001 | D71: =SUM(C54:J54) -> 239.6799 | E71: =$D$70-D71 -> 89.968344 | F71: =$B$70-B71 -> 171.02634 | G71: =IF(C71=0,0,F71/C71) -> 2.1099255 | H71: =IFERROR(MAX(0,1-E71/SUMPRODUCT((C37:J37-C48:J48)*$C$30:$J$30)),0) -> 0 | I71: =IF(MIN(C77:J77)=99,"> 7",MIN(C77:J77)) -> 3
A72: Permissioned blockchain | B72: =SUMPRODUCT((C59:J59+C60:J60+C61:J61)*$C$30:$J$30) -> 124.80319 | C72: =SUMPRODUCT((C62:J62+C63:J63)*$C$30:$J$30) -> 118.4812 | D72: =SUM(C65:J65) -> 243.28439 | E72: =$D$70-D72 -> 86.363854 | F72: =$B$70-B72 -> 204.84506 | G72: =IF(C72=0,0,F72/C72) -> 1.7289245 | H72: =IFERROR(MAX(0,1-E72/SUMPRODUCT((C37:J37-C59:J59)*$C$30:$J$30)),0) -> 0 | I72: =IF(MIN(C79:J79)=99,"> 7",MIN(C79:J79)) -> 4
A75: Cumulative discounted net benefit vs status quo
A76: Central database — cumulative | C76: =(C42-C53)*C$30 -> -25 | D76: =(D42-D53)*D$30+C76 -> -21.307269 | E76: =(E42-E53)*E$30+D76 -> -7.9749681 | F76: =(F42-F53)*F$30+E76 -> 13.914443 | G76: =(G42-G53)*G$30+F76 -> 34.587776 | H76: =(H42-H53)*H$30+G76 -> 54.11259 | I76: =(I42-I53)*I$30+H76 -> 72.552692 | J76: =(J42-J53)*J$30+I76 -> 89.968344
A77: payback flag (year if cumulative ≥ 0, else 99) | C77: =IF(C76>=0,C$26,99) -> 99 | D77: =IF(D76>=0,D$26,99) -> 99 | E77: =IF(E76>=0,E$26,99) -> 99 | F77: =IF(F76>=0,F$26,99) -> 3 | G77: =IF(G76>=0,G$26,99) -> 4 | H77: =IF(H76>=0,H$26,99) -> 5 | I77: =IF(I76>=0,I$26,99) -> 6 | J77: =IF(J76>=0,J$26,99) -> 7
A78: Permissioned blockchain — cumulative | C78: =(C42-C64)*C$30 -> -40 | D78: =(D42-D64)*D$30+C78 -> -39.092416 | E78: =(E42-E64)*E$30+D78 -> -28.73435 | F78: =(F42-F64)*F$30+E78 -> -9.9786584 | G78: =(G42-G64)*G$30+F78 -> 16.209621 | H78: =(H42-H64)*H$30+G78 -> 40.942996 | I78: =(I42-I64)*I$30+H78 -> 64.302295 | J78: =(J42-J64)*J$30+I78 -> 86.363854
A79: payback flag (year if cumulative ≥ 0, else 99) | C79: =IF(C78>=0,C$26,99) -> 99 | D79: =IF(D78>=0,D$26,99) -> 99 | E79: =IF(E78>=0,E$26,99) -> 99 | F79: =IF(F78>=0,F$26,99) -> 99 | G79: =IF(G78>=0,G$26,99) -> 4 | H79: =IF(H78>=0,H$26,99) -> 5 | I79: =IF(I78>=0,I$26,99) -> 6 | J79: =IF(J78>=0,J$26,99) -> 7
A81: Blockchain minus central database (NPV) | E81: =E72-E71 -> -3.6044897
A82: Break-even p_reg multiplier: the factor on the regulatory-event probability at which the option's NPV is zero (0 = pays back even with no regulatory risk, because substitution and reputation benefits already cover costs).

Sheet MC_Results
A1: Monte Carlo results — 20,000 draws per cell, seed 42 (STATIC values from palm_oil_traceability_model.py)
A2: NPV benefit vs status quo, USD m. Same random world is applied to every option (common random numbers). Re-run the script after changing assumptions; these cells do not update by themselves.
A4: Firm | B4: Regime | C4: Option | D4: Mean | E4: 5th pct | F4: Median | G4: 95th pct | H4: P(NPV > 0) | I4: P(blockchain beats database) | J4: Mean (blockchain − database)
A5: Unilever | B5: Base | C5: Central database | D5: 19.372726 | E5: -9.5603664 | F5: 16.348099 | G5: 58.157002 | H5: 0.841
A6: Unilever | B6: Base | C6: Permissioned blockchain | D6: 9.7040342 | E6: -30.156877 | F6: 7.5591098 | G6: 57.453575 | H6: 0.62965 | I6: 0.3198 | J6: -9.6686918
A7: Unilever | B7: Adverse | C7: Central database | D7: 52.375399 | E7: 5.2664951 | F7: 45.141537 | G7: 123.21217 | H7: 0.97385
A8: Unilever | B8: Adverse | C8: Permissioned blockchain | D8: 47.697135 | E8: -9.8415459 | F8: 39.845845 | G8: 132.05336 | H8: 0.90045 | I8: 0.41445 | J8: -4.6782645
A9: Unilever | B9: Severe | C9: Central database | D9: 125.29041 | E9: 36.898822 | F9: 109.9598 | G9: 264.14103 | H9: 0.99905
A10: Unilever | B10: Severe | C10: Permissioned blockchain | D10: 130.58927 | E10: 28.771338 | F10: 112.87718 | G10: 294.04286 | H10: 0.9934 | I10: 0.5195 | J10: 5.2988613
A11: Unilever | B11: Mixed | C11: Central database | D11: 40.85191 | E11: -12.698209 | F11: 17.989507 | G11: 171.75883 | H11: 0.78925
A12: Unilever | B12: Mixed | C12: Permissioned blockchain | D12: 34.141199 | E12: -32.663807 | F12: 9.7294366 | G12: 184.96922 | H12: 0.6236 | I12: 0.35255 | J12: -6.7107113
A13: Nestlé | B13: Base | C13: Central database | D13: 45.168205 | E13: 3.1620487 | F13: 38.042643 | G13: 111.44646 | H13: 0.9684
A14: Nestlé | B14: Base | C14: Permissioned blockchain | D14: 40.549164 | E14: -11.413816 | F14: 32.584989 | G14: 119.09716 | H14: 0.8793 | I14: 0.4016 | J14: -4.6190411
A15: Nestlé | B15: Adverse | C15: Central database | D15: 98.89534 | E15: 22.601235 | F15: 83.32232 | G15: 228.02576 | H15: 0.99735
A16: Nestlé | B16: Adverse | C16: Permissioned blockchain | D16: 102.9453 | E16: 13.433429 | F16: 84.896234 | G16: 255.02897 | H16: 0.98255 | I16: 0.50665 | J16: 4.0499622
A17: Nestlé | B17: Severe | C17: Central database | D17: 213.17421 | E17: 64.121565 | F17: 181.42898 | G17: 468.96869 | H17: 0.99995
A18: Nestlé | B18: Severe | C18: Permissioned blockchain | D18: 234.55849 | E18: 63.602165 | F18: 197.11196 | G18: 533.94533 | H18: 0.99955 | I18: 0.59365 | J18: 21.384286
A19: Nestlé | B19: Mixed | C19: Central database | D19: 79.095657 | E19: -2.1508621 | F19: 39.527506 | G19: 293.53315 | H19: 0.9332
A20: Nestlé | B20: Mixed | C20: Permissioned blockchain | D20: 79.29578 | E20: -16.905702 | F20: 35.635874 | G20: 330.5217 | H20: 0.8275 | I20: 0.42045 | J20: 0.20012276
A21: Wilmar | B21: Base | C21: Central database | D21: 78.11824 | E21: -16.078219 | F21: 70.683213 | G21: 198.13272 | H21: 0.90545
A22: Wilmar | B22: Base | C22: Permissioned blockchain | D22: 53.540337 | E22: -68.233592 | F22: 49.114619 | G22: 190.02262 | H22: 0.7586 | I22: 0.3573 | J22: -24.577903
A23: Wilmar | B23: Adverse | C23: Central database | D23: 165.87761 | E23: 31.72418 | F23: 153.3023 | G23: 344.15472 | H23: 0.98625
A24: Wilmar | B24: Adverse | C24: Permissioned blockchain | D24: 151.11388 | E24: -5.5582086 | F24: 139.43254 | G24: 347.5392 | H24: 0.943 | I24: 0.42325 | J24: -14.763726
A25: Wilmar | B25: Severe | C25: Central database | D25: 387.76644 | E25: 145.63184 | F25: 361.20436 | G25: 721.87105 | H25: 0.99975
A26: Wilmar | B26: Severe | C26: Permissioned blockchain | D26: 392.60604 | E26: 130.07827 | F26: 365.01646 | G26: 748.23575 | H26: 0.99735 | I26: 0.50675 | J26: 4.8396058
A27: Wilmar | B27: Mixed | C27: Central database | D27: 142.56094 | E27: -22.724724 | F27: 81.467556 | G27: 517.52564 | H27: 0.88505
A28: Wilmar | B28: Mixed | C28: Permissioned blockchain | D28: 123.93415 | E28: -69.946226 | F28: 60.441997 | G28: 532.38664 | H28: 0.7567 | I28: 0.38345 | J28: -18.626797
A30: Regimes: Base / Adverse / Severe use the multipliers on Assumptions; 'Mixed' draws a regime per simulation (25% benign EU enforcement, 50% base, 25% severe). Random inputs: event probabilities (log-normal), realised fine 0.5–4%, exclusion share, premium, discount rate 6–11%, baseline coverage, option coverage/ramp/effectiveness (triangular), cost overruns (log-normal), and a CPO price path (GBM, zero drift, σ = 17% estimated from only ~8 weeks of KOZ6 prints — re-estimate on 5Y data).
A33: Distribution of NPV benefit — Unilever, mixed regimes (share of simulations per bin; tails clipped at 1st/99th pct)
A34: Bin mid-point (USD m) | B34: Central database | C34: Permissioned blockchain
A35: -34.9 | B35: 0.00665 | C35: 0.08055
A36: -17.9 | B36: 0.0729 | C36: 0.1663
A37: -0.9 | B37: 0.26285 | C37: 0.22975
A38: 16.1 | B38: 0.23715 | C38: 0.15445
A39: 33.1 | B39: 0.1197 | C39: 0.0902
A40: 50.1 | B40: 0.0637 | C40: 0.0537
A41: 67.2 | B41: 0.0433 | C41: 0.03715
A42: 84.2 | B42: 0.0376 | C42: 0.0309
A43: 101.2 | B43: 0.0295 | C43: 0.02785
A44: 118.2 | B44: 0.0272 | C44: 0.02305
A45: 135.2 | B45: 0.0226 | C45: 0.0205
A46: 152.2 | B46: 0.01785 | C46: 0.0161
... A54: 288.3 | B54: 0.0106 | C54: 0.01505

Sheet Sensitivity
A1: Sensitivity & simulation grids (STATIC values from the Python model)
A2: One-at-a-time tornado, and the traceability-coverage × supplier-substitution grid required by the project brief.
A4: Unilever, permissioned blockchain — base-case NPV benefit (USD m) | D4: 15.992594
A5: Driver (low case / high case) | B5: Δ NPV, low case | C5: Δ NPV, high case | D5: Swing
A6: Regulatory event probability (x0.5 / x2) | B6: -12.172926 | C6: 24.345852 | D6: =ABS(C6-B6) -> 36.518778
A7: Realised fine rate (1% / 4%) | B7: -12.172926 | C7: 24.345852 | D7: =ABS(C7-B7) -> 36.518778
A8: Programme cost (x1.6 / x0.7) | B8: -23.53566 | C8: 11.76783 | D8: =ABS(C8-B8) -> 35.30349
A9: Controversy probability (x0.5 / x2) | B9: -10.144105 | C9: 20.28821 | D9: =ABS(C9-B9) -> 30.432315
A10: Ramp-up years (7 / 3) | B10: -13.568794 | C10: 4.8704673 | D10: =ABS(C10-B10) -> 18.439261
A11: Substitution premium (3% / 12%) | B11: -5.292316 | C11: 10.584632 | D11: =ABS(C11-B11) -> 15.876948
A12: Steady-state coverage (0.75 / 0.95) | B12: -11.790171 | C12: 3.930057 | D12: =ABS(C12-B12) -> 15.720228
A13: Baseline coverage today (45% / 15%) | B13: -7.7611657 | C13: 7.7611657 | D13: =ABS(C13-B13) -> 15.522331
A14: Blockchain effectiveness (0.75 / 0.97) | B14: -10.125014 | C14: 4.7250064 | D14: =ABS(C14-B14) -> 14.85002
A15: Share excluded / re-sourced (15% / 50%) | B15: -5.292316 | C15: 7.0564213 | D15: =ABS(C15-B15) -> 12.348737
A16: Discount rate (12% / 6%) | B16: -4.8159074 | C16: 2.8608634 | D16: =ABS(C16-B16) -> 7.6767708
A18: Regulatory probability and the realised fine rate enter the model multiplicatively, so they have identical swings — treat them as one 'expected regulatory loss' driver. The result is most sensitive to how likely and how costly enforcement is, and to programme cost and ramp-up speed — not to the blockchain-specific effectiveness number.
A24: Unilever — PV of supplier-substitution cost (USD m) by steady traceable share (rows) and share of non-traceable volume excluded (columns); base substitution premium
A25: Traceable share ↓ / excluded → | B25: 10% | C25: 20% | D25: 30% | E25: 40% | F25: 50%
A26: 20% | B26: 6.2183548 | C26: 12.43671 | D26: 18.655064 | E26: 24.873419 | F26: 31.091774
A27: 30% | B27: 5.4410605 | C27: 10.882121 | D27: 16.323181 | E27: 21.764242 | F27: 27.205302
A28: 40% | B28: 4.6637661 | C28: 9.3275322 | D28: 13.991298 | E28: 18.655064 | F28: 23.318831
A29: 50% | B29: 3.8864718 | C29: 7.7729435 | D29: 11.659415 | E29: 15.545887 | F29: 19.432359
A30: 60% | B30: 3.1091774 | C30: 6.2183548 | D30: 9.3275322 | E30: 12.43671 | F30: 15.545887
A31: 70% | B31: 2.3318831 | C31: 4.6637661 | D31: 6.9956492 | E31: 9.3275322 | F31: 11.659415
A32: 80% | B32: 1.5545887 | C32: 3.1091774 | D32: 4.6637661 | E32: 6.2183548 | F32: 7.7729435
A33: 90% | B33: 0.77729435 | C33: 1.5545887 | D33: 2.3318831 | E33: 3.1091774 | F33: 3.8864718
A34: 100% | B34: 1.7259402e-15 | C34: 3.4518803e-15 | D34: 5.1778205e-15 | E34: 6.9037607e-15 | F34: 8.6297009e-15
A37: Unilever — PV of supplier-substitution cost (USD m) by steady traceable share (rows) and share of non-traceable volume excluded (columns); severe substitution premium (×2.5)
A38: Traceable share ↓ / excluded → | B38: 10% | C38: 20% | D38: 30% | E38: 40% | F38: 50%
A39: 20% | B39: 15.545887 | C39: 31.091774 | D39: 46.637661 | E39: 62.183548 | F39: 77.729435
A40: 30% | B40: 13.602651 | C40: 27.205302 | D40: 40.807954 | E40: 54.410605 | F40: 68.013256
A41: 40% | B41: 11.659415 | C41: 23.318831 | D41: 34.978246 | E41: 46.637661 | F41: 58.297076
A42: 50% | B42: 9.7161794 | C42: 19.432359 | D42: 29.148538 | E42: 38.864718 | F42: 48.580897
A43: 60% | B43: 7.7729435 | C43: 15.545887 | D43: 23.318831 | E43: 31.091774 | F43: 38.864718
A44: 70% | B44: 5.8297076 | C44: 11.659415 | D44: 17.489123 | E44: 23.318831 | F44: 29.148538
A45: 80% | B45: 3.8864718 | C45: 7.7729435 | D45: 11.659415 | E45: 15.545887 | F45: 19.432359
A46: 90% | B46: 1.9432359 | C46: 3.8864718 | D46: 5.8297076 | E46: 7.7729435 | F46: 9.7161794
A47: 100% | B47: 4.3148504e-15 | C47: 8.6297009e-15 | D47: 1.2944551e-14 | E47: 1.7259402e-14 | F47: 2.1574252e-14
A50: Risk heat map: green = cheap to substitute (high coverage or few exclusions), red = costly. Moving traceable share from 30% to 80% removes ~70% of the substitution bill at any exclusion rate — that value comes from traceability itself, whichever technology delivers it.

Sheet Risk_Index
A1: Composite palm-oil traceability risk index (0 = low risk, 100 = high risk) — real indicators
A2: Replaces the draft's synthetic 50-supplier index. Each indicator is scaled 0–100 between a 'no-risk' value (floor) and a 'max-risk' value (cap). Edit blue cells; scores update.
A4: Indicator | B4: Source | C4: No-risk value | D4: Max-risk value | E4: Unilever (raw) | F4: Nestlé (raw) | G4: Wilmar (raw) | H4: Unilever (0–100) | I4: Nestlé (0–100) | J4: Wilmar (0–100) | K4: Weight: Base | L4: Weight: Equal | M4: Weight: Env/Social-heavy
A5: BESG ESG score gap (10 − score, 2024) | B5: ESG | C5: 0 | D5: 10 | E5: =10-ESG!J26 -> 5.18 | F5: =10-ESG!J16 -> 4.72 | G5: =10-ESG!J6 -> 3.85 | H5: =MAX(0,MIN(100,(E5-$C5)/($D5-$C5)*100)) -> 51.8 | I5: =MAX(0,MIN(100,(F5-$C5)/($D5-$C5)*100)) -> 47.2 | J5: =MAX(0,MIN(100,(G5-$C5)/($D5-$C5)*100)) -> 38.5 | K5: 0.15 | L5: 0.1 | M5: 0.15
A6: BESG Social pillar gap (10 − score, 2024) | B6: ESG | C6: 0 | D6: 10 | E6: =10-ESG!J28 -> 7.92 | F6: =10-ESG!J18 -> 5.89 | G6: =10-ESG!J8 -> 3.54 | H6: =MAX(0,MIN(100,(E6-$C6)/($D6-$C6)*100)) -> 79.2 | I6: =MAX(0,MIN(100,(F6-$C6)/($D6-$C6)*100)) -> 58.9 | J6: =MAX(0,MIN(100,(G6-$C6)/($D6-$C6)*100)) -> 35.4 | K6: 0.15 | L6: 0.1 | M6: 0.2
A7: Scope 3 intensity (kt CO2e per USD bn revenue, 2024) | B7: ESG, Fundamentals, FX | C7: 0 | D7: 3000 | E7: =ESG!J32/(Fundamentals!H6*Assumptions!$B$11/1000) -> 1788.8729 | F7: =ESG!J22/(Fundamentals!H35*Assumptions!$B$12/1000) -> 593.10946 | G7: =ESG!J12/(Fundamentals!H64*1/1000) -> 2181.6854 | H7: =MAX(0,MIN(100,(E7-$C7)/($D7-$C7)*100)) -> 59.629097 | I7: =MAX(0,MIN(100,(F7-$C7)/($D7-$C7)*100)) -> 19.770315 | J7: =MAX(0,MIN(100,(G7-$C7)/($D7-$C7)*100)) -> 72.722847 | K7: 0.15 | L7: 0.1 | M7: 0.2
A8: Suppliers with business-conduct risk, % | B8: Supply_Chain (SPLC) | C8: 0 | D8: 0.4 | E8: =Supply_Chain!D18 -> 0.13937282 | F8: =Supply_Chain!C18 -> 0.10629921 | G8: =Supply_Chain!B18 -> 0.36666667 | H8: =MAX(0,MIN(100,(E8-$C8)/($D8-$C8)*100)) -> 34.843206 | I8: =MAX(0,MIN(100,(F8-$C8)/($D8-$C8)*100)) -> 26.574803 | J8: =MAX(0,MIN(100,(G8-$C8)/($D8-$C8)*100)) -> 91.666667 | K8: 0.1 | L8: 0.1 | M8: 0.1
A9: Suppliers with high GHG vs peers, % | B9: Supply_Chain (SPLC) | C9: 0 | D9: 0.25 | E9: =Supply_Chain!D19 -> 0.20557491 | F9: =Supply_Chain!C19 -> 0.19488189 | G9: =Supply_Chain!B19 -> 0.13333333 | H9: =MAX(0,MIN(100,(E9-$C9)/($D9-$C9)*100)) -> 82.229965 | I9: =MAX(0,MIN(100,(F9-$C9)/($D9-$C9)*100)) -> 77.952756 | J9: =MAX(0,MIN(100,(G9-$C9)/($D9-$C9)*100)) -> 53.333333 | K9: 0.05 | L9: 0.1 | M9: 0.1
A10: Suppliers that are ESG-score laggards, % | B10: Supply_Chain (SPLC) | C10: 0 | D10: 0.1 | E10: =Supply_Chain!D20 -> 0.045296167 | F10: =Supply_Chain!C20 -> 0.041338583 | G10: =Supply_Chain!B20 -> 0.033333333 | H10: =MAX(0,MIN(100,(E10-$C10)/($D10-$C10)*100)) -> 45.296167 | I10: =MAX(0,MIN(100,(F10-$C10)/($D10-$C10)*100)) -> 41.338583 | J10: =MAX(0,MIN(100,(G10-$C10)/($D10-$C10)*100)) -> 33.333333 | K10: 0.05 | L10: 0.1 | M10: 0.05
A11: Sanctioned + distressed suppliers, % | B11: Supply_Chain (SPLC) | C11: 0 | D11: 0.05 | E11: =Supply_Chain!D17 -> 0.017421603 | F11: =Supply_Chain!C17 -> 0.029527559 | G11: =Supply_Chain!B17 -> 0.033333333 | H11: =MAX(0,MIN(100,(E11-$C11)/($D11-$C11)*100)) -> 34.843206 | I11: =MAX(0,MIN(100,(F11-$C11)/($D11-$C11)*100)) -> 59.055118 | J11: =MAX(0,MIN(100,(G11-$C11)/($D11-$C11)*100)) -> 66.666667 | K11: 0.1 | L11: 0.1 | M11: 0.05
A12: Adverse news severity, 12M (see warning on News_Events) | B12: News_Events | C12: 0 | D12: 20 | E12: =News_Events!C7 -> 12 | F12: =News_Events!C8 -> 1 | G12: =News_Events!C9 -> 19 | H12: =MAX(0,MIN(100,(E12-$C12)/($D12-$C12)*100)) -> 60 | I12: =MAX(0,MIN(100,(F12-$C12)/($D12-$C12)*100)) -> 5 | J12: =MAX(0,MIN(100,(G12-$C12)/($D12-$C12)*100)) -> 95 | K12: 0.1 | L12: 0.1 | M12: 0.05
A13: Equity volatility, 90-day (% ann.) | B13: Market_Data | C13: 10 | D13: 40 | E13: =Market_Data!D26 -> 23.1949 | F13: =Market_Data!C26 -> 23.9151 | G13: =Market_Data!B26 -> 21.6096 | H13: =MAX(0,MIN(100,(E13-$C13)/($D13-$C13)*100)) -> 43.983 | I13: =MAX(0,MIN(100,(F13-$C13)/($D13-$C13)*100)) -> 46.383667 | J13: =MAX(0,MIN(100,(G13-$C13)/($D13-$C13)*100)) -> 38.698667 | K13: 0.05 | L13: 0.1 | M13: 0
A14: Interest cover, 2025 (OI / interest) — lower = riskier | B14: Fundamentals | C14: 12 | D14: 2 | E14: =Fundamentals!I26 -> 9.134058 | F14: =Fundamentals!I55 -> 8.2869875 | G14: =Fundamentals!I84 -> 2.0826063 | H14: =MAX(0,MIN(100,(E14-$C14)/($D14-$C14)*100)) -> 28.65942 | I14: =MAX(0,MIN(100,(F14-$C14)/($D14-$C14)*100)) -> 37.130125 | J14: =MAX(0,MIN(100,(G14-$C14)/($D14-$C14)*100)) -> 99.173937 | K14: 0.1 | L14: 0.1 | M14: 0.1
A15: Weight check (must be 100%) | K15: =SUM(K5:K14) -> 1 | L15: =SUM(L5:L14) -> 1 | M15: =SUM(M5:M14) -> 1
A17: Composite score | H17: Unilever | I17: Nestlé | J17: Wilmar
A18: Base weights | H18: =SUMPRODUCT(H$5:H$14,$K$5:$K$14) -> 53.004404 | I18: =SUMPRODUCT(I$5:I$14,$K$5:$K$14) -> 39.940302 | J18: =SUMPRODUCT(J$5:J$14,$K$5:$K$14) -> 63.512421
A19: Equal weights | H19: =SUMPRODUCT(H$5:H$14,$L$5:$L$14) -> 52.048406 | I19: =SUMPRODUCT(I$5:I$14,$L$5:$L$14) -> 41.930537 | J19: =SUMPRODUCT(J$5:J$14,$L$5:$L$14) -> 62.449545
A20: Env/Social-heavy | H20: =SUMPRODUCT(H$5:H$14,$M$5:$M$14) -> 57.116047 | I20: =SUMPRODUCT(I$5:I$14,$M$5:$M$14) -> 42.249517 | J20: =SUMPRODUCT(J$5:J$14,$M$5:$M$14) -> 61.566963
A21: Rank (1 = highest risk) — Base weights | H21: =RANK(H18,$H18:$J18,0) -> 2 | I21: =RANK(I18,$H18:$J18,0) -> 3 | J21: =RANK(J18,$H18:$J18,0) -> 1
A22: Rank (1 = highest risk) — Equal weights | H22: =RANK(H19,$H19:$J19,0) -> 2 | I22: =RANK(I19,$H19:$J19,0) -> 3 | J22: =RANK(J19,$H19:$J19,0) -> 1
A23: Rank (1 = highest risk) — Env/Social-heavy | H23: =RANK(H20,$H20:$J20,0) -> 2 | I23: =RANK(I20,$H20:$J20,0) -> 3 | J23: =RANK(J20,$H20:$J20,0) -> 1
A24: Ranking stable across the three weight sets? | H24: =IF(AND(H21=H22,H21=H23,I21=I22,I21=I23,J21=J22,J21=J23),"Yes","No — weights matter") -> Yes
A26: How to read: with only three firms the index is a RELATIVE ranking and a worked example of the method — not a validated risk model. To make it publishable: (1) extend to 10–15 firms (add IOI, Musim Mas, AAK, Cargill, P&G, Mondelez, Colgate); (2) score Wilmar's 30 suppliers at node level; (3) calibrate weights against an outcome (e.g. forward 3-month drawdown or controversy count after each event) instead of choosing them by judgement. Unilever's Social-pillar gap dominates its score; Wilmar's is driven by interest cover, supplier conduct risk and news severity.

Sheet Supply_Chain
A1: Supply chain — Bloomberg SPLC (as of 15-Oct-2026)
A2: Blue = typed from SPLC screens. Only the rows visible on screen were captured, so every 'coverage' figure is a LOWER bound on what SPLC holds.
A4: A. SPLC summary panels
A5: Metric | B5: Wilmar | C5: Nestlé | D5: Unilever
A6: Suppliers listed (count) | B6: 30 | C6: 508 | D6: 287
A7: Customers listed (count) | B7: 17 | C7: 172 | D7: 126
A8: Suppliers with sanctions | B8: 1 | C8: 2 | D8: 1
A9: Customers with sanctions | B9: 0 | C9: 3 | D9: 1
A10: Suppliers distressed | B10: 0 | C10: 13 | D10: 4
A11: Customers distressed | B11: 1 | C11: 4 | D11: 3
A12: Suppliers = ESG-score laggards (count) | B12: 1 | C12: 21 | D12: 13
A13: Suppliers = business-conduct risk (count) | B13: 11 | C13: 54 | D13: 40
A14: Suppliers = high GHG vs peers (count) | B14: 4 | C14: 99 | D14: 59
A15: Suppliers = high physical risk (count) | B15: 2 | C15: 11 | D15: 6
A16: Suppliers = high water stress (count) | B16: 5 | C16: 71 | D16: 72
A17: Sanctioned + distressed suppliers, % of suppliers | B17: =(B8+B10)/B6 -> 0.033333333 | C17: =(C8+C10)/C6 -> 0.029527559 | D17: =(D8+D10)/D6 -> 0.017421603
A18: Business-conduct-risk suppliers, % | B18: =B13/B6 -> 0.36666667 | C18: =C13/C6 -> 0.10629921 | D18: =D13/D6 -> 0.13937282
A19: High-GHG suppliers, % | B19: =B14/B6 -> 0.13333333 | C19: =C14/C6 -> 0.19488189 | D19: =D14/D6 -> 0.20557491
A20: ESG-laggard suppliers, % | B20: =B12/B6 -> 0.033333333 | C20: =C12/C6 -> 0.041338583 | D20: =D12/D6 -> 0.045296167
A21: High-water-stress suppliers, % | B21: =B16/B6 -> 0.16666667 | C21: =C16/C6 -> 0.13976378 | D21: =D16/D6 -> 0.25087108
A23: B. Geography (revenue / own facilities / supplier facilities, % of total)
A24: Wilmar | B24: Revenue % | C24: Facilities % | D24: Supplier facilities %
A25: China | B25: 0.4733 | C25: 0.2825 | D25: 0.1761
A26: Indonesia | B26: 0.0444 | C26: 0.2177 | D26: 0.0344
A27: Malaysia | B27: 0.0353 | C27: 0.1089 | D27: 0.08
A28: Australia | B28: 0.0327 | C28: 0.0968 | D28: 0.0172
A29: India | B29: 0.0389 | C29: 0.0685 | D29: 0.0273
A31: Nestlé | B31: Revenue % | C31: Facilities % | D31: Supplier facilities %
A32: USA | B32: 0.3392 | C32: 0.2549 | D32: 0.3249
A33: Brazil | B33: 0.0226 | C33: 0.0562 | D33: 0.0271
A34: France | C34: 0.0475 | D34: 0.0396
A35: Chile | C35: 0.0367 | D35: 0.0096
A36: United Kingdom | C36: 0.0367 | D36: 0.0452
A38: Unilever | B38: Revenue % | C38: Facilities % | D38: Supplier facilities %
A39: India | B39: 0.0433 | C39: 0.2283 | D39: 0.0491
A40: USA | B40: 0.2055 | C40: 0.0868 | D40: 0.3157
A41: United Kingdom | B41: 0.1474 | C41: 0.0502 | D41: 0.0451
A42: Brazil | B42: 0.0747 | C42: 0.0457 | D42: 0.0246
A43: China | B43: 0.1967 | C43: 0.0365 | D43: 0.0907
A45: Read-across: 47% of Wilmar's revenue is China; EU exposure is indirect (via customers). EUDR pressure reaches Wilmar through Unilever/Nestlé-type buyers, not through Wilmar's own EU sales — the ROI sheets use a low EU share for Wilmar for this reason.
A47: C. Commodity exposures shown by SPLC (3-month price change)
A48: Rank | B48: Wilmar | C48: 3M chg | D48: Nestlé | E48: 3M chg | F48: Unilever | G48: 3M chg
A49: 1 | B49: Sugar | C49: 0.319 | D49: Barley | E49: 0.5257 | F49: Diesel | G49: 0.5184
A50: 2 | B50: Polyethylene | C50: 0.212 | D50: Sugar | E50: 0.319 | F50: Sugar | G50: 0.319
A51: 3 | B51: Rice | C51: 0.2064 | D51: Maize | E51: 0.2651 | F51: Crude | G51: 0.225
A52: 4 | B52: Biofuel | C52: -0.1654 | D52: Fish | E52: 0.2638 | F52: Polyethylene | G52: 0.2137
A53: 5 | B53: Eggs | C53: -0.1559 | D53: Polyethylene | E53: 0.2133 | F53: Biofuel | G53: -0.1654
A54: Palm oil is NOT among SPLC's top-5 commodity exposures for any of the three firms. For Unilever/Nestlé it is a small share of total COGS, so the investment case rests on regulatory, Scope 3 and reputational exposure — not on input-cost savings.
A56: D. Wilmar — suppliers visible on screen (24 of 30)
A57: Supplier | B57: Supplier's revenue % from Wilmar | C57: Wilmar cost % (COGS/SGA) | D57: Type | E57: 3M price chg | F57: Palm/plantation node? (Y/N) | G57: Related party / JV? (Y/N, verify) | H57: Cost share ex-related
A58: Yihai Kerry Arawana Holdings | B58: 0.0253 | C58: 0.0128 | D58: COGS | E58: -0.0087 | F58: N | G58: Y | H58: =IF(G58="N",N(C58),0) -> 0
A59: Wilmar Cahaya Indonesia Tbk PT | B59: 0.48 | C59: 0.0042 | D59: COGS | E59: 0.0046 | F59: N | G59: Y | H59: =IF(G59="N",N(C59),0) -> 0
A60: Shree Renuka Sugars | B60: 0.1702 | C60: 0.0025 | D60: COGS | E60: -0.0009 | F60: N | G60: N | H60: =IF(G60="N",N(C60),0) -> 0.0025
A61: Dharma Satya Nusantara Tbk PT | B61: 0.1272 | C61: 0.0014 | D61: COGS | E61: 0.1818 | F61: Y | G61: N | H61: =IF(G61="N",N(C61),0) -> 0.0014
A62: GPT Group/The | B62: 0.0059 | C62: 0.0012 | D62: SGA | E62: -0.0438 | F62: N | G62: N | H62: =IF(G62="N",N(C62),0) -> 0.0012
A63: Ecolab Inc | B63: 0.0032 | C63: 0.0008 | D63: COGS | E63: 0.0646 | F63: N | G63: N | H63: =IF(G63="N",N(C63),0) -> 0.0008
A64: AEP Pinago Plantations Tbk PT | B64: 0.3861 | C64: 0.0007 | D64: COGS | E64: -0.0805 | F64: Y | G64: N | H64: =IF(G64="N",N(C64),0) -> 0.0007
A65: Bakrie Sumatera Plantations Tbk PT | B65: 0.2206 | C65: 0.0005 | D65: COGS | E65: 0.534 | F65: Y | G65: N | H65: =IF(G65="N",N(C65),0) -> 0.0005
A66: Kencana Agri Ltd | B66: 0.1387 | C66: 0.0004 | D66: COGS | E66: 0.1875 | F66: Y | G66: N | H66: =IF(G66="N",N(C66),0) -> 0.0004
A67: Gozco Plantations Tbk PT | B67: 0.4733 | C67: 0.0004 | D67: COGS | E67: -0.0068 | F67: Y | G67: N | H67: =IF(G67="N",N(C67),0) -> 0.0004
A68: PPB Group Bhd | B68: 0.015 | C68: 0.0003 | D68: COGS | E68: -0.0617 | F68: N | G68: N | H68: =IF(G68="N",N(C68),0) -> 0.0003
A69: SIS Ltd | B69: 0.0007 | C69: 0.0003 | D69: SGA | E69: -0.081 | F69: N | G69: N | H69: =IF(G69="N",N(C69),0) -> 0.0003
... A74: Clariant AG | B74: 0.0018 | C74: 0.0001 | D74: COGS | E74: 0.3406 | F74: N | G74: N | H74: =IF(G74="N",N(C74),0) -> 0.0001
A75: Cosan SA | E75: 0.2875 | F75: N | G75: N | H75: =IF(G75="N",N(C75),0) -> 0
A76: Icents Group Holdings Bhd | E76: 0.2109 | F76: N | G76: N | H76: =IF(G76="N",N(C76),0) -> 0
A77: Mitra Pack Tbk PT | E77: -0.2459 | F77: N | G77: N | H77: =IF(G77="N",N(C77),0) -> 0
A78: Sawit Sumbermas Sarana Tbk PT | E78: 0.1648 | F78: Y | G78: N | H78: =IF(G78="N",N(C78),0) -> 0
A79: Humpuss Intermoda Transportasi Tbk PT | F79: N | G79: N | H79: =IF(G79="N",N(C79),0) -> 0
A80: Astra Agro Lestari Tbk PT | E80: 0.3571 | F80: Y | G80: N | H80: =IF(G80="N",N(C80),0) -> 0
A81: Wijaya Karya Beton Tbk PT | E81: -0.0811 | F81: N | G81: N | H81: =IF(G81="N",N(C81),0) -> 0
A82: Visible supplier cost, % of Wilmar COGS+SGA (lower bound) | B82: =SUM(C58:C81) -> 0.0266
A83: of which palm / plantation nodes | B83: =SUMIF(F58:F81,"Y",C58:C81) -> 0.0042
A84: Palm/plantation nodes visible (count) | B84: =COUNTIF(F58:F81,"Y") -> 10
A85: Cost-weighted dependence of palm nodes on Wilmar (buyer leverage) | B85: =SUMPRODUCT((F58:F81="Y")*C58:C81*B58:B81)/SUMIF(F58:F81,"Y",C58:C81) -> 0.27092143
A86: HHI of visible cost shares, ex related parties (0–10,000) | B86: =SUMPRODUCT(H58:H81^2)/SUM(H58:H81)^2*10000 -> 1330.919
A87: Top-3 share of visible cost, ex related parties | B87: =(LARGE(H58:H81,1)+LARGE(H58:H81,2)+LARGE(H58:H81,3))/SUM(H58:H81) -> 0.54255319
A88: Finding: the plantation/mill nodes Bloomberg can see make up a few hundredths of one percent of Wilmar's cost base, yet palm products dominate Wilmar's business. Most palm is bought from third-party mills and smallholders that SPLC does not cover — which is the traceability gap the capstone is about. Palm-node and related-party flags are my judgement from company names; verify before use. Yihai Kerry Arawana, Wilmar Cahaya and AWL Agri are group companies or JVs.
A90: E. Nestlé — top 24 suppliers by cost share (SPLC)
A91: Supplier | B91: Supplier's revenue % from Nestlé | C91: Nestlé cost % | D91: Type | E91: 3M price chg | F91: Category (my coding)
A92: Amcor PLC | B92: 0.0547 | C92: 0.0217 | D92: COGS | E92: -0.0258 | F92: Packaging
A93: Silgan Holdings | B93: 0.14 | C93: 0.0154 | D93: COGS | E93: -0.2143 | F93: Packaging
A94: International Flavors & Fragrances | B94: 0.0595 | C94: 0.0117 | D94: COGS | E94: 0.1897 | F94: Flavours/ingredients
A95: Telefonaktiebolaget LM Ericsson | B95: 0.0021 | C95: 0.0106 | D95: CAPEX | E95: -0.0021 | F95: Technology
A96: Ball Corp | B96: 0.0378 | C96: 0.0093 | D96: COGS | E96: -0.0061 | F96: Packaging
A97: Crown Holdings | B97: 0.0319 | C97: 0.0069 | D97: COGS | E97: -0.004 | F97: Packaging
A98: Alibaba Group Holding | B98: 0.0013 | C98: 0.0067 | D98: SGA | E98: -0.0554 | F98: Technology
A99: Givaudan SA | B99: 0.0437 | C99: 0.0063 | D99: COGS | E99: 0.1283 | F99: Flavours/ingredients
A100: Barry Callebaut AG | B100: 0.0144 | C100: 0.0043 | D100: COGS | E100: -0.0676 | F100: Flavours/ingredients
A101: Symrise AG | B101: 0.0376 | C101: 0.0038 | D101: COGS | E101: 0.1061 | F101: Flavours/ingredients
A102: Daetwyler Holding AG | B102: 0.1568 | C102: 0.0037 | D102: COGS | E102: -0.121 | F102: Industrial
A103: Keurig Dr Pepper | B103: 0.0129 | C103: 0.0036 | D103: COGS | E103: 0.0938 | F103: Beverage
... A115: Jabil Inc | B115: 0.0018 | C115: 0.001 | D115: COGS | E115: -0.0792 | F115: Technology
A116: Visible supplier cost, % of COGS (lower bound) | B116: =SUM(C92:C115) -> 0.1287
A117: Palm / edible-oil / plantation nodes visible (count) | B117: =COUNTIF(F92:F115,"Palm*") -> 0
A118: Packaging share of visible cost | B118: =SUMIF(F92:F115,"Packaging",C92:C115)/SUM(C92:C115) -> 0.48640249
A119: HHI of visible cost shares (0–10,000) | B119: =SUMPRODUCT(C92:C115^2)/SUM(C92:C115)^2*10000 -> 780.55675
A121: F. Unilever — top 24 suppliers by cost share (SPLC)
A122: Supplier | B122: Supplier's revenue % from Unilever | C122: Unilever cost % | D122: Type | E122: 3M price chg | F122: Category (my coding)
A123: Alibaba Group Holding | B123: 0.012 | C123: 0.0528 | D123: SGA | E123: -0.0554 | F123: Technology
A124: Barry Callebaut AG | B124: 0.042 | C124: 0.0248 | D124: COGS | E124: -0.0676 | F124: Flavours/ingredients
...

Sheet News_Events
A1: News & controversy log — hand-coded from Bloomberg CN screens
A2: One row per event cluster (many headlines on the same event count once). Antitrust events are logged but excluded from the adverse score (not supply-chain related). Category, sentiment and severity are MY judgement from headlines — re-code with your own rubric.
A4: As-of date | B4: 46310 | C4: 12M window start | D4: =EDATE(B4,-12) -> 45945
A6: Company | B6: Adverse events (12M, excl. antitrust) | C6: Severity-weighted (12M) | D6: Positive/mitigation events (12M) | E6: Headlines in log (12M) | F6: Screen filter used
A7: ULVR | B7: =COUNTIFS($B$14:$B$35,A7,$H$14:$H$35,TRUE(),$E$14:$E$35,-1,$D$14:$D$35,"<>Antitrust*") -> 5 | C7: =SUMIFS($I$14:$I$35,$B$14:$B$35,A7) -> 12 | D7: =COUNTIFS($B$14:$B$35,A7,$H$14:$H$35,TRUE(),$E$14:$E$35,1) -> 0 | E7: =SUMIFS($G$14:$G$35,$B$14:$B$35,A7,$H$14:$H$35,TRUE()) -> 12 | F7: ESG (+ Palm Oil/deforestation, older)
A8: NESN | B8: =COUNTIFS($B$14:$B$35,A8,$H$14:$H$35,TRUE(),$E$14:$E$35,-1,$D$14:$D$35,"<>Antitrust*") -> 1 | C8: =SUMIFS($I$14:$I$35,$B$14:$B$35,A8) -> 1 | D8: =COUNTIFS($B$14:$B$35,A8,$H$14:$H$35,TRUE(),$E$14:$E$35,1) -> 0 | E8: =SUMIFS($G$14:$G$35,$B$14:$B$35,A8,$H$14:$H$35,TRUE()) -> 5 | F8: Palm Oil ONLY
A9: WIL | B9: =COUNTIFS($B$14:$B$35,A9,$H$14:$H$35,TRUE(),$E$14:$E$35,-1,$D$14:$D$35,"<>Antitrust*") -> 6 | C9: =SUMIFS($I$14:$I$35,$B$14:$B$35,A9) -> 19 | D9: =COUNTIFS($B$14:$B$35,A9,$H$14:$H$35,TRUE(),$E$14:$E$35,1) -> 2 | E9: =SUMIFS($G$14:$G$35,$B$14:$B$35,A9,$H$14:$H$35,TRUE()) -> 26 | F9: ESG + Palm Oil
A11: WARNING — not like-for-like: the three companies were screened with different search filters (Nestlé: 'Palm Oil' only, which returns mostly sell-side cost notes). Re-run all three with the SAME query, e.g. company AND (palm oil OR deforestation OR 'supply chain') with ESG/controversy tags, before relying on the news score. Weight kept low in the index for this reason.
A13: Date | B13: Co. | C13: Event cluster | D13: Category | E13: Sentiment (-1/0/+1) | F13: Severity 0–5 | G13: # headlines | H13: In 12M window? | I13: Adverse severity counted | J13: Screen filter
A14: 46308 | B14: WIL | C14: Wilmar tops global children's-rights benchmark for 5th consecutive year | D14: ESG – positive | E14: 1 | F14: 0 | G14: 1 | H14: =AND(A14>=$D$4,A14<=$B$4) -> TRUE | I14: =IF(AND(H14,E14<0,LEFT(D14,9)<>"Antitrust"),F14,0) -> 0 | J14: Wilmar + Palm Oil
A15: 46276 | B15: WIL | C15: Pakistan regulator probe vs Unity on Wilmar's complaint (Wilmar is complainant) | D15: Regulatory – non-adverse | E15: 0 | F15: 0 | G15: 3 | H15: =AND(A15>=$D$4,A15<=$B$4) -> TRUE | I15: =IF(AND(H15,E15<0,LEFT(D15,9)<>"Antitrust"),F15,0) -> 0 | J15: Wilmar + Palm Oil
A16: 46272 | B16: WIL | C16: ABF–Wilmar JV control of Hebei Mauri cleared in EU | D16: M&A – positive | E16: 1 | F16: 0 | G16: 1 | H16: =AND(A16>=$D$4,A16<=$B$4) -> TRUE | I16: =IF(AND(H16,E16<0,LEFT(D16,9)<>"Antitrust"),F16,0) -> 0 | J16: Wilmar + Palm Oil
A17: 46289 | B17: WIL | C17: Palm-oil prices capped for now; war risk, El Niño 2027 gains (BI) | D17: Commodity / price | E17: 0 | F17: 0 | G17: 3 | H17: =AND(A17>=$D$4,A17<=$B$4) -> TRUE | I17: =IF(AND(H17,E17<0,LEFT(D17,9)<>"Antitrust"),F17,0) -> 0 | J17: Wilmar + Palm Oil
A18: 46246 | B18: WIL | C18: Shares fall most in two months on earnings miss; 1H net income $608.9M vs $594.9M | D18: Earnings | E18: -1 | F18: 1 | G18: 3 | H18: =AND(A18>=$D$4,A18<=$B$4) -> TRUE | I18: =IF(AND(H18,E18<0,LEFT(D18,9)<>"Antitrust"),F18,0) -> 1 | J18: Wilmar + Palm Oil
A19: 46170 | B19: WIL | C19: Indonesia export under-invoicing / transfer-pricing probe of palm firms; Wilmar shares fall most in six years | D19: Regulatory / legal | E19: -1 | F19: 5 | G19: 10 | H19: =AND(A19>=$D$4,A19<=$B$4) -> TRUE | I19: =IF(AND(H19,E19<0,LEFT(D19,9)<>"Antitrust"),F19,0) -> 5 | J19: Wilmar + ESG
A20: 46150 | B20: WIL | C20: Russian government to seize Wilmar stake in indirect unit amid corruption allegations | D20: Legal / geopolitical | E20: -1 | F20: 4 | G20: 1 | H20: =AND(A20>=$D$4,A20<=$B$4) -> TRUE | I20: =IF(AND(H20,E20<0,LEFT(D20,9)<>"Antitrust"),F20,0) -> 4 | J20: Wilmar + ESG
A21: 46120 | B21: WIL | C21: Glass Lewis controversy alert on Wilmar | D21: Governance | E21: -1 | F21: 2 | G21: 1 | H21: =AND(A21>=$D$4,A21<=$B$4) -> TRUE | I21: =IF(AND(H21,E21<0,LEFT(D21,9)<>"Antitrust"),F21,0) -> 2 | J21: Wilmar + ESG
A22: 46084 | B22: WIL | C22: Indonesian court jails Wilmar unit executive (6 yrs) for bribery; shares fall | D22: Legal / corruption | E22: -1 | F22: 4 | G22: 2 | H22: =AND(A22>=$D$4,A22<=$B$4) -> TRUE | I22: =IF(AND(H22,E22<0,LEFT(D22,9)<>"Antitrust"),F22,0) -> 4 | J22: Wilmar + ESG
A23: 46026 | B23: WIL | C23: Indonesia's 'Switzerland-sized' land seizures tighten grip on plantations | D23: Land / deforestation | E23: -1 | F23: 3 | G23: 1 | H23: =AND(A23>=$D$4,A23<=$B$4) -> TRUE | I23: =IF(AND(H23,E23<0,LEFT(D23,9)<>"Antitrust"),F23,0) -> 3 | J23: Wilmar + ESG
A24: 45853 | B24: NESN | C24: Musim Mas, Nestlé and AAK renew palm partnership on environmental/social issues | D24: Mitigation – positive | E24: 1 | F24: 0 | G24: 2 | H24: =AND(A24>=$D$4,A24<=$B$4) -> FALSE | I24: =IF(AND(H24,E24<0,LEFT(D24,9)<>"Antitrust"),F24,0) -> 0 | J24: Nestlé + Palm Oil
A25: 46189 | B25: NESN | C25: Nestlé India higher as palm-oil prices decline, easing supply chain | D25: Commodity / price | E25: 0 | F25: 0 | G25: 1 | H25: =AND(A25>=$D$4,A25<=$B$4) -> TRUE | I25: =IF(AND(H25,E25<0,LEFT(D25,9)<>"Antitrust"),F25,0) -> 0 | J25: Nestlé + Palm Oil
... A35: 44972 | B35: ULVR | C35: Indonesia tames rainforest destruction: crackdowns, boycotts and activism (WSJ, context) | D35: Land / deforestation | E35: 0 | F35: 0 | G35: 1 | H35: =AND(A35>=$D$4,A35<=$B$4) -> FALSE | I35: =IF(AND(H35,E35<0,LEFT(D35,9)<>"Antitrust"),F35,0) -> 0 | J35: Unilever + Palm Oil + deforestation

Sheet ESG
A1: ESG — Bloomberg BESG scores (0–10, higher = better) and GHG emissions
A2: Blue = typed from ESG screens. GHG units as shown by Bloomberg (verify; likely '000 tCO2e). Series breaks flagged below.
A4: Wilmar (WIL SP)
A5: Metric | B5: 2016 | C5: 2017 | D5: 2018 | E5: 2019 | F5: 2020 | G5: 2021 | H5: 2022 | I5: 2023 | J5: 2024 | K5: 2025 | L5: % change first→last
A6: BESG ESG score | B6: 2.71 | C6: 2.76 | D6: 3.06 | E6: 3.74 | F6: 4.9 | G6: 5.12 | H6: 6.29 | I6: 5.97 | J6: 6.15 | L6: =IFERROR(LOOKUP(2,1/ISNUMBER(B6:K6),B6:K6)/INDEX(B6:K6,MATCH(TRUE(),INDEX(ISNUMBER(B6:K6),0),0))-1,"") -> 1.2693727
A7: BESG Environmental pillar | B7: 1.87 | C7: 2.08 | D7: 2.6 | E7: 4.14 | F7: 6.2 | G7: 6.61 | H7: 7.17 | I7: 6.71 | J7: 6.59 | L7: =IFERROR(LOOKUP(2,1/ISNUMBER(B7:K7),B7:K7)/INDEX(B7:K7,MATCH(TRUE(),INDEX(ISNUMBER(B7:K7),0),0))-1,"") -> 2.5240642
A8: BESG Social pillar | B8: 2.45 | C8: 2.32 | D8: 2.31 | E8: 2.28 | F8: 3.26 | G8: 3.29 | H8: 6.31 | I8: 5.59 | J8: 6.46 | L8: =IFERROR(LOOKUP(2,1/ISNUMBER(B8:K8),B8:K8)/INDEX(B8:K8,MATCH(TRUE(),INDEX(ISNUMBER(B8:K8),0),0))-1,"") -> 1.6367347
A9: BESG Governance pillar | B9: 4.68 | C9: 4.58 | D9: 4.81 | E9: 4.72 | F9: 4.6 | G9: 4.78 | H9: 4.9 | I9: 5.16 | J9: 5.16 | L9: =IFERROR(LOOKUP(2,1/ISNUMBER(B9:K9),B9:K9)/INDEX(B9:K9,MATCH(TRUE(),INDEX(ISNUMBER(B9:K9),0),0))-1,"") -> 0.1025641
A10: GHG Scope 1 | B10: 3550.5 | C10: 3937.4 | D10: 4888 | E10: 4955.5 | F10: 6711.1 | G10: 8300 | H10: 9000 | I10: 8700 | J10: 8300 | K10: 9100 | L10: =IFERROR(LOOKUP(2,1/ISNUMBER(B10:K10),B10:K10)/INDEX(B10:K10,MATCH(TRUE(),INDEX(ISNUMBER(B10:K10),0),0))-1,"") -> 1.5630193
A11: GHG Scope 2 (location-based) | B11: 573.6 | C11: 593.9 | D11: 623.5 | E11: 681.2 | F11: 4523.1 | G11: 4273.4 | H11: 3800 | I11: 5300 | J11: 4000 | L11: =IFERROR(LOOKUP(2,1/ISNUMBER(B11:K11),B11:K11)/INDEX(B11:K11,MATCH(TRUE(),INDEX(ISNUMBER(B11:K11),0),0))-1,"") -> 5.9735007
A12: GHG Scope 3 | H12: 160556 | I12: 151000 | J12: 147000 | L12: =IFERROR(LOOKUP(2,1/ISNUMBER(B12:K12),B12:K12)/INDEX(B12:K12,MATCH(TRUE(),INDEX(ISNUMBER(B12:K12),0),0))-1,"") -> -0.0844316
A14: Nestlé (NESN SW)
A15: Metric | B15: 2016 | C15: 2017 | D15: 2018 | E15: 2019 | F15: 2020 | G15: 2021 | H15: 2022 | I15: 2023 | J15: 2024 | K15: 2025 | L15: % change first→last
A16: BESG ESG score | B16: 4.54 | C16: 4.92 | D16: 5.03 | E16: 5.94 | F16: 6.17 | G16: 5.01 | H16: 5.14 | I16: 5.23 | J16: 5.28 | L16: =IFERROR(LOOKUP(2,1/ISNUMBER(B16:K16),B16:K16)/INDEX(B16:K16,MATCH(TRUE(),INDEX(ISNUMBER(B16:K16),0),0))-1,"") -> 0.16299559
A17: BESG Environmental pillar | B17: 5.41 | C17: 4.72 | D17: 4.79 | E17: 5.83 | F17: 5.82 | G17: 4.62 | H17: 4.72 | I17: 5.06 | J17: 5.18 | L17: =IFERROR(LOOKUP(2,1/ISNUMBER(B17:K17),B17:K17)/INDEX(B17:K17,MATCH(TRUE(),INDEX(ISNUMBER(B17:K17),0),0))-1,"") -> -0.042513863
A18: BESG Social pillar | B18: 2.44 | C18: 3.82 | D18: 3.95 | E18: 5.27 | F18: 6.3 | G18: 3.72 | H18: 3.95 | I18: 3.89 | J18: 4.11 | L18: =IFERROR(LOOKUP(2,1/ISNUMBER(B18:K18),B18:K18)/INDEX(B18:K18,MATCH(TRUE(),INDEX(ISNUMBER(B18:K18),0),0))-1,"") -> 0.68442623
A19: BESG Governance pillar | B19: 5.84 | C19: 6.42 | D19: 6.56 | E19: 6.79 | F19: 6.51 | G19: 7.07 | H19: 7.09 | I19: 6.97 | J19: 6.71 | L19: =IFERROR(LOOKUP(2,1/ISNUMBER(B19:K19),B19:K19)/INDEX(B19:K19,MATCH(TRUE(),INDEX(ISNUMBER(B19:K19),0),0))-1,"") -> 0.1489726
A20: GHG Scope 1 | B20: 3607.9 | C20: 3532.1 | D20: 3210 | E20: 3246.4 | F20: 3310 | G20: 3420 | H20: 3230 | I20: 3060 | J20: 3020 | K20: 2820 | L20: =IFERROR(LOOKUP(2,1/ISNUMBER(B20:K20),B20:K20)/INDEX(B20:K20,MATCH(TRUE(),INDEX(ISNUMBER(B20:K20),0),0))-1,"") -> -0.21838188
A21: GHG Scope 2 (location-based) | B21: 3736.6 | C21: 3639 | D21: 2380 | E21: 3089 | F21: 3052.2 | G21: 2600 | H21: 2612.7 | I21: 2583.4 | J21: 2420 | K21: 2480 | L21: =IFERROR(LOOKUP(2,1/ISNUMBER(B21:K21),B21:K21)/INDEX(B21:K21,MATCH(TRUE(),INDEX(ISNUMBER(B21:K21),0),0))-1,"") -> -0.33629503
A22: GHG Scope 3 | B22: 105793 | C22: 106926 | D22: 81940 | E22: 107411 | F22: 99430 | G22: 88910 | H22: 79850 | I22: 69980 | J22: 68000 | K22: 72010 | L22: =IFERROR(LOOKUP(2,1/ISNUMBER(B22:K22),B22:K22)/INDEX(B22:K22,MATCH(TRUE(),INDEX(ISNUMBER(B22:K22),0),0))-1,"") -> -0.31933115
A24: Unilever (ULVR LN)
A25: Metric | B25: 2016 | C25: 2017 | D25: 2018 | E25: 2019 | F25: 2020 | G25: 2021 | H25: 2022 | I25: 2023 | J25: 2024 | K25: 2025 | L25: % change first→last
A26: BESG ESG score | B26: 3.92 | C26: 4.03 | D26: 4.24 | E26: 4.28 | F26: 4.56 | G26: 4.41 | H26: 4.68 | I26: 4.91 | J26: 4.82 | L26: =IFERROR(LOOKUP(2,1/ISNUMBER(B26:K26),B26:K26)/INDEX(B26:K26,MATCH(TRUE(),INDEX(ISNUMBER(B26:K26),0),0))-1,"") -> 0.22959184
A27: BESG Environmental pillar | B27: 3.15 | C27: 3.68 | D27: 4.14 | E27: 4.61 | F27: 5.13 | G27: 4.65 | H27: 4.95 | I27: 5.29 | J27: 5.51 | L27: =IFERROR(LOOKUP(2,1/ISNUMBER(B27:K27),B27:K27)/INDEX(B27:K27,MATCH(TRUE(),INDEX(ISNUMBER(B27:K27),0),0))-1,"") -> 0.74920635
A28: BESG Social pillar | B28: 1.31 | C28: 1.32 | D28: 1.32 | E28: 1.35 | F28: 1.46 | G28: 1.49 | H28: 2.08 | I28: 2.12 | J28: 2.08 | L28: =IFERROR(LOOKUP(2,1/ISNUMBER(B28:K28),B28:K28)/INDEX(B28:K28,MATCH(TRUE(),INDEX(ISNUMBER(B28:K28),0),0))-1,"") -> 0.58778626
A29: BESG Governance pillar | B29: 8.57 | C29: 8.25 | D29: 8.48 | E29: 7.96 | F29: 8.17 | G29: 8.15 | H29: 7.74 | I29: 8.09 | J29: 7.59 | L29: =IFERROR(LOOKUP(2,1/ISNUMBER(B29:K29),B29:K29)/INDEX(B29:K29,MATCH(TRUE(),INDEX(ISNUMBER(B29:K29),0),0))-1,"") -> -0.11435239
A30: GHG Scope 1 | B30: 860.2 | C30: 820.4 | D30: 758.2 | E30: 659 | F30: 606.8 | G30: 730 | H30: 640 | I30: 570 | J30: 480 | K30: 430 | L30: =IFERROR(LOOKUP(2,1/ISNUMBER(B30:K30),B30:K30)/INDEX(B30:K30,MATCH(TRUE(),INDEX(ISNUMBER(B30:K30),0),0))-1,"") -> -0.50011625
A31: GHG Scope 2 (location-based) | B31: 1501.4 | C31: 938.9 | D31: 1430.7 | E31: 1098.6 | F31: 1264.3 | H31: 1260 | I31: 1160 | J31: 1260 | K31: 820 | L31: =IFERROR(LOOKUP(2,1/ISNUMBER(B31:K31),B31:K31)/INDEX(B31:K31,MATCH(TRUE(),INDEX(ISNUMBER(B31:K31),0),0))-1,"") -> -0.45384308
A32: GHG Scope 3 | B32: 61543.2 | C32: 60398.6 | D32: 62017.6 | E32: 61020.4 | F32: 114634 | G32: 120213 | H32: 52820 | I32: 102880 | J32: 107960 | K32: 103770 | L32: =IFERROR(LOOKUP(2,1/ISNUMBER(B32:K32),B32:K32)/INDEX(B32:K32,MATCH(TRUE(),INDEX(ISNUMBER(B32:K32),0),0))-1,"") -> 0.68613267
A34: Why this matters for the capstone: Wilmar's BESG score rose from 2.71 (2016) to 6.15 (2024) while its reported Scope 1 more than doubled (3,551 → 9,100). That pattern points to disclosure improving, not footprint falling — so a BESG score alone is a weak predictor of traceability risk (RQ1). Series breaks: Unilever Scope 3 jumps 61,020 (2019) → 114,634 (2020) → 52,820 (2022) → 102,880 (2023) — a methodology/perimeter change, not real movement. Do not trend across it. Wilmar Scope 3 is missing before 2022 and for 2025; Scope 2 market-based figures exist but are omitted here.

Sheet Fundamentals
A1: Fundamentals — Bloomberg FA screens (transcribed)
A2: Blue = value typed from your Bloomberg screenshots (BBG Adjusted / Standardized, as of 15-Oct-2026). Black = formula. Reporting currencies differ (EUR / CHF / USD) — compare ratios, not levels.
A4: Unilever PLC (ULVR LN) — EUR m
A5: Metric | B5: Unit | C5: 2019 | D5: 2020 | E5: 2021 | F5: 2022 | G5: 2023 | H5: 2024 | I5: 2025 | J5: LTM 06/30/26 | K5: 2026E | L5: 2027E
A6: Revenue | B6: EUR m | C6: 51980 | D6: 50724 | E6: 52444 | F6: 60073 | G6: 59604 | H6: 52479 | I6: 50503 | J6: 50629 | K6: 51834.8 | L6: 53358.6
A7: Cost of revenue | B7: EUR m | C7: 29102 | D7: 28684 | E7: 30259 | F7: 35906 | G7: 34429 | H7: 27976 | I7: 26794
A8: Gross profit | B8: EUR m | C8: =C6-C7 -> 22878 | D8: =D6-D7 -> 22040 | E8: =E6-E7 -> 22185 | F8: =F6-F7 -> 24167 | G8: =G6-G7 -> 25175 | H8: =H6-H7 -> 24503 | I8: =I6-I7 -> 23709 | K8: 24245.7 | L8: 25100.4
A9: Operating income (BBG adj.) | B9: EUR m | C9: 9947 | D9: 9367 | E9: 9636 | F9: 9592 | G9: 9931 | H9: 10198 | I9: 10084 | K9: 10455.8 | L9: 10788.5
A10: Interest expense | B10: EUR m | C10: 763 | D10: 647 | E10: 563 | F10: 782 | G10: 1075 | H10: 1063 | I10: 1104
A11: Pretax income, adjusted | B11: EUR m | C11: 9493 | D11: 9040 | E11: 9564 | F11: 9331 | G11: 9654 | H11: 9941 | I11: 9808 | K11: 9989.4 | L11: 10316.7
A12: Inventories (year-end) | B12: EUR m | C12: 4164 | D12: 4462 | E12: 4683 | F12: 5931 | G12: 5119 | H12: 5177 | I12: 4043
A13: Cash & ST investments | B13: EUR m | C13: 5072 | D13: 6297 | E13: 4495 | F13: 5523 | G13: 5853 | H13: 7317 | I13: 5012
A14: Accounts receivable | B14: EUR m | C14: 4916 | D14: 3433 | E14: 3582 | F14: 4544 | G14: 4023 | H14: 4227 | I14: 4852
A15: PP&E, net | B15: EUR m | C15: 12062 | D15: 10558 | E15: 10347 | F15: 10770 | G15: 10707 | H15: 11669 | I15: 8992
A16: Goodwill | B16: EUR m | C16: 18067 | D16: 18942 | E16: 20330 | F16: 21609 | G16: 21109 | H16: 22311 | I16: 17709
A17: Net income (cash-flow statement) | B17: EUR m | C17: 5625 | D17: 5581 | E17: 6049 | F17: 7642 | G17: 6487 | H17: 5744 | I17: 9469
A18: Depreciation & amortisation | B18: EUR m | C18: 1982 | D18: 2018 | E18: 1763 | F18: 1946 | G18: 1579 | H18: 1382 | I18: 1364
A19: Cash from operations | B19: EUR m | C19: 7725 | D19: 8791 | E19: 7817 | F19: 7010 | G19: 9033 | H19: 9269 | I19: 8436
A20: Capex (acq. fixed & intangibles) | B20: EUR m | C20: -1526 | D20: -1021 | E20: -1340 | F20: -1709 | G20: -1745 | H20: -1614 | I20: -1591
A21: Dividends paid | B21: EUR m | C21: -4209 | D21: -4279 | E21: -4483 | F21: -4329 | G21: -4363 | H21: -4319 | I21: -4453
A22: — derived —
A23: Revenue growth y/y | D23: =D6/C6-1 -> -0.02416314 | E23: =E6/D6-1 -> 0.033908998 | F23: =F6/E6-1 -> 0.14546945 | G23: =G6/F6-1 -> -0.0078071679 | H23: =H6/G6-1 -> -0.11953896 | I23: =I6/H6-1 -> -0.037653157
A24: Gross margin | C24: =C8/C6 -> 0.44013082 | D24: =D8/D6 -> 0.43450832 | E24: =E8/E6 -> 0.42302265 | F24: =F8/F6 -> 0.40229388 | G24: =G8/G6 -> 0.42237098 | H24: =H8/H6 -> 0.46691057 | I24: =I8/I6 -> 0.46945726 | K24: =K8/K6 -> 0.46774947 | L24: =L8/L6 -> 0.47040964
A25: Operating margin | C25: =C9/C6 -> 0.19136206 | D25: =D9/D6 -> 0.18466604 | E25: =E9/E6 -> 0.18373885 | F25: =F9/F6 -> 0.1596724 | G25: =G9/G6 -> 0.16661633 | H25: =H9/H6 -> 0.19432535 | I25: =I9/I6 -> 0.19967131 | K25: =K9/K6 -> 0.20171391 | L25: =L9/L6 -> 0.20218859
A26: Interest cover (OI / interest) | C26: =C9/C10 -> 13.036697 | D26: =D9/D10 -> 14.477589 | E26: =E9/E10 -> 17.115453 | F26: =F9/F10 -> 12.265985 | G26: =G9/G10 -> 9.2381395 | H26: =H9/H10 -> 9.593603 | I26: =I9/I10 -> 9.134058
A27: Inventory days (inv / COGS x 365) | C27: =C12/C7*365 -> 52.225277 | D27: =D12/D7*365 -> 56.778343 | E27: =E12/E7*365 -> 56.488813 | F27: =F12/F7*365 -> 60.291177 | G27: =G12/G7*365 -> 54.269221 | H27: =H12/H7*365 -> 67.543788 | I27: =I12/I7*365 -> 55.075577
A28: Free cash flow (CFO + capex) | C28: =C19+C20 -> 6199 | D28: =D19+D20 -> 7770 | E28: =E19+E20 -> 6477 | F28: =F19+F20 -> 5301 | G28: =G19+G20 -> 7288 | H28: =H19+H20 -> 7655 | I28: =I19+I20 -> 6845
A29: FCF / dividends paid | C29: =IFERROR(-C28/C21,0) -> 1.4727964 | D29: =IFERROR(-D28/D21,0) -> 1.8158448 | E29: =IFERROR(-E28/E21,0) -> 1.4447914 | F29: =IFERROR(-F28/F21,0) -> 1.2245322 | G29: =IFERROR(-G28/G21,0) -> 1.6704103 | H29: =IFERROR(-H28/H21,0) -> 1.772401 | I29: =IFERROR(-I28/I21,0) -> 1.537166
A30: Capex / revenue | C30: =-C20/C6 -> 0.029357445 | D30: =-D20/D6 -> 0.020128539 | E30: =-E20/E6 -> 0.025551064 | F30: =-F20/F6 -> 0.028448721 | G30: =-G20/G6 -> 0.029276559 | H30: =-H20/H6 -> 0.030755159 | I30: =-I20/I6 -> 0.031503079
A33: Nestlé SA (NESN SW) — CHF m
A34: Metric | B34: Unit | C34: 2019 | D34: 2020 | E34: 2021 | F34: 2022 | G34: 2023 | H34: 2024 | I34: 2025 | J34: LTM 06/30/26 | K34: 2026E | L34: 2027E
A35: Revenue | B35: CHF m | C35: 92865 | D35: 84681 | E35: 87470 | F35: 94780 | G35: 93351 | H35: 91720 | I35: 89885 | J35: 88775 | K35: 90103 | L35: 92208.1
A36: Cost of revenue | B36: CHF m | C36: 46647 | D36: 42971 | E36: 45468 | F36: 51745 | G36: 50328 | H36: 48670 | I36: 48694
A37: Gross profit | B37: CHF m | C37: =C35-C36 -> 46218 | D37: =D35-D36 -> 41710 | E37: =E35-E36 -> 42002 | F37: =F35-F36 -> 43035 | G37: =G35-G36 -> 43023 | H37: =H35-H36 -> 43050 | I37: =I35-I36 -> 41191 | K37: 41731.2 | L37: 43139.6
A38: Operating income (BBG adj.) | B38: CHF m | C38: 16047 | D38: 14248 | E38: 14902 | F38: 15839 | G38: 15865 | H38: 15948 | I38: 13947 | K38: 14728.2 | L38: 15083.4
A39: Interest expense | B39: CHF m | C39: 1124 | D39: 831 | E39: 815 | F39: 1124 | G39: 1500 | H39: 1700 | I39: 1683
A40: Pretax income, adjusted | B40: CHF m | C40: 15031 | D40: 13374 | E40: 14029 | F40: 14799 | G40: 14505 | H40: 14463 | I40: 12421 | K40: 13274.7 | L40: 14079.4
A41: Inventories (year-end) | B41: CHF m | C41: 9343 | D41: 10101 | E41: 11982 | F41: 15019 | G41: 11896 | H41: 13260 | I41: 12813
A42: Cash & ST investments | B42: CHF m | C42: 10263 | D42: 8609 | E42: 13995 | F42: 6687 | G42: 5851 | H42: 7871 | I42: 6230
A43: Accounts receivable | B43: CHF m | C43: 9408 | D43: 8087 | E43: 8564 | F43: 8795 | G43: 8992 | H43: 9414 | I43: 8744
A44: PP&E, net | B44: CHF m | C44: 28762 | D44: 25840 | E44: 28345 | F44: 30141 | G44: 30467 | H44: 33706 | I44: 32549
A45: Goodwill | B45: CHF m | C45: 28896 | D45: 27620 | E45: 31012 | F45: 31262 | G45: 28693 | H45: 30595 | I45: 27636
A46: Net income (cash-flow statement) | B46: CHF m | C46: 12609 | D46: 12232 | E46: 16905 | F46: 9270 | G46: 11209 | H46: 10884 | I46: 9033
A47: Depreciation & amortisation | B47: CHF m | C47: 3713 | D47: 3465 | E47: 3440 | F47: 3541 | G47: 3458 | H47: 3582 | I47: 3633
A48: Cash from operations | B48: CHF m | C48: 15850 | D48: 14377 | E48: 13864 | F48: 11907 | G48: 15941 | H48: 16675 | I48: 15904
A49: Capex (acq. fixed & intangibles) | B49: CHF m | C49: -4211 | D49: -4364 | E49: -5341 | F49: -5361 | G49: -6203 | H49: -5963 | I49: -4911
A50: Dividends paid | B50: CHF m | C50: -7230 | D50: -7700 | E50: -7681 | F50: -7618 | G50: -7829 | H50: -7816 | I50: -7849
A51: — derived —
A52: Revenue growth y/y | D52: =D35/C35-1 -> -0.088127928 | E52: =E35/D35-1 -> 0.032935369 | F52: =F35/E35-1 -> 0.08357151 | G52: =G35/F35-1 -> -0.01507702 | H52: =H35/G35-1 -> -0.017471693 | I52: =I35/H35-1 -> -0.020006542
A53: Gross margin | C53: =C37/C35 -> 0.4976902 | D53: =D37/D35 -> 0.49255441 | E53: =E37/E35 -> 0.48018749 | F53: =F37/F35 -> 0.45405149 | G53: =G37/G35 -> 0.46087348 | H53: =H37/H35 -> 0.46936328 | I53: =I37/I35 -> 0.45826334 | K53: =K37/K35 -> 0.46314995 | L53: =L37/L35 -> 0.46785044
A54: Operating margin | C54: =C38/C35 -> 0.17279922 | D54: =D38/D35 -> 0.16825498 | E54: =E38/E35 -> 0.17036698 | F54: =F38/F35 -> 0.16711332 | G54: =G38/G35 -> 0.16994997 | H54: =H38/H35 -> 0.17387702 | I54: =I38/I35 -> 0.15516493 | K54: =K38/K35 -> 0.1634596 | L54: =L38/L35 -> 0.16357999
A55: Interest cover (OI / interest) | C55: =C38/C39 -> 14.27669 | D55: =D38/D39 -> 17.145608 | E55: =E38/E39 -> 18.284663 | F55: =F38/F39 -> 14.091637 | G55: =G38/G39 -> 10.576667 | H55: =H38/H39 -> 9.3811765 | I55: =I38/I39 -> 8.2869875
A56: Inventory days (inv / COGS x 365) | C56: =C41/C36*365 -> 73.106416 | D56: =D41/D36*365 -> 85.798911 | E56: =E41/E36*365 -> 96.186989 | F56: =F41/F36*365 -> 105.94135 | G56: =G41/G36*365 -> 86.274837 | H56: =H41/H36*365 -> 99.443189 | I56: =I41/I36*365 -> 96.043558
A57: Free cash flow (CFO + capex) | C57: =C48+C49 -> 11639 | D57: =D48+D49 -> 10013 | E57: =E48+E49 -> 8523 | F57: =F48+F49 -> 6546 | G57: =G48+G49 -> 9738 | H57: =H48+H49 -> 10712 | I57: =I48+I49 -> 10993
A58: FCF / dividends paid | C58: =IFERROR(-C57/C50,0) -> 1.6098202 | D58: =IFERROR(-D57/D50,0) -> 1.3003896 | E58: =IFERROR(-E57/E50,0) -> 1.1096211 | F58: =IFERROR(-F57/F50,0) -> 0.85928065 | G58: =IFERROR(-G57/G50,0) -> 1.243837 | H58: =IFERROR(-H57/H50,0) -> 1.370522 | I58: =IFERROR(-I57/I50,0) -> 1.4005606
A59: Capex / revenue | C59: =-C49/C35 -> 0.045345394 | D59: =-D49/D35 -> 0.051534583 | E59: =-E49/E35 -> 0.061060935 | F59: =-F49/F35 -> 0.056562566 | G59: =-G49/G35 -> 0.066448137 | H59: =-H49/H35 -> 0.065013083 | I59: =-I49/I35 -> 0.05463648
A62: Wilmar International (WIL SP) — USD m
A63: Metric | B63: Unit | C63: 2019 | D63: 2020 | E63: 2021 | F63: 2022 | G63: 2023 | H63: 2024 | I63: 2025 | J63: LTM 06/30/26 | K63: 2026E | L63: 2027E
A64: Revenue | B64: USD m | C64: 42640.5 | D64: 50526.8 | E64: 65793.6 | F64: 73399 | G64: 67155.3 | H64: 67379.1 | I64: 70415.7 | J64: 76083.6 | K64: 78654 | L64: 83077.6
A65: Cost of revenue | B65: USD m | C65: 38154.4 | D65: 44929.2 | E65: 58602.4 | F65: 66852.7 | G65: 61882.1 | H65: 62168.3 | I65: 64619.9
A66: Gross profit | B66: USD m | C66: =C64-C65 -> 4486.1 | D66: =D64-D65 -> 5597.6 | E66: =E64-E65 -> 7191.2 | F66: =F64-F65 -> 6546.3 | G66: =G64-G65 -> 5273.2 | H66: =H64-H65 -> 5210.8 | I66: =I64-I65 -> 5795.8 | K66: 6386.7 | L66: 6845.6
A67: Operating income (BBG adj.) | B67: USD m | C67: 1866.6 | D67: 2215.6 | E67: 2701.6 | F67: 3190.2 | G67: 2179.4 | H67: 2526.3 | I67: 2243.8 | K67: 2662.3 | L67: 2854.9
A68: Interest expense | B68: USD m | C68: 922.7 | D68: 651.1 | E68: 588.4 | F68: 872.1 | G68: 1251.5 | H68: 1266.7 | I68: 1077.4
A69: Pretax income, adjusted | B69: USD m | C69: 1595.3 | D69: 2363.2 | E69: 2740.8 | F69: 2920.9 | G69: 1757 | H69: 1900.1 | I69: 1818.9 | K69: 2319.7 | L69: 2488.4
A70: Inventories (year-end) | B70: USD m | C70: 7970.2 | D70: 9436.2 | E70: 11738.7 | F70: 13230.1 | G70: 11801.7 | H70: 12989.3 | I70: 14652.6
A71: Cash & ST investments | B71: USD m | C71: 4361.4 | D71: 6214.9 | E71: 6668.4 | F71: 6084.6 | G71: 8436.2 | H71: 7374.9 | I71: 7657.7
A72: Accounts receivable | B72: USD m | C72: 4251.6 | D72: 5277.9 | E72: 6833.4 | F72: 6549 | G72: 6384.5 | H72: 7553.2 | I72: 7351.2
A73: PP&E, net | B73: USD m | C73: 11945.5 | D73: 13439.8 | E73: 14830.6 | F73: 15415.8 | G73: 16310.1 | H73: 16161.6 | I73: 16897.6
A74: Goodwill | B74: USD m | C74: 3791.5 | D74: 3868 | E74: 3819.1 | F74: 3832.2 | G74: 3725.2 | H74: 3619.4 | I74: 5507
A75: Net income (cash-flow statement) | B75: USD m | C75: 1293.4 | D75: 1534.1 | E75: 1890.4 | F75: 2402.5 | G75: 1524.8 | H75: 1169.8 | I75: 1410.9
A76: Depreciation & amortisation | B76: USD m | C76: 878.4 | D76: 1058 | E76: 1146.7 | F76: 1153.4 | G76: 1219.5 | H76: 1298.8 | I76: 1387.9
A77: Cash from operations | B77: USD m | C77: 3479.1 | D77: 726.2 | E77: 51.1 | F77: 2149.5 | G77: 4000.2 | H77: 1441.1 | I77: 2386.2
A78: Capex (acq. fixed & intangibles) | B78: USD m | C78: -1813.2 | D78: -1977.1 | E78: -2527.3 | F78: -2483 | G78: -2210.5 | H78: -1571.9 | I78: -1081
A79: Dividends paid | B79: USD m | C79: -461.8 | D79: -618.6 | E79: -968.3 | F79: -755.4 | G79: -795 | H79: -796.3 | I79: -663.3
A80: — derived —
A81: Revenue growth y/y | D81: =D64/C64-1 -> 0.18494858 | E81: =E64/D64-1 -> 0.30215252 | F81: =F64/E64-1 -> 0.11559483 | G81: =G64/F64-1 -> -0.085065192 | H81: =H64/G64-1 -> 0.0033325739 | I81: =I64/H64-1 -> 0.045067387
A82: Gross margin | C82: =C66/C64 -> 0.10520749 | D82: =D66/D64 -> 0.11078477 | E82: =E66/E64 -> 0.10929938 | F82: =F66/F64 -> 0.089187864 | G82: =G66/G64 -> 0.07852247 | H82: =H66/H64 -> 0.077335554 | I82: =I66/I64 -> 0.082308349 | K82: =K66/K64 -> 0.081199939 | L82: =L66/L64 -> 0.082400069
A83: Operating margin | C83: =C67/C64 -> 0.043775284 | D83: =D67/D64 -> 0.043849996 | E83: =E67/E64 -> 0.041061745 | F83: =F67/F64 -> 0.043463807 | G83: =G67/G64 -> 0.032453135 | H83: =H67/H64 -> 0.037493822 | I83: =I67/I64 -> 0.031865053 | K83: =K67/K64 -> 0.033848247 | L83: =L67/L64 -> 0.034364257
A84: Interest cover (OI / interest) | C84: =C67/C68 -> 2.022976 | D84: =D67/D68 -> 3.4028567 | E84: =E67/E68 -> 4.5914344 | F84: =F67/F68 -> 3.6580667 | G84: =G67/G68 -> 1.7414303 | H84: =H67/H68 -> 1.9943949 | I84: =I67/I68 -> 2.0826063
A85: Inventory days (inv / COGS x 365) | C85: =C70/C65*365 -> 76.246069 | D85: =D70/D65*365 -> 76.658676 | E85: =E70/E65*365 -> 73.113482 | F85: =F70/F65*365 -> 72.233231 | G85: =G70/G65*365 -> 69.610122 | H85: =H70/H65*365 -> 76.262251 | I85: =I70/I65*365 -> 82.763963
A86: Free cash flow (CFO + capex) | C86: =C77+C78 -> 1665.9 | D86: =D77+D78 -> -1250.9 | E86: =E77+E78 -> -2476.2 | F86: =F77+F78 -> -333.5 | G86: =G77+G78 -> 1789.7 | H86: =H77+H78 -> -130.8 | I86: =I77+I78 -> 1305.2
A87: FCF / dividends paid | C87: =IFERROR(-C86/C79,0) -> 3.6074058 | D87: =IFERROR(-D86/D79,0) -> -2.0221468 | E87: =IFERROR(-E86/E79,0) -> -2.5572653 | F87: =IFERROR(-F86/F79,0) -> -0.44148795 | G87: =IFERROR(-G86/G79,0) -> 2.251195 | H87: =IFERROR(-H86/H79,0) -> -0.1642597 | I87: =IFERROR(-I86/I79,0) -> 1.9677371
A88: Capex / revenue | C88: =-C78/C64 -> 0.042522954 | D88: =-D78/D64 -> 0.039129729 | E88: =-E78/E64 -> 0.038412551 | F88: =-F78/F64 -> 0.033828799 | G88: =-G78/G64 -> 0.03291624 | H88: =-H78/H64 -> 0.023329193 | I88: =-I78/I64 -> 0.01535169
A91: Caveats: (1) Unilever FY2024-25 revenue is restated for the ice-cream demerger, so 2023→2024 'growth' is a perimeter change, not trading. (2) Nestlé 2019-21 include large disposal gains in net income. (3) Wilmar 2019 CFO is a working-capital swing. Spot-check any figure you cite against the Terminal.

Sheet Market_Data
A1: Market snapshot — Bloomberg profile / HP / GP screens
A2: Blue = typed from screenshots. Wilmar price table range ends 10/09; header quote 3.47 is later. Check the 'as of' date before quoting.
A4: Metric | B4: Wilmar (WIL SP) | C4: Nestlé (NESN SW) | D4: Unilever (ULVR LN)
A5: Price, last (local ccy; ULVR in GBp) | B5: 3.47 | C5: 78.89 | D5: 4829
A6: 1-day change % | B6: -0.0114 | C6: 0.0206 | D6: 0.0252
A7: 52-week high | B7: 4.02 | C7: 87.09 | D7: 5525
A8: 52-week low | B8: 2.88 | C8: 70.29 | D8: 4068
A9: YTD change % | B9: 0.1266 | C9: 0.0019 | D9: -0.0063
A10: Market cap (local ccy m; SGD / CHF / GBP) | B10: 21667.6 | C10: 203261.7 | D10: 104032.5
A11: P/E (trailing) | B11: 11.82 | C11: 27.28 | D11: 22.58
A12: Est. P/E (FY Dec-26) | B12: 10.74 | C12: 17.7 | D12: 17.5
A13: T12M EPS (USD / CHF / EUR) | B13: 0.23 | C13: 2.89 | D13: 2.52
A14: Est. EPS | B14: 0.25 | C14: 4.46 | D14: 3.26
A15: Est. PEG | B15: 2.71 | C15: 3.47 | D15: 3.9
A16: Indicated gross dividend yield | B16: 0.0432 | C16: 0.0393 | D16: 0.033
... A26: 90-day volatility (Bloomberg chart, % ann.) | B26: 21.6096 | C26: 23.9151 | D26: 23.1949
A28: Palm oil futures — KOZ6 Comdty (Bursa Malaysia CPO, Dec-26), MYR / tonne
A29: Last (15-Oct-26) | B29: 4666
A30: Previous close | B30: 4700
A31: Day high / low | B31: 4,737 / 4,621
A32: Open interest (contracts) | B32: 89521
A33: Range high 12/15/25–10/15/26 (09/08/26) | B33: 5115
A34: Range low (12/19/25) | B34: 3911
A35: Range average | B35: 4511.68
A36: Net change over range | B36: 706
A37: Net change % | B37: 0.1783
A38: Drawdown from range high (formula) | B38: =B29/B33-1 -> -0.087781036
A40: Bloomberg ticker note: your screens use KOZ6 Comdty (a single contract month). For a continuous history use the generic first-month series (KO1 Comdty — confirm with the Terminal search) and state the roll rule. The draft plan's 'KOA Comdty' does not match what you actually pulled.

Sheet Price_Analytics
A1: Price analytics — CPO futures vs the three equities
A2: Daily closes 17-Aug to 15-Oct-2026 typed from the HP tables. Returns are log returns, computed only where both days printed. Only ~8 weeks of data: treat statistics as a demo of method, not evidence.
A6: Date | B6: CPO KOZ6 (MYR/t) | C6: WIL SP (SGD) | D6: NESN SW (CHF) | E6: ULVR LN (GBp) | F6: ret CPO | G6: ret WIL | H6: ret NESN | I6: ret ULVR | J6: CPO (rebased) | K6: WIL (rebased) | L6: NESN (rebased) | M6: ULVR (rebased) | O6: Statistic | P6: CPO | Q6: WIL | R6: NESN | S6: ULVR
A7: 46251 | B7: 4903 | C7: 3.67 | D7: 78.71 | E7: 4512.5 | J7: =B7/B$7*100 -> 100 | K7: =C7/C$7*100 -> 100 | L7: =D7/D$7*100 -> 100 | M7: =E7/E$7*100 -> 100 | O7: Return observations (n) | P7: =COUNT(F8:F50) -> 37 | Q7: =COUNT(G8:G50) -> 39 | R7: =COUNT(H8:H50) -> 39 | S7: =COUNT(I8:I50) -> 40
A8: 46252 | B8: 4943 | C8: 3.7 | D8: 79.2 | E8: 4578 | F8: =IF(AND(ISNUMBER(B8),ISNUMBER(B7)),LN(B8/B7),"") -> 0.0081251717 | G8: =IF(AND(ISNUMBER(C8),ISNUMBER(C7)),LN(C8/C7),"") -> 0.0081411576 | H8: =IF(AND(ISNUMBER(D8),ISNUMBER(D7)),LN(D8/D7),"") -> 0.0062060867 | I8: =IF(AND(ISNUMBER(E8),ISNUMBER(E7)),LN(E8/E7),"") -> 0.014410898 | J8: =IF(ISNUMBER(B8),B8/B$7*100,J7) -> 100.81583 | K8: =IF(ISNUMBER(C8),C8/C$7*100,K7) -> 100.81744 | L8: =IF(ISNUMBER(D8),D8/D$7*100,L7) -> 100.62254 | M8: =IF(ISNUMBER(E8),E8/E$7*100,M7) -> 101.45152 | O8: Annualised volatility (x sqrt 252) | P8: =STDEV(F8:F50)*SQRT(252) -> 0.17050291 | Q8: =STDEV(G8:G50)*SQRT(252) -> 0.19399285 | R8: =STDEV(H8:H50)*SQRT(252) -> 0.17654962 | S8: =STDEV(I8:I50)*SQRT(252) -> 0.18376515
A9: 46253 | B9: 4972 | C9: 3.64 | D9: 79.34 | E9: 4638.5 | F9: =IF(AND(ISNUMBER(B9),ISNUMBER(B8)),LN(B9/B8),"") -> 0.0058497393 | G9: =IF(AND(ISNUMBER(C9),ISNUMBER(C8)),LN(C9/C8),"") -> -0.016349138 | H9: =IF(AND(ISNUMBER(D9),ISNUMBER(D8)),LN(D9/D8),"") -> 0.0017661163 | I9: =IF(AND(ISNUMBER(E9),ISNUMBER(E8)),LN(E9/E8),"") -> 0.013128817 | J9: =IF(ISNUMBER(B9),B9/B$7*100,J8) -> 101.4073 | K9: =IF(ISNUMBER(C9),C9/C$7*100,K8) -> 99.182561 | L9: =IF(ISNUMBER(D9),D9/D$7*100,L8) -> 100.80041 | M9: =IF(ISNUMBER(E9),E9/E$7*100,M8) -> 102.79224 | O9: Correlation vs CPO returns | P9: n/a | Q9: =CORREL(G8:G50,$F$8:$F$50) -> -0.079130062 | R9: =CORREL(H8:H50,$F$8:$F$50) -> 0.23039182 | S9: =CORREL(I8:I50,$F$8:$F$50) -> 0.18419985
A10: 46254 | B10: 5025 | C10: 3.66 | D10: 79.4 | E10: 4649 | F10: =IF(AND(ISNUMBER(B10),ISNUMBER(B9)),LN(B10/B9),"") -> 0.01060328 | G10: =IF(AND(ISNUMBER(C10),ISNUMBER(C9)),LN(C10/C9),"") -> 0.0054794658 | H10: =IF(AND(ISNUMBER(D10),ISNUMBER(D9)),LN(D10/D9),"") -> 0.00075595317 | I10: =IF(AND(ISNUMBER(E10),ISNUMBER(E9)),LN(E10/E9),"") -> 0.0022611046 | J10: =IF(ISNUMBER(B10),B10/B$7*100,J9) -> 102.48827 | K10: =IF(ISNUMBER(C10),C10/C$7*100,K9) -> 99.72752 | L10: =IF(ISNUMBER(D10),D10/D$7*100,L9) -> 100.87664 | M10: =IF(ISNUMBER(E10),E10/E$7*100,M9) -> 103.02493 | O10: Beta vs CPO returns | P10: n/a | Q10: =SLOPE(G8:G50,$F$8:$F$50) -> -0.091405022 | R10: =SLOPE(H8:H50,$F$8:$F$50) -> 0.25001025 | S10: =SLOPE(I8:I50,$F$8:$F$50) -> 0.20661569
A11: 46255 | B11: 5077 | C11: 3.71 | D11: 79.68 | E11: 4681 | F11: =IF(AND(ISNUMBER(B11),ISNUMBER(B10)),LN(B11/B10),"") -> 0.010295082 | G11: =IF(AND(ISNUMBER(C11),ISNUMBER(C10)),LN(C11/C10),"") -> 0.013568729 | H11: =IF(AND(ISNUMBER(D11),ISNUMBER(D10)),LN(D11/D10),"") -> 0.003520245 | I11: =IF(AND(ISNUMBER(E11),ISNUMBER(E10)),LN(E11/E10),"") -> 0.0068596196 | J11: =IF(ISNUMBER(B11),B11/B$7*100,J10) -> 103.54885 | K11: =IF(ISNUMBER(C11),C11/C$7*100,K10) -> 101.08992 | L11: =IF(ISNUMBER(D11),D11/D$7*100,L10) -> 101.23237 | M11: =IF(ISNUMBER(E11),E11/E$7*100,M10) -> 103.73407 | O11: Pairs used with CPO | P11: n/a | Q11: =SUMPRODUCT(ISNUMBER(G8:G50)*ISNUMBER($F$8:$F$50)) -> 33 | R11: =SUMPRODUCT(ISNUMBER(H8:H50)*ISNUMBER($F$8:$F$50)) -> 33 | S11: =SUMPRODUCT(ISNUMBER(I8:I50)*ISNUMBER($F$8:$F$50)) -> 36
A12: 46258 | B12: 5013 | C12: 3.76 | D12: 80.46 | E12: 4782.5 | F12: =IF(AND(ISNUMBER(B12),ISNUMBER(B11)),LN(B12/B11),"") -> -0.012685998 | G12: =IF(AND(ISNUMBER(C12),ISNUMBER(C11)),LN(C12/C11),"") -> 0.013387081 | H12: =IF(AND(ISNUMBER(D12),ISNUMBER(D11)),LN(D12/D11),"") -> 0.0097415532 | I12: =IF(AND(ISNUMBER(E12),ISNUMBER(E11)),LN(E12/E11),"") -> 0.02145166 | J12: =IF(ISNUMBER(B12),B12/B$7*100,J11) -> 102.24352 | K12: =IF(ISNUMBER(C12),C12/C$7*100,K11) -> 102.45232 | L12: =IF(ISNUMBER(D12),D12/D$7*100,L11) -> 102.22335 | M12: =IF(ISNUMBER(E12),E12/E$7*100,M11) -> 105.98338 | O12: Approx. 95% band on correlation (±2/√n) | P12: n/a | Q12: =2/SQRT(Q11) -> 0.34815531 | R12: =2/SQRT(R11) -> 0.34815531 | S12: =2/SQRT(S11) -> 0.33333333
A13: 46259 | C13: 3.75 | D13: 79.82 | E13: 4761.5 | F13: =IF(AND(ISNUMBER(B13),ISNUMBER(B12)),LN(B13/B12),"") | G13: =IF(AND(ISNUMBER(C13),ISNUMBER(C12)),LN(C13/C12),"") -> -0.0026631174 | H13: =IF(AND(ISNUMBER(D13),ISNUMBER(D12)),LN(D13/D12),"") -> -0.0079860669 | I13: =IF(AND(ISNUMBER(E13),ISNUMBER(E12)),LN(E13/E12),"") -> -0.0044006777 | J13: =IF(ISNUMBER(B13),B13/B$7*100,J12) -> 102.24352 | K13: =IF(ISNUMBER(C13),C13/C$7*100,K12) -> 102.17984 | L13: =IF(ISNUMBER(D13),D13/D$7*100,L12) -> 101.41024 | M13: =IF(ISNUMBER(E13),E13/E$7*100,M12) -> 105.51801
A14: 46260 | B14: 4931 | C14: 3.75 | D14: 79.87 | E14: 4772 | F14: =IF(AND(ISNUMBER(B14),ISNUMBER(B13)),LN(B14/B13),"") | G14: =IF(AND(ISNUMBER(C14),ISNUMBER(C13)),LN(C14/C13),"") -> 0 | H14: =IF(AND(ISNUMBER(D14),ISNUMBER(D13)),LN(D14/D13),"") -> 0.00062621331 | I14: =IF(AND(ISNUMBER(E14),ISNUMBER(E13)),LN(E14/E13),"") -> 0.0022027596 | J14: =IF(ISNUMBER(B14),B14/B$7*100,J13) -> 100.57108 | K14: =IF(ISNUMBER(C14),C14/C$7*100,K13) -> 102.17984 | L14: =IF(ISNUMBER(D14),D14/D$7*100,L13) -> 101.47376 | M14: =IF(ISNUMBER(E14),E14/E$7*100,M13) -> 105.75069 | O14: Reading: |corr| below the ±2/√n band is statistically indistinguishable from zero.
A15: 46261 | B15: 4907 | C15: 3.77 | D15: 78.52 | E15: 4752 | F15: =IF(AND(ISNUMBER(B15),ISNUMBER(B14)),LN(B15/B14),"") -> -0.0048790501 | G15: =IF(AND(ISNUMBER(C15),ISNUMBER(C14)),LN(C15/C14),"") -> 0.0053191615 | H15: =IF(AND(ISNUMBER(D15),ISNUMBER(D14)),LN(D15/D14),"") -> -0.017046944 | I15: =IF(AND(ISNUMBER(E15),ISNUMBER(E14)),LN(E15/E14),"") -> -0.0041999222 | J15: =IF(ISNUMBER(B15),B15/B$7*100,J14) -> 100.08158 | K15: =IF(ISNUMBER(C15),C15/C$7*100,K14) -> 102.7248 | L15: =IF(ISNUMBER(D15),D15/D$7*100,L14) -> 99.758608 | M15: =IF(ISNUMBER(E15),E15/E$7*100,M14) -> 105.30748 | O15: Next step: pull ≥5Y daily history with BDH() / BQL and rerun (see Next_Steps sheet).
A16: 46262 | B16: 4988 | C16: 3.81 | D16: 78.62 | E16: 4776 | F16: =IF(AND(ISNUMBER(B16),ISNUMBER(B15)),LN(B16/B15),"") -> 0.016372271 | G16: =IF(AND(ISNUMBER(C16),ISNUMBER(C15)),LN(C16/C15),"") -> 0.010554188 | H16: =IF(AND(ISNUMBER(D16),ISNUMBER(D15)),LN(D16/D15),"") -> 0.0012727506 | I16: =IF(AND(ISNUMBER(E16),ISNUMBER(E15)),LN(E16/E15),"") -> 0.005037794 | J16: =IF(ISNUMBER(B16),B16/B$7*100,J15) -> 101.73363 | K16: =IF(ISNUMBER(C16),C16/C$7*100,K15) -> 103.81471 | L16: =IF(ISNUMBER(D16),D16/D$7*100,L15) -> 99.885656 | M16: =IF(ISNUMBER(E16),E16/E$7*100,M15) -> 105.83934
A17: 46265 | C17: 3.84 | D17: 78.82 | F17: =IF(AND(ISNUMBER(B17),ISNUMBER(B16)),LN(B17/B16),"") | G17: =IF(AND(ISNUMBER(C17),ISNUMBER(C16)),LN(C17/C16),"") -> 0.0078431775 | H17: =IF(AND(ISNUMBER(D17),ISNUMBER(D16)),LN(D17/D16),"") -> 0.0025406518 | I17: =IF(AND(ISNUMBER(E17),ISNUMBER(E16)),LN(E17/E16),"") | J17: =IF(ISNUMBER(B17),B17/B$7*100,J16) -> 101.73363 | K17: =IF(ISNUMBER(C17),C17/C$7*100,K16) -> 104.63215 | L17: =IF(ISNUMBER(D17),D17/D$7*100,L16) -> 100.13975 | M17: =IF(ISNUMBER(E17),E17/E$7*100,M16) -> 105.83934
A18: 46266 | B18: 5072 | C18: 3.76 | D18: 78.51 | E18: 4811 | F18: =IF(AND(ISNUMBER(B18),ISNUMBER(B17)),LN(B18/B17),"") | G18: =IF(AND(ISNUMBER(C18),ISNUMBER(C17)),LN(C18/C17),"") -> -0.021053409 | H18: =IF(AND(ISNUMBER(D18),ISNUMBER(D17)),LN(D18/D17),"") -> -0.0039407666 | I18: =IF(AND(ISNUMBER(E18),ISNUMBER(E17)),LN(E18/E17),"") | J18: =IF(ISNUMBER(B18),B18/B$7*100,J17) -> 103.44687 | K18: =IF(ISNUMBER(C18),C18/C$7*100,K17) -> 102.45232 | L18: =IF(ISNUMBER(D18),D18/D$7*100,L17) -> 99.745903 | M18: =IF(ISNUMBER(E18),E18/E$7*100,M17) -> 106.61496
A19: 46267 | B19: 5065 | C19: 3.84 | D19: 78.63 | E19: 4782.5 | F19: =IF(AND(ISNUMBER(B19),ISNUMBER(B18)),LN(B19/B18),"") -> -0.0013810794 | G19: =IF(AND(ISNUMBER(C19),ISNUMBER(C18)),LN(C19/C18),"") -> 0.021053409 | H19: =IF(AND(ISNUMBER(D19),ISNUMBER(D18)),LN(D19/D18),"") -> 0.0015273008 | I19: =IF(AND(ISNUMBER(E19),ISNUMBER(E18)),LN(E19/E18),"") -> -0.0059415404 | J19: =IF(ISNUMBER(B19),B19/B$7*100,J18) -> 103.3041 | K19: =IF(ISNUMBER(C19),C19/C$7*100,K18) -> 104.63215 | L19: =IF(ISNUMBER(D19),D19/D$7*100,L18) -> 99.898361 | M19: =IF(ISNUMBER(E19),E19/E$7*100,M18) -> 105.98338
A20: 46268 | B20: 5018 | C20: 3.84 | D20: 77.84 | E20: 4733 | F20: =IF(AND(ISNUMBER(B20),ISNUMBER(B19)),LN(B20/B19),"") -> -0.0093226898 | G20: =IF(AND(ISNUMBER(C20),ISNUMBER(C19)),LN(C20/C19),"") -> 0 | H20: =IF(AND(ISNUMBER(D20),ISNUMBER(D19)),LN(D20/D19),"") -> -0.010097868 | I20: =IF(AND(ISNUMBER(E20),ISNUMBER(E19)),LN(E20/E19),"") -> -0.010404171 | J20: =IF(ISNUMBER(B20),B20/B$7*100,J19) -> 102.3455 | K20: =IF(ISNUMBER(C20),C20/C$7*100,K19) -> 104.63215 | L20: =IF(ISNUMBER(D20),D20/D$7*100,L19) -> 98.894677 | M20: =IF(ISNUMBER(E20),E20/E$7*100,M19) -> 104.88643
A21: 46269 | B21: 5054 | C21: 3.82 | D21: 78.31 | E21: 4763 | F21: =IF(AND(ISNUMBER(B21),ISNUMBER(B20)),LN(B21/B20),"") -> 0.007148561 | G21: =IF(AND(ISNUMBER(C21),ISNUMBER(C20)),LN(C21/C20),"") -> -0.005221944 | H21: =IF(AND(ISNUMBER(D21),ISNUMBER(D20)),LN(D21/D20),"") -> 0.0060198709 | I21: =IF(AND(ISNUMBER(E21),ISNUMBER(E20)),LN(E21/E20),"") -> 0.0063184709 | J21: =IF(ISNUMBER(B21),B21/B$7*100,J20) -> 103.07975 | K21: =IF(ISNUMBER(C21),C21/C$7*100,K20) -> 104.08719 | L21: =IF(ISNUMBER(D21),D21/D$7*100,L20) -> 99.491805 | M21: =IF(ISNUMBER(E21),E21/E$7*100,M20) -> 105.55125
A22: 46272 | B22: 5110 | C22: 3.8 | D22: 78.76 | E22: 4693.5 | F22: =IF(AND(ISNUMBER(B22),ISNUMBER(B21)),LN(B22/B21),"") -> 0.011019395 | G22: =IF(AND(ISNUMBER(C22),ISNUMBER(C21)),LN(C22/C21),"") -> -0.0052493559 | H22: =IF(AND(ISNUMBER(D22),ISNUMBER(D21)),LN(D22/D21),"") -> 0.005729945 | I22: =IF(AND(ISNUMBER(E22),ISNUMBER(E21)),LN(E22/E21),"") -> -0.014699149 | J22: =IF(ISNUMBER(B22),B22/B$7*100,J21) -> 104.2219 | K22: =IF(ISNUMBER(C22),C22/C$7*100,K21) -> 103.54223 | L22: =IF(ISNUMBER(D22),D22/D$7*100,L21) -> 100.06352 | M22: =IF(ISNUMBER(E22),E22/E$7*100,M21) -> 104.01108
A23: 46273 | B23: 5115 | C23: 3.73 | D23: 80.39 | E23: 4695.5 | F23: =IF(AND(ISNUMBER(B23),ISNUMBER(B22)),LN(B23/B22),"") -> 0.00097799519 | G23: =IF(AND(ISNUMBER(C23),ISNUMBER(C22)),LN(C23/C22),"") -> -0.018592833 | H23: =IF(AND(ISNUMBER(D23),ISNUMBER(D22)),LN(D23/D22),"") -> 0.020484537 | I23: =IF(AND(ISNUMBER(E23),ISNUMBER(E22)),LN(E23/E22),"") -> 0.00042603047 | J23: =IF(ISNUMBER(B23),B23/B$7*100,J22) -> 104.32388 | K23: =IF(ISNUMBER(C23),C23/C$7*100,K22) -> 101.63488 | L23: =IF(ISNUMBER(D23),D23/D$7*100,L22) -> 102.13442 | M23: =IF(ISNUMBER(E23),E23/E$7*100,M22) -> 104.0554
A24: 46274 | B24: 5109 | C24: 3.73 | D24: 77.73 | E24: 4621 | F24: =IF(AND(ISNUMBER(B24),ISNUMBER(B23)),LN(B24/B23),"") -> -0.0011737091 | G24: =IF(AND(ISNUMBER(C24),ISNUMBER(C23)),LN(C24/C23),"") -> 0 | H24: =IF(AND(ISNUMBER(D24),ISNUMBER(D23)),LN(D24/D23),"") -> -0.033648507 | I24: =IF(AND(ISNUMBER(E24),ISNUMBER(E23)),LN(E24/E23),"") -> -0.015993471 | J24: =IF(ISNUMBER(B24),B24/B$7*100,J23) -> 104.20151 | K24: =IF(ISNUMBER(C24),C24/C$7*100,K23) -> 101.63488 | L24: =IF(ISNUMBER(D24),D24/D$7*100,L23) -> 98.754923 | M24: =IF(ISNUMBER(E24),E24/E$7*100,M23) -> 102.40443
A25: 46275 | B25: 5033 | C25: 3.71 | D25: 77.74 | E25: 4559 | F25: =IF(AND(ISNUMBER(B25),ISNUMBER(B24)),LN(B25/B24),"") -> -0.014987463 | G25: =IF(AND(ISNUMBER(C25),ISNUMBER(C24)),LN(C25/C24),"") -> -0.005376357 | H25: =IF(AND(ISNUMBER(D25),ISNUMBER(D24)),LN(D25/D24),"") -> 0.00012864218 | I25: =IF(AND(ISNUMBER(E25),ISNUMBER(E24)),LN(E25/E24),"") -> -0.013507831 | J25: =IF(ISNUMBER(B25),B25/B$7*100,J24) -> 102.65144 | K25: =IF(ISNUMBER(C25),C25/C$7*100,K24) -> 101.08992 | L25: =IF(ISNUMBER(D25),D25/D$7*100,L24) -> 98.767628 | M25: =IF(ISNUMBER(E25),E25/E$7*100,M24) -> 101.03047
A26: 46276 | B26: 4944 | C26: 3.71 | D26: 77.54 | E26: 4551.5 | F26: =IF(AND(ISNUMBER(B26),ISNUMBER(B25)),LN(B26/B25),"") -> -0.017841508 | G26: =IF(AND(ISNUMBER(C26),ISNUMBER(C25)),LN(C26/C25),"") -> 0 | H26: =IF(AND(ISNUMBER(D26),ISNUMBER(D25)),LN(D26/D25),"") -> -0.0025759932 | I26: =IF(AND(ISNUMBER(E26),ISNUMBER(E25)),LN(E26/E25),"") -> -0.0016464523 | J26: =IF(ISNUMBER(B26),B26/B$7*100,J25) -> 100.83622 | K26: =IF(ISNUMBER(C26),C26/C$7*100,K25) -> 101.08992 | L26: =IF(ISNUMBER(D26),D26/D$7*100,L25) -> 98.513531 | M26: =IF(ISNUMBER(E26),E26/E$7*100,M25) -> 100.86427
A27: 46279 | B27: 4958 | C27: 3.72 | D27: 79.2 | E27: 4697 | F27: =IF(AND(ISNUMBER(B27),ISNUMBER(B26)),LN(B27/B26),"") -> 0.0028277135 | G27: =IF(AND(ISNUMBER(C27),ISNUMBER(C26)),LN(C27/C26),"") -> 0.0026917917 | H27: =IF(AND(ISNUMBER(D27),ISNUMBER(D26)),LN(D27/D26),"") -> 0.021182367 | I27: =IF(AND(ISNUMBER(E27),ISNUMBER(E26)),LN(E27/E26),"") -> 0.031467158 | J27: =IF(ISNUMBER(B27),B27/B$7*100,J26) -> 101.12176 | K27: =IF(ISNUMBER(C27),C27/C$7*100,K26) -> 101.3624 | L27: =IF(ISNUMBER(D27),D27/D$7*100,L26) -> 100.62254 | M27: =IF(ISNUMBER(E27),E27/E$7*100,M26) -> 104.08864
A28: 46280 | B28: 4998 | C28: 3.7 | D28: 77.89 | E28: 4641.5 | F28: =IF(AND(ISNUMBER(B28),ISNUMBER(B27)),LN(B28/B27),"") -> 0.0080353988 | G28: =IF(AND(ISNUMBER(C28),ISNUMBER(C27)),LN(C28/C27),"") -> -0.0053908486 | H28: =IF(AND(ISNUMBER(D28),ISNUMBER(D27)),LN(D28/D27),"") -> -0.016678724 | I28: =IF(AND(ISNUMBER(E28),ISNUMBER(E27)),LN(E28/E27),"") -> -0.011886417 | J28: =IF(ISNUMBER(B28),B28/B$7*100,J27) -> 101.93759 | K28: =IF(ISNUMBER(C28),C28/C$7*100,K27) -> 100.81744 | L28: =IF(ISNUMBER(D28),D28/D$7*100,L27) -> 98.958201 | M28: =IF(ISNUMBER(E28),E28/E$7*100,M27) -> 102.85873
A29: 46281 | C29: 3.71 | D29: 77.66 | E29: 4640 | F29: =IF(AND(ISNUMBER(B29),ISNUMBER(B28)),LN(B29/B28),"") | G29: =IF(AND(ISNUMBER(C29),ISNUMBER(C28)),LN(C29/C28),"") -> 0.002699057 | H29: =IF(AND(ISNUMBER(D29),ISNUMBER(D28)),LN(D29/D28),"") -> -0.0029572506 | I29: =IF(AND(ISNUMBER(E29),ISNUMBER(E28)),LN(E29/E28),"") -> -0.00032322362 | J29: =IF(ISNUMBER(B29),B29/B$7*100,J28) -> 101.93759 | K29: =IF(ISNUMBER(C29),C29/C$7*100,K28) -> 101.08992 | L29: =IF(ISNUMBER(D29),D29/D$7*100,L28) -> 98.665989 | M29: =IF(ISNUMBER(E29),E29/E$7*100,M28) -> 102.82548
A30: 46282 | B30: 4936 | C30: 3.73 | D30: 78.33 | E30: 4632.5 | F30: =IF(AND(ISNUMBER(B30),ISNUMBER(B29)),LN(B30/B29),"") | G30: =IF(AND(ISNUMBER(C30),ISNUMBER(C29)),LN(C30/C29),"") -> 0.005376357 | H30: =IF(AND(ISNUMBER(D30),ISNUMBER(D29)),LN(D30/D29),"") -> 0.0085903471 | I30: =IF(AND(ISNUMBER(E30),ISNUMBER(E29)),LN(E30/E29),"") -> -0.0016176871 | J30: =IF(ISNUMBER(B30),B30/B$7*100,J29) -> 100.67306 | K30: =IF(ISNUMBER(C30),C30/C$7*100,K29) -> 101.63488 | L30: =IF(ISNUMBER(D30),D30/D$7*100,L29) -> 99.517215 | M30: =IF(ISNUMBER(E30),E30/E$7*100,M29) -> 102.65928
A31: 46283 | B31: 4898 | C31: 3.68 | D31: 76.27 | E31: 4621 | F31: =IF(AND(ISNUMBER(B31),ISNUMBER(B30)),LN(B31/B30),"") -> -0.0077283281 | G31: =IF(AND(ISNUMBER(C31),ISNUMBER(C30)),LN(C31/C30),"") -> -0.013495481 | H31: =IF(AND(ISNUMBER(D31),ISNUMBER(D30)),LN(D31/D30),"") -> -0.026650995 | I31: =IF(AND(ISNUMBER(E31),ISNUMBER(E30)),LN(E31/E30),"") -> -0.0024855473 | J31: =IF(ISNUMBER(B31),B31/B$7*100,J30) -> 99.898022 | K31: =IF(ISNUMBER(C31),C31/C$7*100,K30) -> 100.27248 | L31: =IF(ISNUMBER(D31),D31/D$7*100,L30) -> 96.900013 | M31: =IF(ISNUMBER(E31),E31/E$7*100,M30) -> 102.40443
A32: 46286 | B32: 4857 | C32: 3.65 | D32: 77.1 | E32: 4642.5 | F32: =IF(AND(ISNUMBER(B32),ISNUMBER(B31)),LN(B32/B31),"") -> -0.0084059952 | G32: =IF(AND(ISNUMBER(C32),ISNUMBER(C31)),LN(C32/C31),"") -> -0.0081855846 | H32: =IF(AND(ISNUMBER(D32),ISNUMBER(D31)),LN(D32/D31),"") -> 0.010823604 | I32: =IF(AND(ISNUMBER(E32),ISNUMBER(E31)),LN(E32/E31),"") -> 0.0046418824 | J32: =IF(ISNUMBER(B32),B32/B$7*100,J31) -> 99.061799 | K32: =IF(ISNUMBER(C32),C32/C$7*100,K31) -> 99.455041 | L32: =IF(ISNUMBER(D32),D32/D$7*100,L31) -> 97.954517 | M32: =IF(ISNUMBER(E32),E32/E$7*100,M31) -> 102.88089
A33: 46287 | B33: 4810 | C33: 3.65 | D33: 77.09 | E33: 4698 | F33: =IF(AND(ISNUMBER(B33),ISNUMBER(B32)),LN(B33/B32),"") -> -0.0097238792 | G33: =IF(AND(ISNUMBER(C33),ISNUMBER(C32)),LN(C33/C32),"") -> 0 | H33: =IF(AND(ISNUMBER(D33),ISNUMBER(D32)),LN(D33/D32),"") -> -0.0001297101 | I33: =IF(AND(ISNUMBER(E33),ISNUMBER(E32)),LN(E33/E32),"") -> 0.011883872 | J33: =IF(ISNUMBER(B33),B33/B$7*100,J32) -> 98.103202 | K33: =IF(ISNUMBER(C33),C33/C$7*100,K32) -> 99.455041 | L33: =IF(ISNUMBER(D33),D33/D$7*100,L32) -> 97.941812 | M33: =IF(ISNUMBER(E33),E33/E$7*100,M32) -> 104.1108
A34: 46288 | B34: 4768 | C34: 3.67 | D34: 77.1 | E34: 4677 | F34: =IF(AND(ISNUMBER(B34),ISNUMBER(B33)),LN(B34/B33),"") -> -0.0087701544 | G34: =IF(AND(ISNUMBER(C34),ISNUMBER(C33)),LN(C34/C33),"") -> 0.0054644945 | H34: =IF(AND(ISNUMBER(D34),ISNUMBER(D33)),LN(D34/D33),"") -> 0.0001297101 | I34: =IF(AND(ISNUMBER(E34),ISNUMBER(E33)),LN(E34/E33),"") -> -0.0044800075 | J34: =IF(ISNUMBER(B34),B34/B$7*100,J33) -> 97.246584 | K34: =IF(ISNUMBER(C34),C34/C$7*100,K33) -> 100 | L34: =IF(ISNUMBER(D34),D34/D$7*100,L33) -> 97.954517 | M34: =IF(ISNUMBER(E34),E34/E$7*100,M33) -> 103.64543
A35: 46289 | B35: 4772 | C35: 3.65 | D35: 77.94 | E35: 4708.5 | F35: =IF(AND(ISNUMBER(B35),ISNUMBER(B34)),LN(B35/B34),"") -> 0.00083857447 | G35: =IF(AND(ISNUMBER(C35),ISNUMBER(C34)),LN(C35/C34),"") -> -0.0054644945 | H35: =IF(AND(ISNUMBER(D35),ISNUMBER(D34)),LN(D35/D34),"") -> 0.010836019 | I35: =IF(AND(ISNUMBER(E35),ISNUMBER(E34)),LN(E35/E34),"") -> 0.0067125072 | J35: =IF(ISNUMBER(B35),B35/B$7*100,J34) -> 97.328166 | K35: =IF(ISNUMBER(C35),C35/C$7*100,K34) -> 99.455041 | L35: =IF(ISNUMBER(D35),D35/D$7*100,L34) -> 99.021725 | M35: =IF(ISNUMBER(E35),E35/E$7*100,M34) -> 104.34349
A36: 46290 | B36: 4672 | C36: 3.68 | D36: 77.17 | E36: 4664.5 | F36: =IF(AND(ISNUMBER(B36),ISNUMBER(B35)),LN(B36/B35),"") -> -0.021178259 | G36: =IF(AND(ISNUMBER(C36),ISNUMBER(C35)),LN(C36/C35),"") -> 0.0081855846 | H36: =IF(AND(ISNUMBER(D36),ISNUMBER(D35)),LN(D36/D35),"") -> -0.0099285194 | I36: =IF(AND(ISNUMBER(E36),ISNUMBER(E35)),LN(E36/E35),"") -> -0.0093887385 | J36: =IF(ISNUMBER(B36),B36/B$7*100,J35) -> 95.288599 | K36: =IF(ISNUMBER(C36),C36/C$7*100,K35) -> 100.27248 | L36: =IF(ISNUMBER(D36),D36/D$7*100,L35) -> 98.043451 | M36: =IF(ISNUMBER(E36),E36/E$7*100,M35) -> 103.36842
A37: 46293 | B37: 4664 | C37: 3.61 | D37: 77 | E37: 4671 | F37: =IF(AND(ISNUMBER(B37),ISNUMBER(B36)),LN(B37/B36),"") -> -0.0017137965 | G37: =IF(AND(ISNUMBER(C37),ISNUMBER(C36)),LN(C37/C36),"") -> -0.01920498 | H37: =IF(AND(ISNUMBER(D37),ISNUMBER(D36)),LN(D37/D36),"") -> -0.0022053586 | I37: =IF(AND(ISNUMBER(E37),ISNUMBER(E36)),LN(E37/E36),"") -> 0.0013925341 | J37: =IF(ISNUMBER(B37),B37/B$7*100,J36) -> 95.125433 | K37: =IF(ISNUMBER(C37),C37/C$7*100,K36) -> 98.365123 | L37: =IF(ISNUMBER(D37),D37/D$7*100,L36) -> 97.827468 | M37: =IF(ISNUMBER(E37),E37/E$7*100,M36) -> 103.51247
A38: 46294 | B38: 4624 | C38: 3.58 | D38: 76.26 | E38: 4615.5 | F38: =IF(AND(ISNUMBER(B38),ISNUMBER(B37)),LN(B38/B37),"") -> -0.0086133177 | G38: =IF(AND(ISNUMBER(C38),ISNUMBER(C37)),LN(C38/C37),"") -> -0.0083449719 | H38: =IF(AND(ISNUMBER(D38),ISNUMBER(D37)),LN(D38/D37),"") -> -0.0096568674 | I38: =IF(AND(ISNUMBER(E38),ISNUMBER(E37)),LN(E38/E37),"") -> -0.011952977 | J38: =IF(ISNUMBER(B38),B38/B$7*100,J37) -> 94.309606 | K38: =IF(ISNUMBER(C38),C38/C$7*100,K37) -> 97.547684 | L38: =IF(ISNUMBER(D38),D38/D$7*100,L37) -> 96.887308 | M38: =IF(ISNUMBER(E38),E38/E$7*100,M37) -> 102.28255
A39: 46295 | B39: 4610 | C39: 3.61 | D39: 76.02 | E39: 4603.5 | F39: =IF(AND(ISNUMBER(B39),ISNUMBER(B38)),LN(B39/B38),"") -> -0.0030322744 | G39: =IF(AND(ISNUMBER(C39),ISNUMBER(C38)),LN(C39/C38),"") -> 0.0083449719 | H39: =IF(AND(ISNUMBER(D39),ISNUMBER(D38)),LN(D39/D38),"") -> -0.0031520909 | I39: =IF(AND(ISNUMBER(E39),ISNUMBER(E38)),LN(E39/E38),"") -> -0.0026033207 | J39: =IF(ISNUMBER(B39),B39/B$7*100,J38) -> 94.024067 | K39: =IF(ISNUMBER(C39),C39/C$7*100,K38) -> 98.365123 | L39: =IF(ISNUMBER(D39),D39/D$7*100,L38) -> 96.582391 | M39: =IF(ISNUMBER(E39),E39/E$7*100,M38) -> 102.01662
A40: 46296 | B40: 4554 | C40: 3.51 | D40: 74.63 | E40: 4494 | F40: =IF(AND(ISNUMBER(B40),ISNUMBER(B39)),LN(B40/B39),"") -> -0.012221889 | G40: =IF(AND(ISNUMBER(C40),ISNUMBER(C39)),LN(C40/C39),"") -> -0.028091735 | H40: =IF(AND(ISNUMBER(D40),ISNUMBER(D39)),LN(D40/D39),"") -> -0.018453892 | I40: =IF(AND(ISNUMBER(E40),ISNUMBER(E39)),LN(E40/E39),"") -> -0.02407371 | J40: =IF(ISNUMBER(B40),B40/B$7*100,J39) -> 92.881909 | K40: =IF(ISNUMBER(C40),C40/C$7*100,K39) -> 95.640327 | L40: =IF(ISNUMBER(D40),D40/D$7*100,L39) -> 94.816415 | M40: =IF(ISNUMBER(E40),E40/E$7*100,M39) -> 99.590028
A41: 46297 | B41: 4535 | C41: 3.47 | D41: 74.78 | E41: 4483.5 | F41: =IF(AND(ISNUMBER(B41),ISNUMBER(B40)),LN(B41/B40),"") -> -0.0041808841 | G41: =IF(AND(ISNUMBER(C41),ISNUMBER(C40)),LN(C41/C40),"") -> -0.011461444 | H41: =IF(AND(ISNUMBER(D41),ISNUMBER(D40)),LN(D41/D40),"") -> 0.0020078984 | I41: =IF(AND(ISNUMBER(E41),ISNUMBER(E40)),LN(E41/E40),"") -> -0.0023391824 | J41: =IF(ISNUMBER(B41),B41/B$7*100,J40) -> 92.494391 | K41: =IF(ISNUMBER(C41),C41/C$7*100,K40) -> 94.550409 | L41: =IF(ISNUMBER(D41),D41/D$7*100,L40) -> 95.006988 | M41: =IF(ISNUMBER(E41),E41/E$7*100,M40) -> 99.357341
... A46: 46304 | B46: 4592 | C46: 3.55 | D46: 76.04 | E46: 4673.5 | F46: =IF(AND(ISNUMBER(B46),ISNUMBER(B45)),LN(B46/B45),"") -> -0.014914358 | G46: =IF(AND(ISNUMBER(C46),ISNUMBER(C45)),LN(C46/C45),"") -> 0.0056497325 | H46: =IF(AND(ISNUMBER(D46),ISNUMBER(D45)),LN(D46/D45),"") -> 0.00052617733 | I46: =IF(AND(ISNUMBER(E46),ISNUMBER(E45)),LN(E46/E45),"") -> 0.010215692 | J46: =IF(ISNUMBER(B46),B46/B$7*100,J45) -> 93.656945 | K46: =IF(ISNUMBER(C46),C46/C$7*100,K45) -> 96.730245 | L46: =IF(ISNUMBER(D46),D46/D$7*100,L45) -> 96.607801 | M46: =IF(ISNUMBER(E46),E46/E$7*100,M45) -> 103.56787
A47: 46307 | B47: 4637 | E47: 4738 | F47: =IF(AND(ISNUMBER(B47),ISNUMBER(B46)),LN(B47/B46),"") -> 0.0097519464 | G47: =IF(AND(ISNUMBER(C47),ISNUMBER(C46)),LN(C47/C46),"") | H47: =IF(AND(ISNUMBER(D47),ISNUMBER(D46)),LN(D47/D46),"") | I47: =IF(AND(ISNUMBER(E47),ISNUMBER(E46)),LN(E47/E46),"") -> 0.01370685 | J47: =IF(ISNUMBER(B47),B47/B$7*100,J46) -> 94.57475 | K47: =IF(ISNUMBER(C47),C47/C$7*100,K46) -> 96.730245 | L47: =IF(ISNUMBER(D47),D47/D$7*100,L46) -> 96.607801 | M47: =IF(ISNUMBER(E47),E47/E$7*100,M46) -> 104.99723
A48: 46308 | B48: 4682 | E48: 4710.5 | F48: =IF(AND(ISNUMBER(B48),ISNUMBER(B47)),LN(B48/B47),"") -> 0.0096577637 | G48: =IF(AND(ISNUMBER(C48),ISNUMBER(C47)),LN(C48/C47),"") | H48: =IF(AND(ISNUMBER(D48),ISNUMBER(D47)),LN(D48/D47),"") | I48: =IF(AND(ISNUMBER(E48),ISNUMBER(E47)),LN(E48/E47),"") -> -0.0058210462 | J48: =IF(ISNUMBER(B48),B48/B$7*100,J47) -> 95.492556 | K48: =IF(ISNUMBER(C48),C48/C$7*100,K47) -> 96.730245 | L48: =IF(ISNUMBER(D48),D48/D$7*100,L47) -> 96.607801 | M48: =IF(ISNUMBER(E48),E48/E$7*100,M47) -> 104.38781
A49: 46309 | B49: 4700 | E49: 4829 | F49: =IF(AND(ISNUMBER(B49),ISNUMBER(B48)),LN(B49/B48),"") -> 0.0038371396 | G49: =IF(AND(ISNUMBER(C49),ISNUMBER(C48)),LN(C49/C48),"") | H49: =IF(AND(ISNUMBER(D49),ISNUMBER(D48)),LN(D49/D48),"") | I49: =IF(AND(ISNUMBER(E49),ISNUMBER(E48)),LN(E49/E48),"") -> 0.024845347 | J49: =IF(ISNUMBER(B49),B49/B$7*100,J48) -> 95.859678 | K49: =IF(ISNUMBER(C49),C49/C$7*100,K48) -> 96.730245 | L49: =IF(ISNUMBER(D49),D49/D$7*100,L48) -> 96.607801 | M49: =IF(ISNUMBER(E49),E49/E$7*100,M48) -> 107.01385
A50: 46310 | B50: 4666 | F50: =IF(AND(ISNUMBER(B50),ISNUMBER(B49)),LN(B50/B49),"") -> -0.0072603351 | G50: =IF(AND(ISNUMBER(C50),ISNUMBER(C49)),LN(C50/C49),"") | H50: =IF(AND(ISNUMBER(D50),ISNUMBER(D49)),LN(D50/D49),"") | I50: =IF(AND(ISNUMBER(E50),ISNUMBER(E49)),LN(E50/E49),"") | J50: =IF(ISNUMBER(B50),B50/B$7*100,J49) -> 95.166225 | K50: =IF(ISNUMBER(C50),C50/C$7*100,K49) -> 96.730245 | L50: =IF(ISNUMBER(D50),D50/D$7*100,L49) -> 96.607801 | M50: =IF(ISNUMBER(E50),E50/E$7*100,M49) -> 107.01385

Sheet Next_Steps
A1: Next steps — data to pull and checks to run
A2: Confirm every field mnemonic with FLDS <GO> before relying on it; syntax below is the standard Excel add-in form.
A4: Task | B4: Bloomberg route | C4: Why / feeds which RQ
A5: Daily prices, 5–10 years: WIL SP, NESN SW, ULVR LN, palm oil continuous | B5: Excel add-in: =BDH("WIL SP Equity","PX_LAST","10/15/2021","10/15/2026","Dir=V","Days=A") — repeat per ticker; palm oil: generic first-month KO1 Comdty (confirm) | C5: RQ2: volatility, correlation, beta with n in the thousands; event studies
A6: Event study around 28-May-2026 (Indonesia export probe) and 03-Mar-2026 (bribery sentence) | B6: Daily returns of WIL SP vs STI Index; abnormal return = actual − beta × market; cumulative over [-1,+5] days | C6: Calibrates rev_loss / p_reg with an observed event instead of a guess
A7: Full SPLC supplier / customer lists; search for Wilmar, IOI, Musim Mas, AAK, Cargill, Sime Darby Plantation | B7: SPLC <GO> → Suppliers/Customers → export; use the Export button to Excel | C7: RQ1: tests the 'mill → trader → brand owner' chain
A8: Same-query news screen for all firms | B8: CN <GO>: company AND (palm oil OR deforestation OR supply chain) with ESG/controversy tags; export counts by month | C8: Makes the news indicator comparable
A9: Scope 3 and certification coverage (% RSPO / % traceable to mill) | B9: ESG <GO> tabs + company sustainability reports (Unilever, Nestlé, Wilmar) | C9: Replace assumed c0 and ps with disclosed values
A10: FX and WACC | B10: EURUSD Curncy, USDCHF Curncy; WACC <GO> | C10: Replace illustrative FX and the 8% discount rate
A11: Extend the peer set to 10–15 firms | B11: Add IOI, Musim Mas (if covered), AAK, Cargill (private; use disclosures), P&G, Mondelez, Colgate, Sime Darby Plantation | C11: Gives the risk index and any regression real degrees of freedom
A12: Spot-check transcription | B12: Re-read ~10 numbers per sheet against the Terminal (revenue, BESG, Scope 3, SPLC counts, 10 prices) | C12: These values were typed from screenshots
A14: Source used in this review
A15: European Commission, Access2Markets: 'Delay until December 2026 and other developments in the implementation of the EUDR Regulation'
A16: https://trade.ec.europa.eu/access-to-markets/en/news/delay-until-december-2026-and-other-developments-implementation-eudr-regulation
